Workbook

Sheet Quotation Final
H2: Quotation
B3: Address - Corporate HQ : Axestrack Software Solutions Pvt. Ltd., Office No.-19, 6th Floor, Jaipur Electronic Market, Near Riddhi Siddhi, Gopalpura bypass, Jaipur - 302018 , Rajasthan, India
B4: GSTIN | C4: 08AACCH0299P1Z1 | E4: QUOTE # | H4: DATE
B5: MSME No | C5: UDYAM-RJ-17-0051921 | E5: DC/KS/261203 | H5: =TODAY() -> 46127
B6: Contact | C6: Kishor Sharma | E6: Quote Validity : 15 days from submitted date | H6: Payment Terms : Monthly
B7: Phone | C7: +91 7073330772
B8: Email Id | C8: kishor.sharma@axestrack.com
B10: CUSTOMER INFO
B11: Name
B12: Location
B13: Contact | E13: Phone
B14: Email Id
B16: DESCRIPTION OF WORK
B17: Commercials for the proposed solution aiming to digitize the inbound movement of Trucks with E-sealing to enhance efficiency, optimize pilferages & leakages, enhance transparency, and coordination of Trucks with enterprise.
B18: S.No. | C18: Description | E18: Type | F18: Per Trip Price | H18: Remark
B19: Ostwal's Plant Wise (With Platform Capabilities, Barcoded Eseal, Manpower & Reverse Logitics) • Tracking and Functionalities Applied as OOTB • Optimize pilferages & leakages, enhance transparency
B20: 1 | C20: KPL Meghnagar MP | E20: Per trip | F20: ='KPL Meghnagar MP'!H14 -> 357.95457 | H20: Charges are Per Vehicle per Trip Inclusions: • Device mapping/E sealing with the trip. • Reports/route replay • Manpower at the loading and unloading location. • Reverse Logistics of the device back to the loading location. • Real-time alerts
B21: 2 | C21: MBAPL-Saugor(MP) | E21: Per trip | F21: ='MBAPL-Saugor(MP)'!H14 -> 398.41911
B22: 3 | C22: MBAPL-Dhule (MH) | E22: Per trip | F22: ='MBAPL-Dhule (MH)'!H14 -> 481.17333
B23: 4 | C23: OPIL Rajasthan BHL | E23: Per trip | F23: ='OPIL Rajasthan BHL'!H14 -> 688.60791
B24: 5 | C24: SGFL Kapasan Rajasthan | E24: Per trip | F24: ='SGFL Kapasan Rajasthan'!H14 -> 795.76762
B25: 6 | C25: Imported Fertilizers (Kandla) | E25: Per trip | F25: ='Imported Fertilizers (Kandla)'!H14 -> 476.45333
B26: Ostwal's Plant Wise (With Platform Capabilities, Barcoded Eseal only, NO AXESTRACK'S MANPOWER ) • Tracking and Functionalities Applied as OOTB
B27: 1 | C27: KPL Meghnagar MP | E27: Per trip | F27: ='KPL Meghnagar MP'!H33 -> 161.38049 | H27: Charges are Per Vehicle per Trip Inclusions: • Reports/route replay • Real-time alerts Exclusions: • Manpower at Loading & Unloading Site, Reverse logistics of Devices (Device Ownership will be of Axestrack)
B28: 2 | C28: MBAPL-Saugor(MP) | E28: Per trip | F28: ='MBAPL-Saugor(MP)'!H33 -> 164.07126
B29: 3 | C29: MBAPL-Dhule (MH) | E29: Per trip | F29: ='MBAPL-Dhule (MH)'!H33 -> 171.45333
B30: 4 | C30: OPIL Rajasthan BHL | E30: Per trip | F30: ='OPIL Rajasthan BHL'!H33 -> 215.52531
B31: 5 | C31: SGFL Kapasan Rajasthan | E31: Per trip | F31: ='SGFL Kapasan Rajasthan'!H33 -> 228.26762
B32: 6 | C32: Imported Fertilizers (Kandla) | E32: Per trip | F32: ='Imported Fertilizers (Kandla)'!H33 -> 175.55333
B33: Please refer to the next page for Terms and Conditions & Notes
B35: Terms & Conditions
B36: • All the prices mentioned in proposal are in rupees and exclusive of GST. Taxes as applicable • Device ownership remains with Axestrack • Trips are estimated based on received details; any formal change or upgrade in hardware specifications or features (beyond those installed during onboarding) will incur additional charges. • In the event of device loss, tampering, or theft, a charge of INR 1200 plus GST (per device) will be applied • The pricing has been estimated on the following loading and unloading location. Any change in locations will leads to revision of pricing. Loading: Dahej, Hazira, Kandla, Meghnagar, Chhatarpur, RockRaj, Nayara (Gujarat), RIL (Gujarat), HPCL Bhatinda, Sulphur (Uttar Pradesh), and Bina. Unloading: KPL Meghnagar (MP), MBAPL Saugor (MP), MBAPL Dhule (MH), OPIL Rajasthan (BHL), SGFL Kapasan (Rajasthan), and Imported Fertilizers (Kandla). • The pricing has been estimated on the below trip count. Any change in actucal count will leads to revision of pricing. • Billing will be done on a monthly basis based on actual trip count. • If the trip count is less than the minimum trip count mentioned above, then the billing will be done on minimum number of trip as per the above details. Hardware Included in Per Trip Cost : - Plug & play GPS devices - Seals : 20 seals per truck per trip Payment Terms: • 100% payments to be made within 15 days from the date of receipt of original or digitally signed invoice. In case of delay, overdue charges of 1.5% per month will be charged. Project Closure : • All devices must be returned to Axestrack within 15 days of receiving the project closure notification. • Unretured devices will be charged at INR 1200 plus GST (per device).
B37: Thanks for business with Axestrack Software Solution Pvt. Ltd.

Sheet Client Data
C2: Truck/ Tanker | D2: KPL Meghnagar MP | E2: MBAPL-Saugor(MP) | F2: MBAPL-Dhule (MH) | G2: OPIL Rajasthan BHL | H2: SGFL Kapasan Rajasthan | I2: Imported Fertilizers (Kandla) | J2: TOTAL | K2: NO OF TRIP
B3: Rock Dahej/hazira/kandla | C3: Truck | D3: 400000 | E3: =124200+41400+139650+41400 -> 346650 | F3: 200000 | I3: 200000 | J3: =SUM(D3:I3) -> 1146650 | K3: =J3/40 -> 28666.25
B4: Rock meghnagar local MP | C4: Truck-dedicated | D4: 150000 | J4: =SUM(D4:I4) -> 150000 | K4: =J4/40 -> 3750
B5: Rock ChattarPur MP (70 kM) | C5: Truck-dedicated | E5: 40000 | J5: =SUM(D5:I5) -> 40000 | K5: =J5/40 -> 1000
B6: Rock Raj | D6: 3000 | G6: 67800 | H6: 56000 | J6: =SUM(D6:I6) -> 126800 | K6: =J6/40 -> 3170
B7: TOTAL | D7: =SUM(D3:D6) -> 553000 | E7: =SUM(E3:E6) -> 386650 | F7: =SUM(F3:F6) -> 200000 | G7: =SUM(G3:G6) -> 67800 | H7: =SUM(H3:H6) -> 56000 | I7: =SUM(I3:I6) -> 200000 | J7: =SUM(D7:I7) -> 1463450 | K7: =J7/40 -> 36586.25
J8: =SUM(D8:I8) -> 0
B9: Sulphur Indiginious gujarat Nayra/RIL | C9: Truck | D9: 60000 | E9: 30000 | F9: 50000 | J9: =SUM(D9:I9) -> 140000 | K9: =J9/40 -> 3500
B10: bhatinda HPCL | C10: Truck | D10: 30000 | J10: =SUM(D10:I10) -> 30000 | K10: =J10/40 -> 750
B11: sulphur UP | C11: Truck | E11: 20000 | J11: =SUM(D11:I11) -> 20000 | K11: =J11/40 -> 500
B12: BINA | C12: Truck | D12: 5000 | E12: 18000 | J12: =SUM(D12:I12) -> 23000 | K12: =J12/40 -> 575
B13: TOTAL | D13: =SUM(D9:D12) -> 95000 | E13: =SUM(E9:E12) -> 68000 | F13: =SUM(F9:F12) -> 50000 | K13: =SUM(K9:K12) -> 5325
C15: Nature | D15: Location
C16: Loading | D16: Hazira
C17: Loading | D17: Kandla
C18: Loading | D18: Dahej
C19: Loading | D19: Jamnagar
C20: Unloading | D20: Sagar
C21: Unloading | D21: hamirgarh
C22: Unloading | D22: kapasan
C23: Unloading | D23: meghnagar

Sheet Ops Estimations- Ashish
A1: Loading location | B1: Trips per day | C1: Manpower Count | D1: Unloading location | E1: Trips per day Count | F1: Manpower
A2: Dahej | B2: 27 | C2: 3 | D2: KPL Meghnagar MP | E2: 52 | F2: 3
A3: Hazira | B3: 27 | C3: 3 | D3: MBAPL-Saugor(MP) | E3: 36 | F3: 3
A4: Kandla | B4: 27 | C4: 3 | D4: MBAPL-Dhule (MH) | E4: 21 | F4: 3
A5: Meghnagar | B5: 10 | C5: 2 | D5: OPIL Rajasthan BHL | E5: 5 | F5: 1
A6: Chhatarpur | B6: 3 | C6: 1 | D6: SGFL Kapasan Rajasthan | E6: 4 | F6: 1
A7: RockRaj | B7: 9 | C7: 2 | D7: Imported Fertilizers (Kandla) | E7: 14 | F7: 2
A8: Nayra GJ | B8: 5 | C8: 1
A9: RIL GJ | B9: 5 | C9: 1
A10: HPCL Bhatinda | B10: 2 | C10: 1
A11: Sulphur Up | B11: 1 | C11: 1
A12: Bina | B12: 2 | C12: 1
A13: Total | B13: 118 | C13: 19 | E13: 131 | F13: 13
A15: RL | B15: 3
A16: Ops | B16: 3
A17: TL | B17: 1

Sheet Trips data
D1: Yearly MT | J1: Daily Trips | Q1: Monthly Trips
D2: KPL Meghnagar MP | E2: MBAPL-Saugor(MP) | F2: MBAPL-Dhule (MH) | G2: OPIL Rajasthan BHL | H2: SGFL Kapasan Rajasthan | I2: Imported Fertilizers (Kandla) | J2: KPL Meghnagar MP | K2: MBAPL-Saugor(MP) | L2: MBAPL-Dhule (MH) | M2: OPIL Rajasthan BHL | N2: SGFL Kapasan Rajasthan | O2: Imported Fertilizers (Kandla) | Q2: KPL Meghnagar MP | R2: MBAPL-Saugor(MP) | S2: MBAPL-Dhule (MH) | T2: OPIL Rajasthan BHL | U2: SGFL Kapasan Rajasthan | V2: Imported Fertilizers (Kandla)
C3: Manpower | Q3: 3 | R3: 3 | S3: 3 | T3: 1 | U3: 1 | V3: 2 | W3: =SUM(Q3:V3) -> 13
A4: Rock | B4: Dahej | C4: 3 | D4: 133333.33 | E4: 115550 | F4: 66666.667 | I4: 66666.667 | J4: =D4/12/30/40 -> 9.2592593 | K4: =E4/12/30/40 -> 8.0243056 | L4: =F4/12/30/40 -> 4.6296296 | M4: =G4/12/30/40 -> 0 | N4: =H4/12/30/40 -> 0 | O4: =I4/12/30/40 -> 4.6296296 | P4: =C4/4 -> 0.75 | Q4: =D4/12/40 -> 277.77778 | R4: =E4/12/40 -> 240.72917 | S4: =F4/12/40 -> 138.88889 | T4: =G4/12/40 -> 0 | U4: =H4/12/40 -> 0 | V4: =I4/12/40 -> 138.88889
B5: Hazira | C5: 3 | D5: 133333.33 | E5: 115550 | F5: 66666.667 | I5: 66666.667 | J5: =D5/12/30/40 -> 9.2592593 | K5: =E5/12/30/40 -> 8.0243056 | L5: =F5/12/30/40 -> 4.6296296 | M5: =G5/12/30/40 -> 0 | N5: =H5/12/30/40 -> 0 | O5: =I5/12/30/40 -> 4.6296296 | P5: =C5/4 -> 0.75 | Q5: =D5/12/40 -> 277.77778 | R5: =E5/12/40 -> 240.72917 | S5: =F5/12/40 -> 138.88889 | T5: =G5/12/40 -> 0 | U5: =H5/12/40 -> 0 | V5: =I5/12/40 -> 138.88889
B6: Kandla | C6: 3 | D6: 133333.33 | E6: 115550 | F6: 66666.667 | I6: 66666.667 | J6: =D6/12/30/40 -> 9.2592593 | K6: =E6/12/30/40 -> 8.0243056 | L6: =F6/12/30/40 -> 4.6296296 | M6: =G6/12/30/40 -> 0 | N6: =H6/12/30/40 -> 0 | O6: =I6/12/30/40 -> 4.6296296 | P6: =C6/4 -> 0.75 | Q6: =D6/12/40 -> 277.77778 | R6: =E6/12/40 -> 240.72917 | S6: =F6/12/40 -> 138.88889 | T6: =G6/12/40 -> 0 | U6: =H6/12/40 -> 0 | V6: =I6/12/40 -> 138.88889
A7: Meghnagar | C7: 2 | D7: 150000 | J7: =D7/12/30/40 -> 10.416667 | K7: =E7/12/30/40 -> 0 | L7: =F7/12/30/40 -> 0 | M7: =G7/12/30/40 -> 0 | N7: =H7/12/30/40 -> 0 | O7: =I7/12/30/40 -> 0 | P7: =C7/1 -> 2 | Q7: =D7/12/40 -> 312.5 | R7: =E7/12/40 -> 0 | S7: =F7/12/40 -> 0 | T7: =G7/12/40 -> 0 | U7: =H7/12/40 -> 0 | V7: =I7/12/40 -> 0
A8: Chhatarpur | C8: 1 | E8: 40000 | J8: =D8/12/30/40 -> 0 | K8: =E8/12/30/40 -> 2.7777778 | L8: =F8/12/30/40 -> 0 | M8: =G8/12/30/40 -> 0 | N8: =H8/12/30/40 -> 0 | O8: =I8/12/30/40 -> 0 | P8: =C8/1 -> 1 | Q8: =D8/12/40 -> 0 | R8: =E8/12/40 -> 83.333333 | S8: =F8/12/40 -> 0 | T8: =G8/12/40 -> 0 | U8: =H8/12/40 -> 0 | V8: =I8/12/40 -> 0
A9: Rock Raj | C9: 2 | D9: 3000 | G9: 67800 | H9: 56000 | J9: =D9/12/30/40 -> 0.20833333 | K9: =E9/12/30/40 -> 0 | L9: =F9/12/30/40 -> 0 | M9: =G9/12/30/40 -> 4.7083333 | N9: =H9/12/30/40 -> 3.8888889 | O9: =I9/12/30/40 -> 0 | P9: =C9/3 -> 0.66666667 | Q9: =D9/12/40 -> 6.25 | R9: =E9/12/40 -> 0 | S9: =F9/12/40 -> 0 | T9: =G9/12/40 -> 141.25 | U9: =H9/12/40 -> 116.66667 | V9: =I9/12/40 -> 0
A10: Sulphur Indiginious gujarat | B10: Nayra | C10: 1 | D10: 30000 | E10: 15000 | F10: 25000 | J10: =D10/12/30/40 -> 2.0833333 | K10: =E10/12/30/40 -> 1.0416667 | L10: =F10/12/30/40 -> 1.7361111 | M10: =G10/12/30/40 -> 0 | N10: =H10/12/30/40 -> 0 | O10: =I10/12/30/40 -> 0 | P10: =C10/3 -> 0.33333333 | Q10: =D10/12/40 -> 62.5 | R10: =E10/12/40 -> 31.25 | S10: =F10/12/40 -> 52.083333 | T10: =G10/12/40 -> 0 | U10: =H10/12/40 -> 0 | V10: =I10/12/40 -> 0
B11: RIL | C11: 1 | D11: 30000 | E11: 15000 | F11: 25000 | J11: =D11/12/30/40 -> 2.0833333 | K11: =E11/12/30/40 -> 1.0416667 | L11: =F11/12/30/40 -> 1.7361111 | M11: =G11/12/30/40 -> 0 | N11: =H11/12/30/40 -> 0 | O11: =I11/12/30/40 -> 0 | P11: =C11/3 -> 0.33333333 | Q11: =D11/12/40 -> 62.5 | R11: =E11/12/40 -> 31.25 | S11: =F11/12/40 -> 52.083333 | T11: =G11/12/40 -> 0 | U11: =H11/12/40 -> 0 | V11: =I11/12/40 -> 0
A12: bhatinda HPCL | C12: 1 | D12: 30000 | J12: =D12/12/30/40 -> 2.0833333 | K12: =E12/12/30/40 -> 0 | L12: =F12/12/30/40 -> 0 | M12: =G12/12/30/40 -> 0 | N12: =H12/12/30/40 -> 0 | O12: =I12/12/30/40 -> 0 | P12: =C12/1 -> 1 | Q12: =D12/12/40 -> 62.5 | R12: =E12/12/40 -> 0 | S12: =F12/12/40 -> 0 | T12: =G12/12/40 -> 0 | U12: =H12/12/40 -> 0 | V12: =I12/12/40 -> 0
A13: sulphur UP | C13: 1 | E13: 20000 | J13: =D13/12/30/40 -> 0 | K13: =E13/12/30/40 -> 1.3888889 | L13: =F13/12/30/40 -> 0 | M13: =G13/12/30/40 -> 0 | N13: =H13/12/30/40 -> 0 | O13: =I13/12/30/40 -> 0 | P13: =C13/1 -> 1 | Q13: =D13/12/40 -> 0 | R13: =E13/12/40 -> 41.666667 | S13: =F13/12/40 -> 0 | T13: =G13/12/40 -> 0 | U13: =H13/12/40 -> 0 | V13: =I13/12/40 -> 0
A14: BINA | C14: 1 | D14: 5000 | E14: 18000 | J14: =D14/12/30/40 -> 0.34722222 | K14: =E14/12/30/40 -> 1.25 | L14: =F14/12/30/40 -> 0 | M14: =G14/12/30/40 -> 0 | N14: =H14/12/30/40 -> 0 | O14: =I14/12/30/40 -> 0 | P14: =C14/2 -> 0.5 | Q14: =D14/12/40 -> 10.416667 | R14: =E14/12/40 -> 37.5 | S14: =F14/12/40 -> 0 | T14: =G14/12/40 -> 0 | U14: =H14/12/40 -> 0 | V14: =I14/12/40 -> 0
C15: =SUM(C4:C14) -> 19 | D15: =SUM(D4:D14) -> 648000 | E15: =SUM(E4:E14) -> 454650 | F15: =SUM(F4:F14) -> 250000 | G15: =SUM(G4:G14) -> 67800 | H15: =SUM(H4:H14) -> 56000 | I15: =SUM(I4:I14) -> 200000 | J15: =SUM(J4:J14) -> 45 | ... O15: =SUM(O4:O14) -> 13.888889 | Q15: =SUM(Q4:Q14) -> 1350 | R15: =SUM(R4:R14) -> 947.1875 | S15: =SUM(S4:S14) -> 520.83333 | T15: =SUM(T4:T14) -> 141.25 | U15: =SUM(U4:U14) -> 116.66667 | V15: =SUM(V4:V14) -> 416.66667
O16: =SUM(J15:O15) -> 116.42014 | V16: =SUM(Q15:V15) -> 3492.6042

Sheet Field manpower per plant
A1: KPL Meghnagar MP | D1: MBAPL-Saugor(MP) | G1: MBAPL-Dhule (MH)
A2: Total monthly trips | B2: ='Trips data'!Q15 -> 1350 | D2: Total monthly trips | E2: ='Trips data'!R15 -> 947.1875 | G2: Total monthly trips | H2: ='Trips data'!S15 -> 520.83333
A3: Manpower at Unloading | B3: ='Trips data'!Q3 -> 3 | D3: Manpower at Unloading | E3: ='Trips data'!R3 -> 3 | G3: Manpower at Unloading | H3: ='Trips data'!S3 -> 3
A4: Manpower at loading | B4: ='Trips data'!P4+'Trips data'!P5+'Trips data'!P6+'Trips data'!P7+'Trips data'!P9+'Trips data'!P10+'Trips data'!P11+'Trips data'!P12+'Trips data'!P14 -> 7.0833333 | D4: Manpower at loading | E4: ='Trips data'!P4+'Trips data'!P5+'Trips data'!P6+'Trips data'!P8+'Trips data'!P10+'Trips data'!P11+'Trips data'!P13+'Trips data'!P14 -> 5.4166667 | G4: Manpower at loading | H4: ='Trips data'!P4+'Trips data'!P5+'Trips data'!P6+'Trips data'!P10+'Trips data'!P11 -> 2.9166667
A5: Per head Cost | B5: 20000 | D5: Per head Cost | E5: 20000 | G5: Per head Cost | H5: 20000
A6: Manpower cost | B6: =(B5+B4)*B3 -> 60021.25 | D6: Manpower cost | E6: =(E5+E4)*E3 -> 60016.25 | G6: Manpower cost | H6: =(H5+H4)*H3 -> 60008.75
A7: manpower Per trip | B7: =B6/B2 -> 44.460185 | D7: manpower Per trip | E7: =E6/E2 -> 63.362587 | G7: manpower Per trip | H7: =H6/H2 -> 115.2168
A8: Seals | B8: 20 | D8: Seals | E8: 20 | G8: Seals | H8: 20
A9: Per Seal Cost+ Acceseries | B9: 2.5 | D9: Per Seal Cost+ Acceseries | E9: 2.5 | G9: Per Seal Cost+ Acceseries | H9: 2.5
A10: Seal Cost Per trip | B10: =B8*B9 -> 50 | D10: Seal Cost Per trip | E10: =E8*E9 -> 50 | G10: Seal Cost Per trip | H10: =H8*H9 -> 50
A12: OPIL Rajasthan BHL | D12: SGFL Kapasan Rajasthan | G12: Imported Fertilizers (Kandla)
A13: Total monthly trips | B13: ='Trips data'!T15 -> 141.25 | D13: Total monthly trips | E13: ='Trips data'!U15 -> 116.66667 | G13: Total monthly trips | H13: ='Trips data'!V15 -> 416.66667
A14: Manpower at Unloading | B14: ='Trips data'!T3 -> 1 | D14: Manpower at Unloading | E14: ='Trips data'!U3 -> 1 | G14: Manpower at Unloading | H14: ='Trips data'!V3 -> 2
A15: Manpower at loading | B15: ='Trips data'!P9 -> 0.66666667 | D15: Manpower at loading | E15: ='Trips data'!P9 -> 0.66666667 | G15: Manpower at loading | H15: ='Trips data'!P4+'Trips data'!P5+'Trips data'!P6 -> 2.25
A16: Per head Cost | B16: 20000 | D16: Per head Cost | E16: 20000 | G16: Per head Cost | H16: 20000
A17: Manpower cost | B17: =(B16+B15)*B14 -> 20000.667 | D17: Manpower cost | E17: =(E16+E15)*E14 -> 20000.667 | G17: Manpower cost | H17: =(H16+H15)*H14 -> 40004.5
A18: manpower Per trip | B18: =B17/B13 -> 141.59764 | D18: manpower Per trip | E18: =E17/E13 -> 171.43429 | G18: manpower Per trip | H18: =H17/H13 -> 96.0108
A19: Seals | B19: 20 | D19: Seals | E19: 20 | G19: Seals | H19: 20
A20: Per Seal Cost+ Acceseries | B20: 2.5 | D20: Per Seal Cost+ Acceseries | E20: 2.5 | G20: Per Seal Cost+ Acceseries | H20: 2.5
A21: Seal Cost Per trip | B21: =B19*B20 -> 50 | D21: Seal Cost Per trip | E21: =E19*E20 -> 50 | G21: Seal Cost Per trip | H21: =H19*H20 -> 50
A23: Control Tower
B24: Total | C24: Per Plant
A25: RL / RL Executives | B25: 3 | C25: =B25/6 -> 0.5
A26: Ops / Control Tower Executives | B26: 3 | C26: =B26/6 -> 0.5
A27: TL / Project Manager | B27: 1 | C27: =B27/6 -> 0.16666667
A28: Customer Success | B28: 1 | C28: =B28/6 -> 0.16666667

Sheet KPL Meghnagar MP
C2: Standard Model (Per Trip RL) - KPL Meghnagar MP - with Manpower & RL
C3: Inputs | G3: Per Trip Costings | K3: Commercial Values
C4: Trips Per Month | D4: ='Field manpower per plant'!B2 -> 1350 | G4: Capital | H4: =D15*E15/D4 -> 15.707654 | I4: =H4/$H$14 -> 0.043881698 | K4: Duration (Months) | L4: 1
C5: Device Rotation Days | D5: 8 | G5: Interest | H5: =D15*E16/D4 -> 3.9269136 | I5: =H5/$H$14 -> 0.010970425 | K5: Monthly CV | L5: =D4*(H14-H10) -> 469738.67
C6: Trips/Device/Month | D6: =30/D5 -> 3.75 | G6: Manpower | H6: =D16/D4 -> 176.66667 | I6: =H6/$H$14 -> 0.49354494 | K6: Annual CV | L6: =L5*12 -> 5636864
C7: Buffer Inventory | D7: 0.15 | F7: 38 | G7: SIM | H7: =D8*F7/D4 -> 11.653333 | I7: =H7/$H$14 -> 0.032555342 | K7: TCV | L7: =L5*L4 -> 469738.67
C8: Device Quantity | D8: =D4/D6*(1+D7) -> 414 | E8: 1200 | G8: Server+License | H8: 5 | I8: =H8/$H$14 -> 0.013968253
B9: Loading + Unloading | C9: Field Technicians | D9: ='Field manpower per plant'!B3+'Field manpower per plant'!B4 -> 10.083333 | E9: 20000 | G9: Consumables | H9: ='Field manpower per plant'!B10 -> 50 | I9: =H9/$H$14 -> 0.13968253
C10: RL Executives | D10: ='Field manpower per plant'!C25 -> 0.5 | E10: 22000 | G10: Penalties | H10: 10 | I10: =H10/$H$14 -> 0.027936506
C11: Control Tower Executives | D11: ='Field manpower per plant'!C26 -> 0.5 | E11: 25000 | G11: RL Courier Exp | H11: 25 | I11: =H11/$H$14 -> 0.069841265
C12: Project Manager OPS | D12: ='Field manpower per plant'!C27 -> 0.16666667 | E12: 30000 | G12: Man Cost at Loading point/trip | H12: 0 | I12: =H12/$H$14 -> 0
C13: Customer Success | D13: ='Field manpower per plant'!C28 -> 0.16666667 | E13: 50000 | G13: Net Margin | H13: 60 | I13: =H13/$H$14 -> 0.16761904
C14: Laptops | D14: =SUM(D10:D13) -> 1.3333333 | E14: 25000 | G14: Net Quote | H14: =SUM(H4:H13) -> 357.95457 | I14: =H14/$H$14 -> 1
C15: Total Capital (Assets) | D15: =D8*E8+D14*E14 -> 530133.33 | E15: 0.04 | F15: Dep | G15: Net Margin | H15: =H13*D4 -> 81000
C16: Monthly Manpower | D16: =SUMPRODUCT(D9:D13,E9:E13) -> 238500 | E16: 0.01 | F16: Int | G16: Cash Gen (Ops) | H16: =(H12+H13)*D4 -> 81000
G17: Months Capital Offset | H17: =D15/(H16+H4*D4) -> 5.1869439
C21: Standard Model (Per Trip RL) - KPL Meghnagar MP - without Manpower & RL
C22: Inputs | G22: Per Trip Costings | K22: Commercial Values
C23: Trips Per Month | D23: =D4 -> 1350 | G23: Capital | H23: =D34*E34/D23 -> 14.843457 | I23: =H23/$H$14 -> 0.041467432 | K23: Duration (Months) | L23: 1
C24: Device Rotation Days | D24: 8 | G24: Interest | H24: =D34*E35/D23 -> 3.7108642 | I24: =H24/$H$14 -> 0.010366858 | K24: Monthly CV | L24: =D23*(H33-H29) -> 204363.67
C25: Trips/Device/Month | D25: =30/D24 -> 3.75 | G25: Manpower | H25: =D35/D23 -> 6.1728395 | I25: =H25/$H$14 -> 0.017244757 | K25: Annual CV | L25: =L24*12 -> 2452364
C26: Buffer Inventory | D26: 0.15 | F26: 38 | G26: SIM | H26: =D27*F26/D23 -> 11.653333 | I26: =H26/$H$14 -> 0.032555342 | K26: TCV | L26: =L24*L23 -> 204363.67
C27: Device Quantity | D27: =D23/D25*(1+D26) -> 414 | E27: 1200 | G27: Server+License | H27: 5 | I27: =H27/$H$14 -> 0.013968253
B28: Loading + Unloading | C28: Field Technicians | D28: 0 | E28: 20000 | G28: Consumables | H28: =H9 -> 50 | I28: =H28/$H$14 -> 0.13968253
C29: RL Executives | D29: 0 | E29: 22000 | G29: Penalties | H29: 10 | I29: =H29/$H$14 -> 0.027936506
C30: Control Tower Executives | D30: 0 | E30: 25000 | G30: RL Courier Exp | H30: 0 | I30: =H30/$H$14 -> 0
C31: Project Manager OPS | D31: - | E31: 30000 | G31: Man Cost at Loading point/trip | H31: 0 | I31: =H31/$H$14 -> 0
C32: Customer Success | D32: =D13 -> 0.16666667 | E32: 50000 | G32: Net Margin | H32: 60 | I32: =H32/$H$14 -> 0.16761904
C33: Laptops | D33: =SUM(D29:D32) -> 0.16666667 | E33: 25000 | G33: Net Quote | H33: =SUM(H23:H32) -> 161.38049 | I33: =H33/$H$14 -> 0.45084072
C34: Total Capital (Assets) | D34: =D27*E27+D33*E33 -> 500966.67 | E34: 0.04 | F34: Dep | G34: Net Margin | H34: =H32*D23 -> 81000
C35: Monthly Manpower | D35: =SUMPRODUCT(D28:D32,E28:E32) -> 8333.3333 | E35: 0.01 | F35: Int | G35: Cash Gen (Ops) | H35: =(H31+H32)*D23 -> 81000
G36: Months Capital Offset | H36: =D34/(H35+H23*D23) -> 4.9581678

Sheet MBAPL-Saugor(MP)
C2: Standard Model (Per Trip RL) - MBAPL-Saugor(MP) - with Manpower & RL
C3: Inputs | G3: Per Trip Costings | K3: Commercial Values
C4: Trips Per Month | D4: ='Field manpower per plant'!E2 -> 947.1875 | G4: Capital | H4: =D15*E15/D4 -> 16.127676 | I4: =H4/$H$14 -> 0.040479173 | K4: Duration (Months) | L4: 1
C5: Device Rotation Days | D5: 8 | G5: Interest | H5: =D15*E16/D4 -> 4.0319191 | I5: =H5/$H$14 -> 0.010119793 | K5: Monthly CV | L5: =D4*(H14-H10) -> 367905.73
C6: Trips/Device/Month | D6: =30/D5 -> 3.75 | G6: Manpower | H6: =D16/D4 -> 216.60618 | I6: =H6/$H$14 -> 0.54366414 | K6: Annual CV | L6: =L5*12 -> 4414868.7
C7: Buffer Inventory | D7: 0.15 | F7: 38 | G7: SIM | H7: =D8*F7/D4 -> 11.653333 | I7: =H7/$H$14 -> 0.029248932 | K7: TCV | L7: =L5*L4 -> 367905.73
C8: Device Quantity | D8: =D4/D6*(1+D7) -> 290.47083 | E8: 1200 | G8: Server+License | H8: 5 | I8: =H8/$H$14 -> 0.012549599
B9: Loading + Unloading | C9: Field Technicians | D9: ='Field manpower per plant'!E3+'Field manpower per plant'!E4 -> 8.4166667 | E9: 20000 | G9: Consumables | H9: ='Field manpower per plant'!E10 -> 50 | I9: =H9/$H$14 -> 0.12549599
C10: RL Executives | D10: ='Field manpower per plant'!C25 -> 0.5 | E10: 22000 | G10: Penalties | H10: 10 | I10: =H10/$H$14 -> 0.025099198
C11: Control Tower Executives | D11: ='Field manpower per plant'!C26 -> 0.5 | E11: 25000 | G11: RL Courier Exp | H11: 25 | I11: =H11/$H$14 -> 0.062747994
C12: Project Manager OPS | D12: ='Field manpower per plant'!C27 -> 0.16666667 | E12: 30000 | G12: Man Cost at Loading point/trip | H12: 0 | I12: =H12/$H$14 -> 0
C13: Customer Success | D13: ='Field manpower per plant'!C28 -> 0.16666667 | E13: 50000 | G13: Net Margin | H13: 60 | I13: =H13/$H$14 -> 0.15059519
C14: Laptops | D14: =SUM(D10:D13) -> 1.3333333 | E14: 25000 | G14: Net Quote | H14: =SUM(H4:H13) -> 398.41911 | I14: =H14/$H$14 -> 1
C15: Total Capital (Assets) | D15: =D8*E8+D14*E14 -> 381898.33 | E15: 0.04 | F15: Dep | G15: Net Margin | H15: =H13*D4 -> 56831.25
C16: Monthly Manpower | D16: =SUMPRODUCT(D9:D13,E9:E13) -> 205166.67 | E16: 0.01 | F16: Int | G16: Cash Gen (Ops) | H16: =(H12+H13)*D4 -> 56831.25
G17: Months Capital Offset | H17: =D15/(H16+H4*D4) -> 5.2962592 | J17: 2
C21: Standard Model (Per Trip RL) - MBAPL-Saugor(MP) - without Manpower & RL
C22: Inputs | G22: Per Trip Costings | K22: Commercial Values
C23: Trips Per Month | D23: =D4 -> 947.1875 | G23: Capital | H23: =D34*E34/D23 -> 14.89596 | I23: =H23/$H$14 -> 0.037387663 | K23: Duration (Months) | L23: 1
C24: Device Rotation Days | D24: 8 | G24: Interest | H24: =D34*E35/D23 -> 3.7239899 | I24: =H24/$H$14 -> 0.0093469158 | K24: Monthly CV | L24: =D23*(H33-H29) -> 145934.37
C25: Trips/Device/Month | D25: =30/D24 -> 3.75 | G25: Manpower | H25: =D35/D23 -> 8.7979765 | I25: =H25/$H$14 -> 0.022082215 | K25: Annual CV | L25: =L24*12 -> 1751212.4
C26: Buffer Inventory | D26: 0.15 | F26: 38 | G26: SIM | H26: =D27*F26/D23 -> 11.653333 | I26: =H26/$H$14 -> 0.029248932 | K26: TCV | L26: =L24*L23 -> 145934.37
C27: Device Quantity | D27: =D23/D25*(1+D26) -> 290.47083 | E27: 1200 | G27: Server+License | H27: 5 | I27: =H27/$H$14 -> 0.012549599
B28: Loading + Unloading | C28: Field Technicians | D28: 0 | E28: 20000 | G28: Consumables | H28: =H9 -> 50 | I28: =H28/$H$14 -> 0.12549599
C29: RL Executives | D29: 0 | E29: 22000 | G29: Penalties | H29: 10 | I29: =H29/$H$14 -> 0.025099198
C30: Control Tower Executives | D30: 0 | E30: 25000 | G30: RL Courier Exp | H30: 0 | I30: =H30/$H$14 -> 0
C31: Project Manager OPS | D31: 0 | E31: 30000 | G31: Man Cost at Loading point/trip | H31: 0 | I31: =H31/$H$14 -> 0
C32: Customer Success | D32: =D13 -> 0.16666667 | E32: 50000 | G32: Net Margin | H32: 60 | I32: =H32/$H$14 -> 0.15059519
C33: Laptops | D33: =SUM(D29:D32) -> 0.16666667 | E33: 25000 | G33: Net Quote | H33: =SUM(H23:H32) -> 164.07126 | I33: =H33/$H$14 -> 0.4118057
C34: Total Capital (Assets) | D34: =D27*E27+D33*E33 -> 352731.67 | E34: 0.04 | F34: Dep | G34: Net Margin | H34: =H32*D23 -> 56831.25
C35: Monthly Manpower | D35: =SUMPRODUCT(D28:D32,E28:E32) -> 8333.3333 | E35: 0.01 | F35: Int | G35: Cash Gen (Ops) | H35: =(H31+H32)*D23 -> 56831.25
G36: Months Capital Offset | H36: =D34/(H35+H23*D23) -> 4.9722173

Sheet MBAPL-Dhule (MH)
C2: Standard Model (Per Trip RL) - MBAPL-Dhule (MH) - with Manpower & RL
C3: Inputs | G3: Per Trip Costings | K3: Commercial Values
C4: Trips Per Month | D4: ='Field manpower per plant'!H2 -> 520.83333 | G4: Capital | H4: =D15*E15/D4 -> 17.28 | I4: =H4/$H$14 -> 0.035912215 | K4: Duration (Months) | L4: 1
C5: Device Rotation Days | D5: 8 | G5: Interest | H5: =D15*E16/D4 -> 4.32 | I5: =H5/$H$14 -> 0.0089780536 | K5: Monthly CV | L5: =D4*(H14-H10) -> 245402.78
C6: Trips/Device/Month | D6: =30/D5 -> 3.75 | G6: Manpower | H6: =D16/D4 -> 297.92 | I6: =H6/$H$14 -> 0.61915318 | K6: Annual CV | L6: =L5*12 -> 2944833.3
C7: Buffer Inventory | D7: 0.15 | F7: 38 | G7: SIM | H7: =D8*F7/D4 -> 11.653333 | I7: =H7/$H$14 -> 0.024218577 | K7: TCV | L7: =L5*L4 -> 245402.78
C8: Device Quantity | D8: =D4/D6*(1+D7) -> 159.72222 | E8: 1200 | G8: Server+License | H8: 5 | I8: =H8/$H$14 -> 0.010391266
B9: Loading + Unloading | C9: Field Technicians | D9: ='Field manpower per plant'!H3+'Field manpower per plant'!H4 -> 5.9166667 | E9: 20000 | G9: Consumables | H9: ='Field manpower per plant'!H10 -> 50 | I9: =H9/$H$14 -> 0.10391266
C10: RL Executives | D10: ='Field manpower per plant'!C25 -> 0.5 | E10: 22000 | G10: Penalties | H10: 10 | I10: =H10/$H$14 -> 0.020782532
C11: Control Tower Executives | D11: ='Field manpower per plant'!C26 -> 0.5 | E11: 25000 | G11: RL Courier Exp | H11: 25 | I11: =H11/$H$14 -> 0.051956329
C12: Project Manager OPS | D12: ='Field manpower per plant'!C27 -> 0.16666667 | E12: 30000 | G12: Man Cost at Loading point/trip | H12: 0 | I12: =H12/$H$14 -> 0
C13: Customer Success | D13: ='Field manpower per plant'!C28 -> 0.16666667 | E13: 50000 | G13: Net Margin | H13: 60 | I13: =H13/$H$14 -> 0.12469519
C14: Laptops | D14: =SUM(D10:D13) -> 1.3333333 | E14: 25000 | G14: Net Quote | H14: =SUM(H4:H13) -> 481.17333 | I14: =H14/$H$14 -> 1
C15: Total Capital (Assets) | D15: =D8*E8+D14*E14 -> 225000 | E15: 0.04 | F15: Dep | G15: Net Margin | H15: =H13*D4 -> 31250
C16: Monthly Manpower | D16: =SUMPRODUCT(D9:D13,E9:E13) -> 155166.67 | E16: 0.01 | F16: Int | G16: Cash Gen (Ops) | H16: =(H12+H13)*D4 -> 31250
G17: Months Capital Offset | H17: =D15/(H16+H4*D4) -> 5.5900621 | J17: 2
C21: Standard Model (Per Trip RL) - MBAPL-Dhule (MH)- without Manpower & RL
C22: Inputs | G22: Per Trip Costings | K22: Commercial Values
C23: Trips Per Month | D23: =D4 -> 520.83333 | G23: Capital | H23: =D34*E34/D23 -> 15.04 | I23: =H23/$H$14 -> 0.031256928 | K23: Duration (Months) | L23: 1
C24: Device Rotation Days | D24: 8 | G24: Interest | H24: =D34*E35/D23 -> 3.76 | I24: =H24/$H$14 -> 0.0078142319 | K24: Monthly CV | L24: =D23*(H33-H29) -> 84090.278
C25: Trips/Device/Month | D25: =30/D24 -> 3.75 | G25: Manpower | H25: =D35/D23 -> 16 | I25: =H25/$H$14 -> 0.033252051 | K25: Annual CV | L25: =L24*12 -> 1009083.3
C26: Buffer Inventory | D26: 0.15 | F26: 38 | G26: SIM | H26: =D27*F26/D23 -> 11.653333 | I26: =H26/$H$14 -> 0.024218577 | K26: TCV | L26: =L24*L23 -> 84090.278
C27: Device Quantity | D27: =D23/D25*(1+D26) -> 159.72222 | E27: 1200 | G27: Server+License | H27: 5 | I27: =H27/$H$14 -> 0.010391266
B28: Loading + Unloading | C28: Field Technicians | D28: 0 | E28: 20000 | G28: Consumables | H28: =H9 -> 50 | I28: =H28/$H$14 -> 0.10391266
C29: RL Executives | D29: 0 | E29: 22000 | G29: Penalties | H29: 10 | I29: =H29/$H$14 -> 0.020782532
C30: Control Tower Executives | D30: 0 | E30: 25000 | G30: RL Courier Exp | H30: 0 | I30: =H30/$H$14 -> 0
C31: Project Manager OPS | D31: 0 | E31: 30000 | G31: Man Cost at Loading point/trip | H31: 0 | I31: =H31/$H$14 -> 0
C32: Customer Success | D32: =D13 -> 0.16666667 | E32: 50000 | G32: Net Margin | H32: 60 | I32: =H32/$H$14 -> 0.12469519
C33: Laptops | D33: =SUM(D29:D32) -> 0.16666667 | E33: 25000 | G33: Net Quote | H33: =SUM(H23:H32) -> 171.45333 | I33: =H33/$H$14 -> 0.35632343
C34: Total Capital (Assets) | D34: =D27*E27+D33*E33 -> 195833.33 | E34: 0.04 | F34: Dep | G34: Net Margin | H34: =H32*D23 -> 31250
C35: Monthly Manpower | D35: =SUMPRODUCT(D28:D32,E28:E32) -> 8333.3333 | E35: 0.01 | F35: Int | G35: Cash Gen (Ops) | H35: =(H31+H32)*D23 -> 31250
G36: Months Capital Offset | H36: =D34/(H35+H23*D23) -> 5.010661

Sheet OPIL Rajasthan BHL
C2: Standard Model (Per Trip RL) - OPIL Rajasthan BHL - with Manpower & RL
C3: Inputs | G3: Per Trip Costings | K3: Commercial Values
C4: Trips Per Month | D4: ='Field manpower per plant'!B13 -> 141.25 | G4: Capital | H4: =D15*E15/D4 -> 24.159528 | I4: =H4/$H$14 -> 0.035084593 | K4: Duration (Months) | L4: 1
C5: Device Rotation Days | D5: 8 | G5: Interest | H5: =D15*E16/D4 -> 6.039882 | I5: =H5/$H$14 -> 0.0087711482 | K5: Monthly CV | L5: =D4*(H14-H10) -> 95853.367
C6: Trips/Device/Month | D6: =30/D5 -> 3.75 | G6: Manpower | H6: =D16/D4 -> 496.75516 | I6: =H6/$H$14 -> 0.72139044 | K6: Annual CV | L6: =L5*12 -> 1150240.4
C7: Buffer Inventory | D7: 0.15 | F7: 38 | G7: SIM | H7: =D8*F7/D4 -> 11.653333 | I7: =H7/$H$14 -> 0.016923032 | K7: TCV | L7: =L5*L4 -> 95853.367
C8: Device Quantity | D8: =D4/D6*(1+D7) -> 43.316667 | E8: 1200 | G8: Server+License | H8: 5 | I8: =H8/$H$14 -> 0.0072610261
B9: Loading + Unloading | C9: Field Technicians | D9: ='Field manpower per plant'!B14+'Field manpower per plant'!B15 -> 1.6666667 | E9: 20000 | G9: Consumables | H9: ='Field manpower per plant'!B21 -> 50 | I9: =H9/$H$14 -> 0.072610261
C10: RL Executives | D10: ='Field manpower per plant'!C25 -> 0.5 | E10: 22000 | G10: Penalties | H10: 10 | I10: =H10/$H$14 -> 0.014522052
C11: Control Tower Executives | D11: ='Field manpower per plant'!C26 -> 0.5 | E11: 25000 | G11: RL Courier Exp | H11: 25 | I11: =H11/$H$14 -> 0.036305131
C12: Project Manager OPS | D12: ='Field manpower per plant'!C27 -> 0.16666667 | E12: 30000 | G12: Man Cost at Loading point/trip | H12: 0 | I12: =H12/$H$14 -> 0
C13: Customer Success | D13: ='Field manpower per plant'!C28 -> 0.16666667 | E13: 50000 | G13: Net Margin | H13: 60 | I13: =H13/$H$14 -> 0.087132314
C14: Laptops | D14: =SUM(D10:D13) -> 1.3333333 | E14: 25000 | G14: Net Quote | H14: =SUM(H4:H13) -> 688.60791 | I14: =H14/$H$14 -> 1
C15: Total Capital (Assets) | D15: =D8*E8+D14*E14 -> 85313.333 | E15: 0.04 | F15: Dep | G15: Net Margin | H15: =H13*D4 -> 8475
C16: Monthly Manpower | D16: =SUMPRODUCT(D9:D13,E9:E13) -> 70166.667 | E16: 0.01 | F16: Int | G16: Cash Gen (Ops) | H16: =(H12+H13)*D4 -> 8475
G17: Months Capital Offset | H17: =D15/(H16+H4*D4) -> 7.1767061 | J17: 2
C21: Standard Model (Per Trip RL) - OPIL Rajasthan BHL)- without Manpower & RL
C22: Inputs | G22: Per Trip Costings | K22: Commercial Values
C23: Trips Per Month | D23: =D4 -> 141.25 | G23: Capital | H23: =D34*E34/D23 -> 15.899941 | I23: =H23/$H$14 -> 0.023089977 | K23: Duration (Months) | L23: 1
C24: Device Rotation Days | D24: 8 | G24: Interest | H24: =D34*E35/D23 -> 3.9749853 | I24: =H24/$H$14 -> 0.0057724944 | K24: Monthly CV | L24: =D23*(H33-H29) -> 29030.45
C25: Trips/Device/Month | D25: =30/D24 -> 3.75 | G25: Manpower | H25: =D35/D23 -> 58.99705 | I25: =H25/$H$14 -> 0.085675825 | K25: Annual CV | L25: =L24*12 -> 348365.4
C26: Buffer Inventory | D26: 0.15 | F26: 38 | G26: SIM | H26: =D27*F26/D23 -> 11.653333 | I26: =H26/$H$14 -> 0.016923032 | K26: TCV | L26: =L24*L23 -> 29030.45
C27: Device Quantity | D27: =D23/D25*(1+D26) -> 43.316667 | E27: 1200 | G27: Server+License | H27: 5 | I27: =H27/$H$14 -> 0.0072610261
B28: Loading + Unloading | C28: Field Technicians | D28: 0 | E28: 20000 | G28: Consumables | H28: =H9 -> 50 | I28: =H28/$H$14 -> 0.072610261
C29: RL Executives | D29: 0 | E29: 22000 | G29: Penalties | H29: 10 | I29: =H29/$H$14 -> 0.014522052
C30: Control Tower Executives | D30: 0 | E30: 25000 | G30: RL Courier Exp | H30: 0 | I30: =H30/$H$14 -> 0
C31: Project Manager OPS | D31: 0 | E31: 30000 | G31: Man Cost at Loading point/trip | H31: 0 | I31: =H31/$H$14 -> 0
C32: Customer Success | D32: =D13 -> 0.16666667 | E32: 50000 | G32: Net Margin | H32: 60 | I32: =H32/$H$14 -> 0.087132314
C33: Laptops | D33: =SUM(D29:D32) -> 0.16666667 | E33: 25000 | G33: Net Quote | H33: =SUM(H23:H32) -> 215.52531 | I33: =H33/$H$14 -> 0.31298698
C34: Total Capital (Assets) | D34: =D27*E27+D33*E33 -> 56146.667 | E34: 0.04 | F34: Dep | G34: Net Margin | H34: =H32*D23 -> 8475
C35: Monthly Manpower | D35: =SUMPRODUCT(D28:D32,E28:E32) -> 8333.3333 | E35: 0.01 | F35: Int | G35: Cash Gen (Ops) | H35: =(H31+H32)*D23 -> 8475
G36: Months Capital Offset | H36: =D34/(H35+H23*D23) -> 5.2371388

Sheet SGFL Kapasan Rajasthan
C2: Standard Model (Per Trip RL) - SGFL Kapasan Rajasthan - with Manpower & RL
C3: Inputs | G3: Per Trip Costings | K3: Commercial Values
C4: Trips Per Month | D4: ='Field manpower per plant'!E13 -> 116.66667 | G4: Capital | H4: =D15*E15/D4 -> 26.148571 | I4: =H4/$H$14 -> 0.032859557 | K4: Duration (Months) | L4: 1
C5: Device Rotation Days | D5: 8 | G5: Interest | H5: =D15*E16/D4 -> 6.5371429 | I5: =H5/$H$14 -> 0.0082148892 | K5: Monthly CV | L5: =D4*(H14-H10) -> 91672.889
C6: Trips/Device/Month | D6: =30/D5 -> 3.75 | G6: Manpower | H6: =D16/D4 -> 601.42857 | I6: =H6/$H$14 -> 0.75578417 | K6: Annual CV | L6: =L5*12 -> 1100074.7
C7: Buffer Inventory | D7: 0.15 | F7: 38 | G7: SIM | H7: =D8*F7/D4 -> 11.653333 | I7: =H7/$H$14 -> 0.014644141 | K7: TCV | L7: =L5*L4 -> 91672.889
C8: Device Quantity | D8: =D4/D6*(1+D7) -> 35.777778 | E8: 1200 | G8: Server+License | H8: 5 | I8: =H8/$H$14 -> 0.0062832413
B9: Loading + Unloading | C9: Field Technicians | D9: ='Field manpower per plant'!E14+'Field manpower per plant'!E15 -> 1.6666667 | E9: 20000 | G9: Consumables | H9: ='Field manpower per plant'!E21 -> 50 | I9: =H9/$H$14 -> 0.062832413
C10: RL Executives | D10: ='Field manpower per plant'!C25 -> 0.5 | E10: 22000 | G10: Penalties | H10: 10 | I10: =H10/$H$14 -> 0.012566483
C11: Control Tower Executives | D11: ='Field manpower per plant'!C26 -> 0.5 | E11: 25000 | G11: RL Courier Exp | H11: 25 | I11: =H11/$H$14 -> 0.031416207
C12: Project Manager OPS | D12: ='Field manpower per plant'!C27 -> 0.16666667 | E12: 30000 | G12: Man Cost at Loading point/trip | H12: 0 | I12: =H12/$H$14 -> 0
C13: Customer Success | D13: ='Field manpower per plant'!C28 -> 0.16666667 | E13: 50000 | G13: Net Margin | H13: 60 | I13: =H13/$H$14 -> 0.075398896
C14: Laptops | D14: =SUM(D10:D13) -> 1.3333333 | E14: 25000 | G14: Net Quote | H14: =SUM(H4:H13) -> 795.76762 | I14: =H14/$H$14 -> 1
C15: Total Capital (Assets) | D15: =D8*E8+D14*E14 -> 76266.667 | E15: 0.04 | F15: Dep | G15: Net Margin | H15: =H13*D4 -> 7000
C16: Monthly Manpower | D16: =SUMPRODUCT(D9:D13,E9:E13) -> 70166.667 | E16: 0.01 | F16: Int | G16: Cash Gen (Ops) | H16: =(H12+H13)*D4 -> 7000
G17: Months Capital Offset | H17: =D15/(H16+H4*D4) -> 7.5882197 | J17: 2
C21: Standard Model (Per Trip RL) - SGFL Kapasan Rajasthan - without Manpower & RL
C22: Inputs | G22: Per Trip Costings | K22: Commercial Values
C23: Trips Per Month | D23: =D4 -> 116.66667 | G23: Capital | H23: =D34*E34/D23 -> 16.148571 | I23: =H23/$H$14 -> 0.020293074 | K23: Duration (Months) | L23: 1
C24: Device Rotation Days | D24: 8 | G24: Interest | H24: =D34*E35/D23 -> 4.0371429 | I24: =H24/$H$14 -> 0.0050732686 | K24: Monthly CV | L24: =D23*(H33-H29) -> 25464.556
C25: Trips/Device/Month | D25: =30/D24 -> 3.75 | G25: Manpower | H25: =D35/D23 -> 71.428571 | I25: =H25/$H$14 -> 0.089760591 | K25: Annual CV | L25: =L24*12 -> 305574.67
C26: Buffer Inventory | D26: 0.15 | F26: 38 | G26: SIM | H26: =D27*F26/D23 -> 11.653333 | I26: =H26/$H$14 -> 0.014644141 | K26: TCV | L26: =L24*L23 -> 25464.556
C27: Device Quantity | D27: =D23/D25*(1+D26) -> 35.777778 | E27: 1200 | G27: Server+License | H27: 5 | I27: =H27/$H$14 -> 0.0062832413
B28: Loading + Unloading | C28: Field Technicians | D28: 0 | E28: 20000 | G28: Consumables | H28: =H9 -> 50 | I28: =H28/$H$14 -> 0.062832413
C29: RL Executives | D29: 0 | E29: 22000 | G29: Penalties | H29: 10 | I29: =H29/$H$14 -> 0.012566483
C30: Control Tower Executives | D30: 0 | E30: 25000 | G30: RL Courier Exp | H30: 0 | I30: =H30/$H$14 -> 0
C31: Project Manager OPS | D31: 0 | E31: 30000 | G31: Man Cost at Loading point/trip | H31: 0 | I31: =H31/$H$14 -> 0
C32: Customer Success | D32: =D13 -> 0.16666667 | E32: 50000 | G32: Net Margin | H32: 60 | I32: =H32/$H$14 -> 0.075398896
C33: Laptops | D33: =SUM(D29:D32) -> 0.16666667 | E33: 25000 | G33: Net Quote | H33: =SUM(H23:H32) -> 228.26762 | I33: =H33/$H$14 -> 0.28685211
C34: Total Capital (Assets) | D34: =D27*E27+D33*E33 -> 47100 | E34: 0.04 | F34: Dep | G34: Net Margin | H34: =H32*D23 -> 7000
C35: Monthly Manpower | D35: =SUMPRODUCT(D28:D32,E28:E32) -> 8333.3333 | E35: 0.01 | F35: Int | G35: Cash Gen (Ops) | H35: =(H31+H32)*D23 -> 7000
G36: Months Capital Offset | H36: =D34/(H35+H23*D23) -> 5.3016659

Sheet Imported Fertilizers (Kandla)
C2: Standard Model (Per Trip RL) - Imported Fertilizers (Kandla) - with Manpower & RL
C3: Inputs | G3: Per Trip Costings | K3: Commercial Values
C4: Trips Per Month | D4: ='Field manpower per plant'!H13 -> 416.66667 | G4: Capital | H4: =D15*E15/D4 -> 17.92 | I4: =H4/$H$14 -> 0.037611239 | K4: Duration (Months) | L4: 1
C5: Device Rotation Days | D5: 8 | G5: Interest | H5: =D15*E16/D4 -> 4.48 | I5: =H5/$H$14 -> 0.0094028096 | K5: Monthly CV | L5: =D4*(H14-H10) -> 194355.56
C6: Trips/Device/Month | D6: =30/D5 -> 3.75 | G6: Manpower | H6: =D16/D4 -> 292.4 | I6: =H6/$H$14 -> 0.61370124 | K6: Annual CV | L6: =L5*12 -> 2332266.7
C7: Buffer Inventory | D7: 0.15 | F7: 38 | G7: SIM | H7: =D8*F7/D4 -> 11.653333 | I7: =H7/$H$14 -> 0.024458499 | K7: TCV | L7: =L5*L4 -> 194355.56
C8: Device Quantity | D8: =D4/D6*(1+D7) -> 127.77778 | E8: 1200 | G8: Server+License | H8: 5 | I8: =H8/$H$14 -> 0.010494207
B9: Loading + Unloading | C9: Field Technicians | D9: ='Field manpower per plant'!H14+'Field manpower per plant'!H15 -> 4.25 | E9: 20000 | G9: Consumables | H9: ='Field manpower per plant'!H21 -> 50 | I9: =H9/$H$14 -> 0.10494207
C10: RL Executives | D10: ='Field manpower per plant'!C25 -> 0.5 | E10: 22000 | G10: Penalties | H10: 10 | I10: =H10/$H$14 -> 0.020988414
C11: Control Tower Executives | D11: ='Field manpower per plant'!C26 -> 0.5 | E11: 25000 | G11: RL Courier Exp | H11: 25 | I11: =H11/$H$14 -> 0.052471036
C12: Project Manager OPS | D12: ='Field manpower per plant'!C27 -> 0.16666667 | E12: 30000 | G12: Man Cost at Loading point/trip | H12: 0 | I12: =H12/$H$14 -> 0
C13: Customer Success | D13: ='Field manpower per plant'!C28 -> 0.16666667 | E13: 50000 | G13: Net Margin | H13: 60 | I13: =H13/$H$14 -> 0.12593049
C14: Laptops | D14: =SUM(D10:D13) -> 1.3333333 | E14: 25000 | G14: Net Quote | H14: =SUM(H4:H13) -> 476.45333 | I14: =H14/$H$14 -> 1
C15: Total Capital (Assets) | D15: =D8*E8+D14*E14 -> 186666.67 | E15: 0.04 | F15: Dep | G15: Net Margin | H15: =H13*D4 -> 25000
C16: Monthly Manpower | D16: =SUMPRODUCT(D9:D13,E9:E13) -> 121833.33 | E16: 0.01 | F16: Int | G16: Cash Gen (Ops) | H16: =(H12+H13)*D4 -> 25000
G17: Months Capital Offset | H17: =D15/(H16+H4*D4) -> 5.7494867 | J17: 2
C21: Standard Model (Per Trip RL) - Imported Fertilizers (Kandla) - without Manpower & RL
C22: Inputs | G22: Per Trip Costings | K22: Commercial Values
C23: Trips Per Month | D23: =D4 -> 416.66667 | G23: Capital | H23: =D34*E34/D23 -> 15.12 | I23: =H23/$H$14 -> 0.031734483 | K23: Duration (Months) | L23: 1
C24: Device Rotation Days | D24: 8 | G24: Interest | H24: =D34*E35/D23 -> 3.78 | I24: =H24/$H$14 -> 0.0079336206 | K24: Monthly CV | L24: =D23*(H33-H29) -> 68980.556
C25: Trips/Device/Month | D25: =30/D24 -> 3.75 | G25: Manpower | H25: =D35/D23 -> 20 | I25: =H25/$H$14 -> 0.041976829 | K25: Annual CV | L25: =L24*12 -> 827766.67
C26: Buffer Inventory | D26: 0.15 | F26: 38 | G26: SIM | H26: =D27*F26/D23 -> 11.653333 | I26: =H26/$H$14 -> 0.024458499 | K26: TCV | L26: =L24*L23 -> 68980.556
C27: Device Quantity | D27: =D23/D25*(1+D26) -> 127.77778 | E27: 1200 | G27: Server+License | H27: 5 | I27: =H27/$H$14 -> 0.010494207
B28: Loading + Unloading | C28: Field Technicians | D28: 0 | E28: 20000 | G28: Consumables | H28: =H9 -> 50 | I28: =H28/$H$14 -> 0.10494207
C29: RL Executives | D29: 0 | E29: 22000 | G29: Penalties | H29: 10 | I29: =H29/$H$14 -> 0.020988414
C30: Control Tower Executives | D30: 0 | E30: 25000 | G30: RL Courier Exp | H30: 0 | I30: =H30/$H$14 -> 0
C31: Project Manager OPS | D31: 0 | E31: 30000 | G31: Man Cost at Loading point/trip | H31: 0 | I31: =H31/$H$14 -> 0
C32: Customer Success | D32: =D13 -> 0.16666667 | E32: 50000 | G32: Net Margin | H32: 60 | I32: =H32/$H$14 -> 0.12593049
C33: Laptops | D33: =SUM(D29:D32) -> 0.16666667 | E33: 25000 | G33: Net Quote | H33: =SUM(H23:H32) -> 175.55333 | I33: =H33/$H$14 -> 0.36845861
C34: Total Capital (Assets) | D34: =D27*E27+D33*E33 -> 157500 | E34: 0.04 | F34: Dep | G34: Net Margin | H34: =H32*D23 -> 25000
C35: Monthly Manpower | D35: =SUMPRODUCT(D28:D32,E28:E32) -> 8333.3333 | E35: 0.01 | F35: Int | G35: Cash Gen (Ops) | H35: =(H31+H32)*D23 -> 25000
G36: Months Capital Offset | H36: =D34/(H35+H23*D23) -> 5.0319489
