Workbook

Sheet Quotation with formula
H1: Quotation
B2: Address - Corporate HQ : Axestrack Software Solutions Pvt. Ltd., Office No.-19, 6th Floor, Jaipur Electronic Market, Near Riddhi Siddhi, Gopalpura bypass, Jaipur - 302018 , Rajasthan, India
B3: GSTIN | D3: 08AACCH0299P1Z1 | F3: QUOTE # | H3: DATE
B4: MSME No | D4: UDYAM-RJ-17-0051921 | F4: ABC/XY/YYMM##
B5: Contact Person
B6: Phone | F6: Quote Validity : 15 days from submitted date
B7: Email Id
B9: CUSTOMER INFO
B10: Company Name
B11: Address
B12: Contact Person | F12: Phone
B13: Email Id
B15: DESCRIPTION OF WORK
B16: Connected Plant Logistics (CPL) solution that digitizes plant-level gate processes, integrates with existing Tracking Partner, and provides real-time monitoring of inbound vehicles TAT to enhance visibility, efficiency, and accountability across 8 Ashok Leyland plants
B17: S.No. | C17: Year | E17: Items | G17: Type | I17: Amount
B18: 1 | C18: Hardware Cost (including Hardware Transportation) | E18: Option 1 (Recommended) : RFID Reader + ANPR Camera Based Solution (with Industrial Grade Tablet at Gate In of each plant) | G18: One time (For all 8 plants) | I18: ='Commercials 1 - RFID+ANPR'!M13 -> 2115600
E19: Option 2 : RFID Reader Based Solution (with Industrial Grade Tablet at Gate In of each plant) | G19: One time (For all 8 plants) | I19: ='Commercials 2 - RFID'!M14 -> 1316100 | L19: =I19 -> 1316100
B20: 2 | C20: Implementation Cost | E20: Installation and hardware commissioning Cost per plant | G20: One time/ per plant | I20: ='Commercials 1 - RFID+ANPR'!L15+'Commercials 1 - RFID+ANPR'!L16 -> 16969.697 | L20: =I20*8 -> 135757.58
E21: Integration Cost (with Tracking Platform & ERP) | G21: One time (For all 8 plants) | I21: ='Commercials 1 - RFID+ANPR'!M17 -> 50000 | L21: =I21 -> 50000
B22: 3 | C22: Subscription Fee Post Go-Live | E22: Platform Subscription + Support & Maintenance | G22: Per Month (For all 8 plants) | I22: =K22 -> 104444.44 | J22: ='Commercials 1 - RFID+ANPR'!L20+'Commercials 1 - RFID+ANPR'!L22 -> 1253333.3 | K22: =J22/12 -> 104444.44 | L22: =K22*12 -> 1253333.3
B24: Terms & Conditions
B25: • All prices quoted in this proposal are in Indian Rupees (INR) and are exclusive of GST. Taxes as applicable. • Device ownership shall remain with the Client. • These commercials are applicable only for scope mentioned in the proposal document. For the detailed scope of the solution, please refer to the proposal document. • The above estimation is based on details received and the agreed scope. Any formal change or upgrade in hardware specifications, integration requirements, workflows, or product features beyond those included in proposal doucumnet shall be treated as a change request and will attract additional charges. • The Subscription Fee covers up to Eight (8) plants only. • The standard one-year hardware warranty, as per OEM guidelines, shall apply from the date of hardware delivery. Burnt, physically damaged, or tampered hardware is excluded from warranty and shall not be covered under AMC. Kindly refer to the attached Hardware Warranty T&C. • The proposed pricing assumes a minimum engagement period of three (3) years from the date of deployment, ensuring continuity and optimal cost efficiency. • Civil works (including trenching, power supply, LAN/Wi-Fi readiness, enclosures), UPS provisioning, and related site readiness shall remain in the Client’s scope, as outlined in the assumptions and dependencies section. • AMC charges from the 2nd year onwards will be billed separately. Pricing and detailed AMC terms will be shared upon request. • Spares and accessory parts, if required, will be charged separately at prevailing rates. Payment Terms: • 100% of the hardware cost is payable upfront at project kickoff. • Payment for platform subscription, support, and maintenance will be on a quarterly advance basis. • All invoices are payable within fifteen (15) days from the date of receipt (original or digitally signed). • Any delay in payment will attract an overdue charge of 1.5% per month or the maximum permissible under law, whichever is lower.
B26: Thanks for doing business with Axestrack Software Solution Pvt. Ltd.

Sheet Quote Nomeclature
B2: Quote no Format
B3: ABC/XY/YYMM##
B5: ABC | C5: Client name short Form like Hindalco Industries Limited will be HIL
B6: XY | C6: Axestrack Sales SPOC Intials
B7: YY | C7: Year
B8: MM | C8: Month
B9: ## | C9: Quote send by Sales SPOC in that particular month, quote nos. should be start from 11

Sheet Commercials 1 - RFID+ANPR
B2: Customer | D2: Ashok Leyland
B3: Date | D3: 45975
B4: Contract Year | D4: 3
B5: AMC Cost | D5: 0.15
B6: Hardware Transportation Cost | D6: 0.025
B7: ERP Integration/ Tracking platform Cost | D7: 50000
B8: Software Subscription Cost/month/plant | D8: 12000
B10: Model | C10: Items | E10: Details | F10: Type | G10: Unit Cost | H10: Count | I10: Years | J10: Landed Cost to Axestrack | K10: Margin | L10: Unit price with Margin | M10: Cost for Customer | N10: Project Margin | O10: Project Margin %
B11: Hardware + Implementation | C11: Hardware Cost | D11: ANPR + RFID Based solution | E11: ANPR + RFID based solution | F11: One Time | G11: =BOQ!J36 -> 1548000 | H11: 0 | J11: =IF(H11=0,G11,G11*H11) -> 1548000 | K11: 0.25 | L11: =G11/(1-K11) -> 2064000 | M11: =J11/(1-K11) -> 2064000 | N11: =M11-J11 -> 516000 | O11: =N11/M11 -> 0.25 | P11: =M11/(M11+#REF!) -> #REF!
E12: Hardware Transportation Cost | F12: One Time | G12: =$D$6*G11 -> 38700 | H12: 0 | J12: =IF(H12=0,G12,G12*H12) -> 38700 | K12: 0.25 | L12: =G12/(1-K12) -> 51600 | M12: =J12/(1-K12) -> 51600 | N12: =M12-J12 -> 12900 | O12: =N12/M12 -> 0.25
E13: Hardware Cost | J13: =SUM(J11:J12) -> 1586700 | M13: =SUM(M11:M12) -> 2115600 | N13: =SUM(N11:N12) -> 528900 | O13: =N13/M13 -> 0.25
D14: Total Hardware Cost | J14: =J13 -> 1586700 | M14: =M13 -> 2115600 | N14: =N13 -> 528900 | O14: =N14/M14 -> 0.25
C15: Implementation Cost | D15: Per Plant Installation Cost | E15: Installation Cost per plant | F15: One Time | G15: ='Manpower-PM Cost'!I9 -> 7727.2727 | H15: 8 | J15: =IF(H15=0,G15,G15*H15) -> 61818.182 | K15: 0.25 | L15: =G15/(1-K15) -> 10303.03 | M15: =J15/(1-K15) -> 82424.242 | N15: =M15-J15 -> 20606.061 | O15: =N15/M15 -> 0.25
D16: Boarding & Lodging | E16: Resource cost for implementation per week | F16: One Time | G16: ='Manpower-PM Cost'!J24 -> 5000 | H16: 8 | J16: =IF(H16=0,G16,G16*H16) -> 40000 | K16: 0.25 | L16: =G16/(1-K16) -> 6666.6667 | M16: =J16/(1-K16) -> 53333.333 | N16: =M16-J16 -> 13333.333 | O16: =N16/M16 -> 0.25
D17: ERP Integration | E17: ERP/Tracking Platform Integration | F17: One Time | G17: =$D$7 -> 50000 | H17: 1 | J17: =IF(H17=0,G17,G17*H17) -> 50000 | K17: 0 | L17: =G17/(1-K17) -> 50000 | M17: =J17/(1-K17) -> 50000 | N17: =M17-J17 -> 0 | O17: =N17/M17 -> 0
D18: Total Installation, Setup & API Development Cost | J18: =SUM(J15:J17) -> 151818.18 | L18: =SUM(L15:L17) -> 66969.697 | M18: =SUM(M15:M17) -> 185757.58 | N18: =SUM(N15:N17) -> 33939.394 | O18: =N18/M18 -> 0.18270799
C19: One Time Cost | J19: =J14+J18 -> 1738518.2 | L19: =L14+L18 -> 66969.697 | M19: =M14+M18 -> 2301357.6 | N19: =N14+N18 -> 562839.39 | O19: =N19/M19 -> 0.24456842
B20: Subscription Fee | C20: Annual Subscription fee | D20: PMO, Support & Maintenance | E20: Project Manpower Cost | F20: Per Year | G20: ='Manpower-PM Cost'!U9+'Manpower-PM Cost'!V24 -> 76000 | I20: =$D$4 -> 3 | J20: =IF(H20=0,G20*I20,G20*H20*I20) -> 228000 | K20: 0.25 | L20: =G20/(1-K20) -> 101333.33 | M20: =J20/(1-K20) -> 304000 | N20: =M20*K20 -> 76000 | O20: =N20/M20 -> 0.25
D21: Project Management Cost | J21: =SUM(J20:J20) -> 228000 | L21: =SUM(L20:L20) -> 101333.33 | M21: =SUM(M20:M20) -> 304000 | N21: =SUM(N20) -> 76000 | O21: =N21/M21 -> 0.25
D22: Platform Subscription Fee | E22: Platform Subscription Fee per plant | F22: Per Year | G22: =D8*12*8 -> 1152000 | I22: 3 | J22: =IF(H22=0,G22*I22,G22*H22*I22) -> 3456000 | K22: 0 | L22: =G22/(1-K22) -> 1152000 | M22: =J22/(1-K22) -> 3456000 | N22: =M22*0.5 -> 1728000 | O22: =N22/M22 -> 0.5
D23: Platform Fee | J23: =SUM(J22) -> 3456000 | L23: =SUM(L22) -> 1152000 | M23: =SUM(M22) -> 3456000 | N23: =SUM(N22) -> 1728000 | O23: =N23/M23 -> 0.5
C24: Subscription Fee | J24: =J21+J23 -> 3684000 | L24: =L21+L23 -> 1253333.3 | M24: =M21+M23 -> 3760000 | N24: =N21+N23 -> 1804000 | O24: =N24/M24 -> 0.47978723
B25: AMC | C25: AMC | D25: Hardware AMC | E25: AMC from 2nd Year | F25: Per Year | G25: =G11*$D$5 -> 232200 | H25: =Master!$B$9 -> 2 | I25: =$D$4-1 -> 2 | J25: =IF(H25=0,G25*I25,G25*H25*I25) -> 928800 | K25: 0.25 | L25: =G25/(1-K25) -> 309600 | M25: =J25/(1-K25) -> 1238400 | N25: =M25*K25 -> 309600 | O25: =N25/M25 -> 0.25
C26: AMC | J26: =SUM(J25:J25) -> 928800 | L26: =SUM(L25:L25) -> 309600 | M26: =SUM(M25:M25) -> 1238400 | N26: =SUM(N25:N25) -> 309600 | O26: =N26/M26 -> 0.25
B27: Total Cost of the Project Implementation & Support + AMC | J27: =J19+J24+J26 -> 6351318.2 | M27: =M19+M24+M26 -> 7299757.6 | N27: =N19+N24+N26 -> 2676439.4 | O27: =N27/M27 -> 0.36664771

Sheet Commercials 2 - RFID
B2: Customer | D2: Ashok Leyland
B3: Date | D3: 45975
B4: Contract Year | D4: 3
B5: AMC Cost | D5: 0.15
B6: Hardware Transportation Cost | D6: 0.025
B7: ERP Integration/ Tracking platform Cost | D7: 50000
B8: Software Subscription Cost/month/plant | D8: 12000
B10: Model | C10: Items | E10: Details | F10: Type | G10: Unit Cost | H10: Count | I10: Years | J10: Landed Cost to Axestrack | K10: Margin | L10: Unit price with Margin | M10: Cost for Customer | N10: Project Margin | O10: Project Margin %
B11: Hardware + Implementation | C11: Hardware Cost | D11: ANPR + RFID Based solution | E11: RFID based solution | F11: One Time | G11: ='Total Hardware'!K8 -> 963000 | H11: 0 | J11: =BOQ!N36 -> 963000 | K11: 0.25 | L11: =G11/(1-K11) -> 1284000 | M11: =J11/(1-K11) -> 1284000 | N11: =M11-J11 -> 321000 | O11: =N11/M11 -> 0.25 | P11: =M11/(M11+#REF!) -> #REF!
E12: Hardware Transportation Cost | F12: One Time | G12: =$D$6*G11 -> 24075 | H12: 0 | J12: =IF(H12=0,G12,G12*H12) -> 24075 | K12: 0.25 | L12: =G12/(1-K12) -> 32100 | M12: =J12/(1-K12) -> 32100 | N12: =M12-J12 -> 8025 | O12: =N12/M12 -> 0.25
E13: Hardware Cost | J13: =SUM(J11:J12) -> 987075 | M13: =SUM(M11:M12) -> 1316100 | N13: =SUM(N11:N12) -> 329025 | O13: =N13/M13 -> 0.25
D14: Total Hardware Cost | J14: =J13 -> 987075 | M14: =M13 -> 1316100 | N14: =N13 -> 329025 | O14: =N14/M14 -> 0.25
C15: Implementation Cost | D15: Per Plant Installation Cost | E15: Installation Cost per plant | F15: One Time | G15: ='Manpower-PM Cost'!I9 -> 7727.2727 | H15: 8 | J15: =IF(H15=0,G15,G15*H15) -> 61818.182 | K15: 0.25 | L15: =G15/(1-K15) -> 10303.03 | M15: =J15/(1-K15) -> 82424.242 | N15: =M15-J15 -> 20606.061 | O15: =N15/M15 -> 0.25
D16: Boarding & Lodging | E16: Resource cost for implementation per week | F16: One Time | G16: ='Manpower-PM Cost'!J24 -> 5000 | H16: 8 | J16: =IF(H16=0,G16,G16*H16) -> 40000 | K16: 0.25 | L16: =G16/(1-K16) -> 6666.6667 | M16: =J16/(1-K16) -> 53333.333 | N16: =M16-J16 -> 13333.333 | O16: =N16/M16 -> 0.25
D17: ERP Integration | E17: ERP/Tracking Platform Integration | F17: One Time | G17: =$D$7 -> 50000 | H17: 1 | J17: =IF(H17=0,G17,G17*H17) -> 50000 | K17: 0 | L17: =G17/(1-K17) -> 50000 | M17: =J17/(1-K17) -> 50000 | N17: =M17-J17 -> 0 | O17: =N17/M17 -> 0
D18: Total Installation, Setup & API Development Cost | J18: =SUM(J15:J17) -> 151818.18 | L18: =SUM(L15:L17) -> 66969.697 | M18: =SUM(M15:M17) -> 185757.58 | N18: =SUM(N15:N17) -> 33939.394 | O18: =N18/M18 -> 0.18270799
C19: One Time Cost | J19: =J14+J18 -> 1138893.2 | L19: =L14+L18 -> 66969.697 | M19: =M14+M18 -> 1501857.6 | N19: =N14+N18 -> 362964.39 | O19: =N19/M19 -> 0.24167697
B20: Subscription Fee | C20: Annual Subscription fee | D20: PMO, Support & Maintenance | E20: Project Manpower Cost | F20: Per Year | G20: ='Manpower-PM Cost'!U9+'Manpower-PM Cost'!V24 -> 76000 | I20: =$D$4 -> 3 | J20: =IF(H20=0,G20*I20,G20*H20*I20) -> 228000 | K20: 0.25 | L20: =G20/(1-K20) -> 101333.33 | M20: =J20/(1-K20) -> 304000 | N20: =M20*K20 -> 76000 | O20: =N20/M20 -> 0.25
D21: Project Management Cost | J21: =SUM(J20:J20) -> 228000 | L21: =SUM(L20:L20) -> 101333.33 | M21: =SUM(M20:M20) -> 304000 | N21: =SUM(N20) -> 76000 | O21: =N21/M21 -> 0.25
D22: Platform Subscription Fee | E22: Platform Subscription Fee per plant | F22: Per Year | G22: =D8*12*8 -> 1152000 | I22: 3 | J22: =IF(H22=0,G22*I22,G22*H22*I22) -> 3456000 | K22: 0 | L22: =G22/(1-K22) -> 1152000 | M22: =J22/(1-K22) -> 3456000 | N22: =M22*0.5 -> 1728000 | O22: =N22/M22 -> 0.5
D23: Platform Fee | J23: =SUM(J22) -> 3456000 | L23: =SUM(L22) -> 1152000 | M23: =SUM(M22) -> 3456000 | N23: =SUM(N22) -> 1728000 | O23: =N23/M23 -> 0.5
C24: Subscription Fee | J24: =J21+J23 -> 3684000 | L24: =L21+L23 -> 1253333.3 | M24: =M21+M23 -> 3760000 | N24: =N21+N23 -> 1804000 | O24: =N24/M24 -> 0.47978723
B25: AMC | C25: AMC | D25: Hardware AMC | E25: AMC from 2nd Year | F25: Per Year | G25: =G11*$D$5 -> 144450 | H25: =Master!$B$9 -> 2 | I25: =$D$4-1 -> 2 | J25: =IF(H25=0,G25*I25,G25*H25*I25) -> 577800 | K25: 0.25 | L25: =G25/(1-K25) -> 192600 | M25: =J25/(1-K25) -> 770400 | N25: =M25*K25 -> 192600 | O25: =N25/M25 -> 0.25
C26: AMC | J26: =SUM(J25:J25) -> 577800 | L26: =SUM(L25:L25) -> 192600 | M26: =SUM(M25:M25) -> 770400 | N26: =SUM(N25:N25) -> 192600 | O26: =N26/M26 -> 0.25
B27: Total Cost of the Project Implementation & Support + AMC | J27: =J19+J24+J26 -> 5400693.2 | M27: =M19+M24+M26 -> 6032257.6 | N27: =N19+N24+N26 -> 2359564.4 | O27: =N27/M27 -> 0.39115777

Sheet Manpower-PM Cost
B2: Per Weighbridge Installation Cost | N2: Project Support Manpower (Post Go-Live)
C4: Implementation Cost | O4: Support Manpower (Post Go-Live)
C5: Per Plant Installation Cost | O5: Support & Maintenance Manpower
C6: Type of Manpower | D6: Type | E6: Count per shift | F6: Nos. of shifts | G6: Cost per Resource per month | H6: Duration in Months | I6: Total | O6: Type of Manpower | P6: Type | Q6: Count per shift | R6: Nos. of shifts | S6: Cost per Resource per month | T6: Duration in Months | U6: Total
C7: Hardware Engineer | D7: Onsite | E7: 1 | F7: 1 | G7: 25000 | H7: =2/22 -> 0.090909091 | I7: =PRODUCT(E7:H7) -> 2272.7273 | O7: Customer Success | P7: Offshore | Q7: 0.25 | R7: 0.5 | S7: 40000 | T7: 12 | U7: =PRODUCT(Q7:T7) -> 60000
C8: Software Engineer | D8: Offshore | E8: 1 | F8: 1 | G8: 60000 | H8: =2/22 -> 0.090909091 | I8: =PRODUCT(E8:H8) -> 5454.5455 | O8: Software Enginner | P8: Offshore | Q8: 0 | R8: 0 | S8: 0 | T8: 0 | U8: =PRODUCT(Q8:T8) -> 0
E9: =SUMPRODUCT(E7:E7,F7:F7) -> 1 | H9: Total | I9: =SUM(I7:I8) -> 7727.2727 | Q9: =SUMPRODUCT(Q7:Q7,R7:R7) -> 0.125 | T9: Total | U9: =SUM(U7:U8) -> 60000
C12: Current Equipments | E12: Count | F12: Productivity per resource | G12: Resources Required | L12: Planned Equipments
C13: Machines | E13: 47 | F13: 6 | G13: =ROUND(E13/F13,0) -> 8 | L13: Machines
C14: Gate Lanes | E14: 40 | F14: 7 | G14: =ROUND(E14/F14,0) -> 6 | L14: Gate Lanes
C15: Vehicles | E15: 810 | F15: 120 | G15: =ROUND(E15/F15,0) -> 7 | L15: Vehicles
F16: Onsite | G16: =SUM(G13:G15) -> 21
F17: MIS | G17: =ROUND(G16/8,0) -> 3
F18: Total | G18: =G16+G17 -> 24
C19: Travel Cost (Till Go-Live) | O19: Project Management Cost - Travel & Lodging
C20: Boarding & Lodging - Per Plant Installation Cost | O20: Annual Project Management Cost - Travel & Lodging
C21: Type of Manpower | D21: Type | E21: Day Allowance | F21: Travel Cost | G21: Stay Cost per Day | H21: Days per trip | I21: Frequency (Till Go-live) | J21: Total | O21: Type of Manpower | P21: Type | Q21: Travel Allowance | R21: Travel Cost | S21: Stay Cost per Day | T21: Days per trip | U21: Frequency (Annually) | V21: Total
C22: Hardware Engineer | D22: Onsite | E22: 750 | F22: =750*2 -> 1500 | G22: 1000 | H22: =2 -> 2 | I22: 1 | J22: =(I22*H22*E22)+(F22*I22)+(G22*H22*I22) -> 5000 | O22: Support Engineers | P22: Per Year | Q22: 0 | R22: 0 | S22: 0 | T22: 0 | U22: 0 | V22: =(U22*T22*Q22)+(R22*U22)+(S22*T22*U22) -> 0
C23: Software Engineer | D23: Offshore | E23: 0 | F23: 0 | G23: 0 | H23: 0 | I23: 0 | J23: =(I23*H23*E23)+(F23*I23)+(G23*H23*I23) -> 0 | O23: Mis. Travel | P23: Per Year | Q23: 1000 | R23: 1500 | S23: 1500 | T23: 1 | U23: 4 | V23: =(U23*T23*Q23)+(R23*U23)+(S23*T23*U23) -> 16000
I24: Total | J24: =SUM(J22:J23) -> 5000 | U24: Total | V24: =SUM(V22:V23) -> 16000
S26: `

Sheet Total Hardware
D2: With ANPR CAMERA | J2: Without ANPR CAMERA - RFID Based solution
A3: Sr. No. | B3: Hardware | C3: Unit Price | D3: Count | E3: Landing Cost of Hardware | F3: Spares | G3: Landing Cost of Spares | H3: Total Landing Cost | I3: Total Count | J3: Count | K3: Landing Cost of Hardware | L3: Spares | M3: Landing Cost of Spares | N3: Total Landing Cost | O3: Total Count
A4: 1 | B4: RFID Reader | C4: =VLOOKUP($B4,Master!$A$3:$B$6,2,FALSE) -> 33000 | D4: =SUMIF(BOQ!$D$4:$I$35,'Total Hardware'!$B4,BOQ!$H$4:$H$35) -> 18 | E4: =D4*$C4 -> 594000 | F4: 2 | G4: =F4*$C4 -> 66000 | H4: =E4+G4 -> 660000 | I4: =D4+F4 -> 20 | J4: =SUMIF(BOQ!$D$4:$N$35,'Total Hardware'!$B4,BOQ!$M$4:$M$35) -> 18 | K4: =J4*$C4 -> 594000 | L4: 2 | M4: =L4*$C4 -> 66000 | N4: =K4+M4 -> 660000 | O4: =J4+L4 -> 20
A5: 2 | B5: ANPR Camera | C5: =VLOOKUP($B5,Master!$A$3:$B$6,2,FALSE) -> 65000 | D5: =SUMIF(BOQ!$D$4:$I$35,'Total Hardware'!$B5,BOQ!$H$4:$H$35) -> 9 | E5: =D5*$C5 -> 585000 | F5: 1 | G5: =F5*$C5 -> 65000 | H5: =E5+G5 -> 650000 | I5: =D5+F5 -> 10 | J5: =SUMIF(BOQ!$D$4:$N$35,'Total Hardware'!$B5,BOQ!$M$4:$M$35) -> 0 | K5: =J5*$C5 -> 0 | L5: 0 | M5: =L5*$C5 -> 0 | N5: =K5+M5 -> 0 | O5: =J5+L5 -> 0
A6: 3 | B6: Tablet | C6: =VLOOKUP($B6,Master!$A$3:$B$6,2,FALSE) -> 41000 | D6: =SUMIF(BOQ!$D$4:$I$35,'Total Hardware'!$B6,BOQ!$H$4:$H$35) -> 9 | E6: =D6*$C6 -> 369000 | F6: 0 | G6: =F6*$C6 -> 0 | H6: =E6+G6 -> 369000 | I6: =D6+F6 -> 9 | J6: =SUMIF(BOQ!$D$4:$N$35,'Total Hardware'!$B6,BOQ!$M$4:$M$35) -> 9 | K6: =J6*$C6 -> 369000 | L6: 0 | M6: =L6*$C6 -> 0 | N6: =K6+M6 -> 369000 | O6: =J6+L6 -> 9
A7: 4 | B7: AT Controller | C7: =VLOOKUP($B7,Master!$A$3:$B$6,2,FALSE) -> 12000 | D7: =SUMIF(BOQ!$D$4:$I$35,'Total Hardware'!$B7,BOQ!$H$4:$H$35) -> 0 | E7: =D7*$C7 -> 0 | F7: 0 | G7: =F7*$C7 -> 0 | H7: =E7+G7 -> 0 | I7: =D7+F7 -> 0 | J7: =SUMIF(BOQ!$D$4:$N$35,'Total Hardware'!$B7,BOQ!$M$4:$M$35) -> 0 | K7: =J7*$C7 -> 0 | L7: 0 | M7: =L7*$C7 -> 0 | N7: =K7+M7 -> 0 | O7: =J7+L7 -> 0
B8: Total | D8: =SUM(D4:D7) -> 36 | E8: =SUM(E4:E7) -> 1548000 | F8: =SUM(F4:F7) -> 3 | G8: =SUM(G4:G7) -> 131000 | H8: =SUM(H4:H7) -> 1679000 | I8: =SUM(I4:I7) -> 39 | J8: =SUM(J4:J7) -> 27 | K8: =SUM(K4:K7) -> 963000 | ... O8: =SUM(O4:O7) -> 29
B10: This is formula driven sheet. Only update the spares Count
B11: Please update the BOQ sheet for other fields

Sheet BOQ
F2: With ANPR CAMERA | K2: Without ANPR CAMERA - RFID Based solution
A3: # | B3: Plant | C3: Location | D3: Hardware | E3: Unit Price | F3: Quantity per Check Point | G3: Check point | H3: Total Quantity as per stage | I3: Total | J3: Plant wise Price | K3: Quantity per Check Point | L3: Check point | M3: Total Quantity as per stage | N3: Total | O3: Plant wise Price
A4: 1 | B4: Ennore | C4: Gate In | D4: RFID Reader | E4: =VLOOKUP(D4,Master!$A$3:$B$6,2,0) -> 33000 | F4: 1 | G4: =VLOOKUP($B4,Master!$A$9:$B$16,2,FALSE) -> 2 | H4: =F4*G4 -> 2 | I4: =H4*$E4 -> 66000 | J4: =SUM(I4:I7) -> 344000 | K4: 1 | L4: =VLOOKUP($B4,Master!$A$9:$B$16,2,FALSE) -> 2 | M4: =K4*L4 -> 2 | N4: =M4*$E4 -> 66000 | O4: =SUM(N4:N7) -> 214000
B5: Ennore | C5: Gate In | D5: ANPR Camera | E5: =VLOOKUP(D5,Master!$A$3:$B$6,2,0) -> 65000 | F5: 1 | G5: =VLOOKUP($B5,Master!$A$9:$B$16,2,FALSE) -> 2 | H5: =F5*G5 -> 2 | I5: =H5*$E5 -> 130000 | K5: 0 | L5: =VLOOKUP($B5,Master!$A$9:$B$16,2,FALSE) -> 2 | M5: =K5*L5 -> 0 | N5: =M5*$E5 -> 0
B6: Ennore | C6: Gate In | D6: Tablet | E6: =VLOOKUP(D6,Master!$A$3:$B$6,2,0) -> 41000 | F6: 1 | G6: =VLOOKUP($B6,Master!$A$9:$B$16,2,FALSE) -> 2 | H6: =F6*G6 -> 2 | I6: =H6*$E6 -> 82000 | K6: 1 | L6: =VLOOKUP($B6,Master!$A$9:$B$16,2,FALSE) -> 2 | M6: =K6*L6 -> 2 | N6: =M6*$E6 -> 82000
B7: Ennore | C7: Gate Out | D7: RFID Reader | E7: =VLOOKUP(D7,Master!$A$3:$B$6,2,0) -> 33000 | F7: 1 | G7: =VLOOKUP($B7,Master!$A$9:$B$16,2,FALSE) -> 2 | H7: =F7*G7 -> 2 | I7: =H7*$E7 -> 66000 | K7: 1 | L7: =VLOOKUP($B7,Master!$A$9:$B$16,2,FALSE) -> 2 | M7: =K7*L7 -> 2 | N7: =M7*$E7 -> 66000
A8: 2 | B8: Hosur 1 | C8: Gate In | D8: RFID Reader | E8: =VLOOKUP(D8,Master!$A$3:$B$6,2,0) -> 33000 | F8: 1 | G8: =VLOOKUP($B8,Master!$A$9:$B$16,2,FALSE) -> 1 | H8: =F8*G8 -> 1 | I8: =H8*$E8 -> 33000 | J8: =SUM(I8:I11) -> 172000 | K8: 1 | L8: =VLOOKUP($B8,Master!$A$9:$B$16,2,FALSE) -> 1 | M8: =K8*L8 -> 1 | N8: =M8*$E8 -> 33000 | O8: =SUM(N8:N11) -> 107000
B9: Hosur 1 | C9: Gate In | D9: ANPR Camera | E9: =VLOOKUP(D9,Master!$A$3:$B$6,2,0) -> 65000 | F9: 1 | G9: =VLOOKUP($B9,Master!$A$9:$B$16,2,FALSE) -> 1 | H9: =F9*G9 -> 1 | I9: =H9*$E9 -> 65000 | K9: 0 | L9: =VLOOKUP($B9,Master!$A$9:$B$16,2,FALSE) -> 1 | M9: =K9*L9 -> 0 | N9: =M9*$E9 -> 0
B10: Hosur 1 | C10: Gate In | D10: Tablet | E10: =VLOOKUP(D10,Master!$A$3:$B$6,2,0) -> 41000 | F10: 1 | G10: =VLOOKUP($B10,Master!$A$9:$B$16,2,FALSE) -> 1 | H10: =F10*G10 -> 1 | I10: =H10*$E10 -> 41000 | K10: 1 | L10: =VLOOKUP($B10,Master!$A$9:$B$16,2,FALSE) -> 1 | M10: =K10*L10 -> 1 | N10: =M10*$E10 -> 41000
B11: Hosur 1 | C11: Gate Out | D11: RFID Reader | E11: =VLOOKUP(D11,Master!$A$3:$B$6,2,0) -> 33000 | F11: 1 | G11: =VLOOKUP($B11,Master!$A$9:$B$16,2,FALSE) -> 1 | H11: =F11*G11 -> 1 | I11: =H11*$E11 -> 33000 | K11: 1 | L11: =VLOOKUP($B11,Master!$A$9:$B$16,2,FALSE) -> 1 | M11: =K11*L11 -> 1 | N11: =M11*$E11 -> 33000
A12: 3 | B12: Hosur 2 | C12: Gate In | D12: RFID Reader | E12: =VLOOKUP(D12,Master!$A$3:$B$6,2,0) -> 33000 | F12: 1 | G12: =VLOOKUP($B12,Master!$A$9:$B$16,2,FALSE) -> 1 | H12: =F12*G12 -> 1 | I12: =H12*$E12 -> 33000 | J12: =SUM(I12:I15) -> 172000 | K12: 1 | L12: =VLOOKUP($B12,Master!$A$9:$B$16,2,FALSE) -> 1 | M12: =K12*L12 -> 1 | N12: =M12*$E12 -> 33000 | O12: =SUM(N12:N15) -> 107000
B13: Hosur 2 | C13: Gate In | D13: ANPR Camera | E13: =VLOOKUP(D13,Master!$A$3:$B$6,2,0) -> 65000 | F13: 1 | G13: =VLOOKUP($B13,Master!$A$9:$B$16,2,FALSE) -> 1 | H13: =F13*G13 -> 1 | I13: =H13*$E13 -> 65000 | K13: 0 | L13: =VLOOKUP($B13,Master!$A$9:$B$16,2,FALSE) -> 1 | M13: =K13*L13 -> 0 | N13: =M13*$E13 -> 0
B14: Hosur 2 | C14: Gate In | D14: Tablet | E14: =VLOOKUP(D14,Master!$A$3:$B$6,2,0) -> 41000 | F14: 1 | G14: =VLOOKUP($B14,Master!$A$9:$B$16,2,FALSE) -> 1 | H14: =F14*G14 -> 1 | I14: =H14*$E14 -> 41000 | K14: 1 | L14: =VLOOKUP($B14,Master!$A$9:$B$16,2,FALSE) -> 1 | M14: =K14*L14 -> 1 | N14: =M14*$E14 -> 41000
B15: Hosur 2 | C15: Gate Out | D15: RFID Reader | E15: =VLOOKUP(D15,Master!$A$3:$B$6,2,0) -> 33000 | F15: 1 | G15: =VLOOKUP($B15,Master!$A$9:$B$16,2,FALSE) -> 1 | H15: =F15*G15 -> 1 | I15: =H15*$E15 -> 33000 | K15: 1 | L15: =VLOOKUP($B15,Master!$A$9:$B$16,2,FALSE) -> 1 | M15: =K15*L15 -> 1 | N15: =M15*$E15 -> 33000
A16: 4 | B16: Alwar | C16: Gate In | D16: RFID Reader | E16: =VLOOKUP(D16,Master!$A$3:$B$6,2,0) -> 33000 | F16: 1 | G16: =VLOOKUP($B16,Master!$A$9:$B$16,2,FALSE) -> 1 | H16: =F16*G16 -> 1 | I16: =H16*$E16 -> 33000 | J16: =SUM(I16:I19) -> 172000 | K16: 1 | L16: =VLOOKUP($B16,Master!$A$9:$B$16,2,FALSE) -> 1 | M16: =K16*L16 -> 1 | N16: =M16*$E16 -> 33000 | O16: =SUM(N16:N19) -> 107000
B17: Alwar | C17: Gate In | D17: ANPR Camera | E17: =VLOOKUP(D17,Master!$A$3:$B$6,2,0) -> 65000 | F17: 1 | G17: =VLOOKUP($B17,Master!$A$9:$B$16,2,FALSE) -> 1 | H17: =F17*G17 -> 1 | I17: =H17*$E17 -> 65000 | K17: 0 | L17: =VLOOKUP($B17,Master!$A$9:$B$16,2,FALSE) -> 1 | M17: =K17*L17 -> 0 | N17: =M17*$E17 -> 0
B18: Alwar | C18: Gate In | D18: Tablet | E18: =VLOOKUP(D18,Master!$A$3:$B$6,2,0) -> 41000 | F18: 1 | G18: =VLOOKUP($B18,Master!$A$9:$B$16,2,FALSE) -> 1 | H18: =F18*G18 -> 1 | I18: =H18*$E18 -> 41000 | K18: 1 | L18: =VLOOKUP($B18,Master!$A$9:$B$16,2,FALSE) -> 1 | M18: =K18*L18 -> 1 | N18: =M18*$E18 -> 41000
B19: Alwar | C19: Gate Out | D19: RFID Reader | E19: =VLOOKUP(D19,Master!$A$3:$B$6,2,0) -> 33000 | F19: 1 | G19: =VLOOKUP($B19,Master!$A$9:$B$16,2,FALSE) -> 1 | H19: =F19*G19 -> 1 | I19: =H19*$E19 -> 33000 | K19: 1 | L19: =VLOOKUP($B19,Master!$A$9:$B$16,2,FALSE) -> 1 | M19: =K19*L19 -> 1 | N19: =M19*$E19 -> 33000
A20: 5 | B20: Pantnagar | C20: Gate In | D20: RFID Reader | E20: =VLOOKUP(D20,Master!$A$3:$B$6,2,0) -> 33000 | F20: 1 | G20: =VLOOKUP($B20,Master!$A$9:$B$16,2,FALSE) -> 1 | H20: =F20*G20 -> 1 | I20: =H20*$E20 -> 33000 | J20: =SUM(I20:I23) -> 172000 | K20: 1 | L20: =VLOOKUP($B20,Master!$A$9:$B$16,2,FALSE) -> 1 | M20: =K20*L20 -> 1 | N20: =M20*$E20 -> 33000 | O20: =SUM(N20:N23) -> 107000
B21: Pantnagar | C21: Gate In | D21: ANPR Camera | E21: =VLOOKUP(D21,Master!$A$3:$B$6,2,0) -> 65000 | F21: 1 | G21: =VLOOKUP($B21,Master!$A$9:$B$16,2,FALSE) -> 1 | H21: =F21*G21 -> 1 | I21: =H21*$E21 -> 65000 | K21: 0 | L21: =VLOOKUP($B21,Master!$A$9:$B$16,2,FALSE) -> 1 | M21: =K21*L21 -> 0 | N21: =M21*$E21 -> 0
B22: Pantnagar | C22: Gate In | D22: Tablet | E22: =VLOOKUP(D22,Master!$A$3:$B$6,2,0) -> 41000 | F22: 1 | G22: =VLOOKUP($B22,Master!$A$9:$B$16,2,FALSE) -> 1 | H22: =F22*G22 -> 1 | I22: =H22*$E22 -> 41000 | K22: 1 | L22: =VLOOKUP($B22,Master!$A$9:$B$16,2,FALSE) -> 1 | M22: =K22*L22 -> 1 | N22: =M22*$E22 -> 41000
B23: Pantnagar | C23: Gate Out | D23: RFID Reader | E23: =VLOOKUP(D23,Master!$A$3:$B$6,2,0) -> 33000 | F23: 1 | G23: =VLOOKUP($B23,Master!$A$9:$B$16,2,FALSE) -> 1 | H23: =F23*G23 -> 1 | I23: =H23*$E23 -> 33000 | K23: 1 | L23: =VLOOKUP($B23,Master!$A$9:$B$16,2,FALSE) -> 1 | M23: =K23*L23 -> 1 | N23: =M23*$E23 -> 33000
A24: 6 | B24: Bhandara | C24: Gate In | D24: RFID Reader | E24: =VLOOKUP(D24,Master!$A$3:$B$6,2,0) -> 33000 | F24: 1 | G24: =VLOOKUP($B24,Master!$A$9:$B$16,2,FALSE) -> 1 | H24: =F24*G24 -> 1 | I24: =H24*$E24 -> 33000 | J24: =SUM(I24:I27) -> 172000 | K24: 1 | L24: =VLOOKUP($B24,Master!$A$9:$B$16,2,FALSE) -> 1 | M24: =K24*L24 -> 1 | N24: =M24*$E24 -> 33000 | O24: =SUM(N24:N27) -> 107000
B25: Bhandara | C25: Gate In | D25: ANPR Camera | E25: =VLOOKUP(D25,Master!$A$3:$B$6,2,0) -> 65000 | F25: 1 | G25: =VLOOKUP($B25,Master!$A$9:$B$16,2,FALSE) -> 1 | H25: =F25*G25 -> 1 | I25: =H25*$E25 -> 65000 | K25: 0 | L25: =VLOOKUP($B25,Master!$A$9:$B$16,2,FALSE) -> 1 | M25: =K25*L25 -> 0 | N25: =M25*$E25 -> 0
B26: Bhandara | C26: Gate In | D26: Tablet | E26: =VLOOKUP(D26,Master!$A$3:$B$6,2,0) -> 41000 | F26: 1 | G26: =VLOOKUP($B26,Master!$A$9:$B$16,2,FALSE) -> 1 | H26: =F26*G26 -> 1 | I26: =H26*$E26 -> 41000 | K26: 1 | L26: =VLOOKUP($B26,Master!$A$9:$B$16,2,FALSE) -> 1 | M26: =K26*L26 -> 1 | N26: =M26*$E26 -> 41000
B27: Bhandara | C27: Gate Out | D27: RFID Reader | E27: =VLOOKUP(D27,Master!$A$3:$B$6,2,0) -> 33000 | F27: 1 | G27: =VLOOKUP($B27,Master!$A$9:$B$16,2,FALSE) -> 1 | H27: =F27*G27 -> 1 | I27: =H27*$E27 -> 33000 | K27: 1 | L27: =VLOOKUP($B27,Master!$A$9:$B$16,2,FALSE) -> 1 | M27: =K27*L27 -> 1 | N27: =M27*$E27 -> 33000
A28: 7 | B28: ALFD Ennore | C28: Gate In | D28: RFID Reader | E28: =VLOOKUP(D28,Master!$A$3:$B$6,2,0) -> 33000 | F28: 1 | G28: =VLOOKUP($B28,Master!$A$9:$B$16,2,FALSE) -> 1 | H28: =F28*G28 -> 1 | I28: =H28*$E28 -> 33000 | J28: =SUM(I28:I31) -> 172000 | K28: 1 | L28: =VLOOKUP($B28,Master!$A$9:$B$16,2,FALSE) -> 1 | M28: =K28*L28 -> 1 | N28: =M28*$E28 -> 33000 | O28: =SUM(N28:N31) -> 107000
B29: ALFD Ennore | C29: Gate In | D29: ANPR Camera | E29: =VLOOKUP(D29,Master!$A$3:$B$6,2,0) -> 65000 | F29: 1 | G29: =VLOOKUP($B29,Master!$A$9:$B$16,2,FALSE) -> 1 | H29: =F29*G29 -> 1 | I29: =H29*$E29 -> 65000 | K29: 0 | L29: =VLOOKUP($B29,Master!$A$9:$B$16,2,FALSE) -> 1 | M29: =K29*L29 -> 0 | N29: =M29*$E29 -> 0
B30: ALFD Ennore | C30: Gate In | D30: Tablet | E30: =VLOOKUP(D30,Master!$A$3:$B$6,2,0) -> 41000 | F30: 1 | G30: =VLOOKUP($B30,Master!$A$9:$B$16,2,FALSE) -> 1 | H30: =F30*G30 -> 1 | I30: =H30*$E30 -> 41000 | K30: 1 | L30: =VLOOKUP($B30,Master!$A$9:$B$16,2,FALSE) -> 1 | M30: =K30*L30 -> 1 | N30: =M30*$E30 -> 41000
B31: ALFD Ennore | C31: Gate Out | D31: RFID Reader | E31: =VLOOKUP(D31,Master!$A$3:$B$6,2,0) -> 33000 | F31: 1 | G31: =VLOOKUP($B31,Master!$A$9:$B$16,2,FALSE) -> 1 | H31: =F31*G31 -> 1 | I31: =H31*$E31 -> 33000 | K31: 1 | L31: =VLOOKUP($B31,Master!$A$9:$B$16,2,FALSE) -> 1 | M31: =K31*L31 -> 1 | N31: =M31*$E31 -> 33000
A32: 8 | B32: ALFD Sriperumbudur | C32: Gate In | D32: RFID Reader | E32: =VLOOKUP(D32,Master!$A$3:$B$6,2,0) -> 33000 | F32: 1 | G32: =VLOOKUP($B32,Master!$A$9:$B$16,2,FALSE) -> 1 | H32: =F32*G32 -> 1 | I32: =H32*$E32 -> 33000 | J32: =SUM(I32:I35) -> 172000 | K32: 1 | L32: =VLOOKUP($B32,Master!$A$9:$B$16,2,FALSE) -> 1 | M32: =K32*L32 -> 1 | N32: =M32*$E32 -> 33000 | O32: =SUM(N32:N35) -> 107000
B33: ALFD Sriperumbudur | C33: Gate In | D33: ANPR Camera | E33: =VLOOKUP(D33,Master!$A$3:$B$6,2,0) -> 65000 | F33: 1 | G33: =VLOOKUP($B33,Master!$A$9:$B$16,2,FALSE) -> 1 | H33: =F33*G33 -> 1 | I33: =H33*$E33 -> 65000 | K33: 0 | L33: =VLOOKUP($B33,Master!$A$9:$B$16,2,FALSE) -> 1 | M33: =K33*L33 -> 0 | N33: =M33*$E33 -> 0
B34: ALFD Sriperumbudur | C34: Gate In | D34: Tablet | E34: =VLOOKUP(D34,Master!$A$3:$B$6,2,0) -> 41000 | F34: 1 | G34: =VLOOKUP($B34,Master!$A$9:$B$16,2,FALSE) -> 1 | H34: =F34*G34 -> 1 | I34: =H34*$E34 -> 41000 | K34: 1 | L34: =VLOOKUP($B34,Master!$A$9:$B$16,2,FALSE) -> 1 | M34: =K34*L34 -> 1 | N34: =M34*$E34 -> 41000
B35: ALFD Sriperumbudur | C35: Gate Out | D35: RFID Reader | E35: =VLOOKUP(D35,Master!$A$3:$B$6,2,0) -> 33000 | F35: 1 | G35: =VLOOKUP($B35,Master!$A$9:$B$16,2,FALSE) -> 1 | H35: =F35*G35 -> 1 | I35: =H35*$E35 -> 33000 | K35: 1 | L35: =VLOOKUP($B35,Master!$A$9:$B$16,2,FALSE) -> 1 | M35: =K35*L35 -> 1 | N35: =M35*$E35 -> 33000
H36: =SUM(H4:H35) -> 36 | I36: =SUM(I4:I35) -> 1548000 | J36: =SUM(J4:J35) -> 1548000 | M36: =SUM(M4:M35) -> 27 | N36: =SUM(N4:N35) -> 963000 | O36: =SUM(O4:O35) -> 963000

Sheet Master
A2: Equipment | B2: Cost
A3: RFID Reader | B3: 33000
A4: ANPR Camera | B4: 65000
A5: Tablet | B5: 41000
A6: AT Controller | B6: 12000
A8: Plant | B8: Qty
A9: Ennore | B9: 2
A10: Hosur 1 | B10: 1
A11: Hosur 2 | B11: 1
A12: Alwar | B12: 1
A13: Pantnagar | B13: 1
A14: Bhandara | B14: 1
A15: ALFD Ennore | B15: 1
A16: ALFD Sriperumbudur | B16: 1
A18: Location | B18: Qty
A19: Gate In | B19: 1
A20: Gate Out | B20: 1
