Workbook

Sheet Quotation 
E2: Quotation
B3: Address - Corporate HQ : Axestrack Software Solutions Pvt. Ltd., Office No.-19, 6th Floor, Jaipur Electronic Market, Near Riddhi Siddhi, Gopalpura bypass, Jaipur - 302018 , Rajasthan, India
B4: GSTIN | C4: 08AACCH0299P1Z1 | E4: QUOTE # | H4: DATE
B5: MSME No | C5: UDYAM-RJ-17-0051921 | E5: JKLC/KS/241111 | H5: =TODAY() -> 45964
B6: Contact | C6: Prem Singh Singhaniya | E6: Quote Validity : 15 days from submitted date | H6: Payment Terms : Monthly
B7: Phone | C7: +91 9004748848
B8: Email Id | C8: prem.singhaniya@axestrack.com
B10: CUSTOMER INFO
B11: Name | C11: ATUL LIMITED
B12: Location | C12: Mumbai
B13: Contact | E13: Phone
B14: Email Id
B16: DESCRIPTION OF WORK
B18: S.No. | C18: Items | F18: UOM | H18: price
B19: Opex Model - Per trip basis
B20: 1 | C20: GPS Based Track and Trace | F20: Per trip | H20: =summary!E2 -> 330.19091
B21: 2 | C21: GPS Based Track and Trace including tracking from the port | F21: Per trip | H21: =summary!E3 -> 419.76667
B22: 3 | C22: Reverse Logistics Charges | F22: Per trip | H22: =summary!E4 -> 85
B23: 4 | C23: ePOD | F23: Per trip | H23: =summary!E5 -> 12
B24: Capex model
B25: 4 | C25: Fixed GPS Non AIS 140(Capex Model)-Unlimited trip | F25: First Year Per Device | H25: =summary!E6 -> 2750
B26: 5 | C26: Fixed GPS Non AIS 140(Capex Model)-Unlimited trip | F26: Second Year Per Device | H26: =summary!E7 -> 1800
B27: ERP Integration
B28: 1 | C28: ERP Integration Cost | F28: One Time | H28: 100000
B29: Terms & Conditions
B30: * All prices mentioned above are exclusive of GST, with taxes applied. * Capex Model: Device ownership remains with ATUL Limited, and standard hardware warranty applies as provided by the OEM. * Opex Model: Device ownership remains with Axestrack. In case of theft and physical demage of devices during the transit and in custody of depo and port representatives, 1950+gst will be charged to ATUL Limited. * This quote is only for the outbound and inbound trips for valsad plant. * Manpower at the plant for gps installation is considered for 2 shifts * This quote does not include Control tower manpower for real time intevention on non compliances. * ATUL Limited will assist for reverse logistics of gps from depots and port * contract period is for 3 years * Payment Terms: Payment invoices to be raised on a monthly basis for opex model and one time yearly basis(advance) for capex model. Bills to be validated with 7 days from the date of bill generations. In case of payment delay beyond 30 days, overdue charges at 1.5% per month will be applicable.
B31: *
B32: * This quotation is based on the reverse logistics model and assumes ATUL Limited’s support in facilitating the retrieval of GPS devices from depots and ports.
B33: Thanks for business with Axestrack Software Solution Pvt. Ltd.

Sheet Reverse Logistics-Plastic seal
C2: Standard Model (Per Trip RL) | M2: No. of trips per day
C3: Inputs | G3: Per Trip Costings | K3: Commercial Values | M3: Loading points
C4: Trips Per Month | D4: 650 | G4: Capital | H4: =D15*E15/D4 -> 5.52 | I4: =H4/$H$14 -> 0.018535403 | K4: Duration (Months) | L4: 1 | M4: Loading duration
C5: Device Rotation Days | D5: 3 | G5: Interest | H5: =D15*E16/D4 -> 1.38 | I5: =H5/$H$14 -> 0.0046338509 | K5: Monthly CV | L5: =D4*(H14-H10) -> 193575.5
C6: Trips/Device/Month | D6: =30/D5 -> 10 | G6: Manpower | H6: =D16/D4 -> 161.53846 | I6: =H6/$H$14 -> 0.54242402 | K6: Annual CV | L6: =L5*12 -> 2322906
C7: Buffer Inventory | D7: 0.15 | F7: 38 | G7: SIM | H7: =D8*F7/D4 -> 4.37 | I7: =H7/$H$14 -> 0.014673861 | K7: TCV | L7: =L5*L4 -> 193575.5
C8: Device Quantity | D8: =D4/D6*(1+D7) -> 74.75 | E8: 1200 | G8: Server+License | H8: 5 | I8: =H8/$H$14 -> 0.016789315
C9: Field Technicians | D9: =3+4 -> 7 | E9: 15000 | G9: Consumables | H9: =10+(20*1.75) -> 45 | I9: =H9/$H$14 -> 0.15110383
C10: Control Tower Executives | D10: 0 | E10: 18000 | G10: Penalties | H10: 0 | I10: =H10/$H$14 -> 0
C11: RL Executives | D11: 0 | E11: 20000 | G11: RL Courier Exp | H11: 25 | I11: =H11/$H$14 -> 0.083946574
C12: Customer Success | D12: 0 | E12: 40000 | G12: Man Cost at Loading point/trip | H12: 0 | I12: =H12/$H$14 -> 0
C13: Project Manager | D13: 0 | E13: 40000 | G13: Net Margin | H13: 50 | I13: =H13/$H$14 -> 0.16789315
C14: Laptops | D14: 0 | E14: 25000 | G14: Net Quote | H14: =SUM(H4:H13) -> 297.80846 | I14: =H14/$H$14 -> 1
C15: Total Capital (Assets) | D15: =D8*E8+D14*E14 -> 89700 | E15: 0.04 | F15: Dep | G15: Net Margin | H15: =H13*D4 -> 32500
C16: Monthly Manpower | D16: =SUMPRODUCT(D9:D13,E9:E13) -> 105000 | E16: 0.01 | F16: Int | G16: Cash Gen (Ops) | H16: =(H12+H13)*D4 -> 32500
G17: Months Capital Offset | H17: =D15/(H16+H4*D4) -> 2.4855908

Sheet Reverse Logistics-Metal Seal
C2: Standard Model (Per Trip RL) | M2: No. of trips per day
C3: Inputs | G3: Per Trip Costings | K3: Commercial Values | M3: Loading points
C4: Trips Per Month | D4: 650 | G4: Capital | H4: =D15*E15/D4 -> 5.52 | I4: =H4/$H$14 -> 0.015870804 | K4: Duration (Months) | L4: 1 | M4: Loading duration
C5: Device Rotation Days | D5: 3 | G5: Interest | H5: =D15*E16/D4 -> 1.38 | I5: =H5/$H$14 -> 0.0039677011 | K5: Monthly CV | L5: =D4*(H14-H10) -> 226075.5
C6: Trips/Device/Month | D6: =30/D5 -> 10 | G6: Manpower | H6: =D16/D4 -> 161.53846 | I6: =H6/$H$14 -> 0.46444661 | K6: Annual CV | L6: =L5*12 -> 2712906
C7: Buffer Inventory | D7: 0.15 | F7: 38 | G7: SIM | H7: =D8*F7/D4 -> 4.37 | I7: =H7/$H$14 -> 0.012564387 | K7: TCV | L7: =L5*L4 -> 226075.5
C8: Device Quantity | D8: =D4/D6*(1+D7) -> 74.75 | E8: 1200 | G8: Server+License | H8: 5 | I8: =H8/$H$14 -> 0.014375728
C9: Field Technicians | D9: 7 | E9: 15000 | G9: Consumables | H9: =10+(20*5) -> 110 | I9: =H9/$H$14 -> 0.31626603
C10: Control Tower Executives | D10: 0 | E10: 18000 | G10: Penalties | H10: 0 | I10: =H10/$H$14 -> 0
C11: RL Executives | D11: 0 | E11: 20000 | G11: RL Courier Exp | H11: 10 | I11: =H11/$H$14 -> 0.028751457
C12: Customer Success | D12: 0 | E12: 40000 | G12: Man Cost at Loading point/trip | H12: 0 | I12: =H12/$H$14 -> 0
C13: Project Manager | D13: 0 | E13: 40000 | G13: Net Margin | H13: 50 | I13: =H13/$H$14 -> 0.14375728
C14: Laptops | D14: 0 | E14: 25000 | G14: Net Quote | H14: =SUM(H4:H13) -> 347.80846 | I14: =H14/$H$14 -> 1
C15: Total Capital (Assets) | D15: =D8*E8+D14*E14 -> 89700 | E15: 0.04 | F15: Dep | G15: Net Margin | H15: =H13*D4 -> 32500
C16: Monthly Manpower | D16: =SUMPRODUCT(D9:D13,E9:E13) -> 105000 | E16: 0.01 | F16: Int | G16: Cash Gen (Ops) | H16: =(H12+H13)*D4 -> 32500
G17: Months Capital Offset | H17: =D15/(H16+H4*D4) -> 2.4855908

Sheet Reverse Logistics
C2: Standard Model (Per Trip RL) | M2: No. of trips per day
C3: Inputs | G3: Per Trip Costings | K3: Commercial Values | M3: Loading points
C4: Trips Per Month | D4: 550 | G4: Capital | H4: =D15*E15/D4 -> 44.490909 | I4: =H4/$H$14 -> 0.10715771 | K4: Duration (Months) | L4: 1 | M4: Loading duration
C5: Device Rotation Days | D5: 15 | G5: Interest | H5: =D15*E16/D4 -> 11.122727 | I5: =H5/$H$14 -> 0.026789429 | K5: Monthly CV | L5: =D4*(H14-H10) -> 228355
C6: Trips/Device/Month | D6: =30/D5 -> 2 | G6: Manpower | H6: =D16/D4 -> 132.72727 | I6: =H6/$H$14 -> 0.31967769 | K6: Annual CV | L6: =L5*12 -> 2740260
C7: Buffer Inventory | D7: 0.15 | F7: 38 | G7: SIM | H7: =D8*F7/D4 -> 21.85 | I7: =H7/$H$14 -> 0.052626393 | K7: TCV | L7: =L5*L4 -> 228355
C8: Device Quantity | D8: =D4/D6*(1+D7) -> 316.25 | E8: 1800 | G8: Server+License | H8: 5 | I8: =H8/$H$14 -> 0.012042653
C9: Field Technicians | D9: =2 -> 2 | E9: 18000 | G9: Consumables | H9: 15 | I9: =H9/$H$14 -> 0.036127959
C10: Control Tower Executives | D10: 0.5 | E10: 18000 | G10: Penalties | H10: 0 | I10: =H10/$H$14 -> 0
C11: RL Executives | D11: 1 | E11: 20000 | G11: RL Courier Exp | H11: 85 | I11: =H11/$H$14 -> 0.2047251
C12: Customer Success | D12: 0.2 | E12: 40000 | G12: Man Cost at Loading point/trip | H12: 0 | I12: =H12/$H$14 -> 0
C13: Project Manager | D13: 0 | E13: 40000 | G13: Net Margin | H13: 100 | I13: =H13/$H$14 -> 0.24085306
C14: Laptops | D14: =SUM(D10:D12) -> 1.7 | E14: 25000 | G14: Net Quote | H14: =SUM(H4:H13) -> 415.19091 | I14: =H14/$H$14 -> 1
C15: Total Capital (Assets) | D15: =D8*E8+D14*E14 -> 611750 | E15: 0.04 | F15: Dep | G15: Net Margin | H15: =H13*D4 -> 55000
C16: Monthly Manpower | D16: =SUMPRODUCT(D9:D13,E9:E13) -> 73000 | E16: 0.01 | F16: Int | G16: Cash Gen (Ops) | H16: =(H12+H13)*D4 -> 55000
C17: ePOD | G17: Months Capital Offset | H17: =D15/(H16+H4*D4) -> 7.6978734
C21: This quote is only for valsad plant, monthly trips considered are 550
C22: Operations at plant concidered for 2 shifts
C23: This quote does not include manpower for Control tower
C24: AVG. transit days considered as 5 days
C25: ATUL will assist for reverse logistics of gps from depots and port

Sheet Reverse logistics with port
C2: Standard Model (Per Trip RL) | M2: No. of trips per day
C3: Inputs | G3: Per Trip Costings | K3: Commercial Values | M3: Loading points
C4: Trips Per Month | D4: 750 | G4: Capital | H4: =D15*E15/D4 -> 43.666667 | I4: =H4/$H$14 -> 0.086508618 | K4: Duration (Months) | L4: 1 | M4: Loading duration
C5: Device Rotation Days | D5: 15 | G5: Interest | H5: =D15*E16/D4 -> 10.916667 | I5: =H5/$H$14 -> 0.021627154 | K5: Monthly CV | L5: =D4*(H14-H10) -> 378575
C6: Trips/Device/Month | D6: =30/D5 -> 2 | G6: Manpower | H6: =D16/D4 -> 193.33333 | I6: =H6/$H$14 -> 0.38301525 | K6: Annual CV | L6: =L5*12 -> 4542900
C7: Buffer Inventory | D7: 0.15 | F7: 38 | G7: SIM | H7: =D8*F7/D4 -> 21.85 | I7: =H7/$H$14 -> 0.043287327 | K7: TCV | L7: =L5*L4 -> 378575
C8: Device Quantity | D8: =D4/D6*(1+D7) -> 431.25 | E8: 1800 | G8: Server+License | H8: 5 | I8: =H8/$H$14 -> 0.0099055669
C9: Field Technicians | D9: =6 -> 6 | E9: 18000 | G9: Consumables | H9: 15 | I9: =H9/$H$14 -> 0.029716701
C10: Control Tower Executives | D10: 0.5 | E10: 18000 | G10: Penalties | H10: 0 | I10: =H10/$H$14 -> 0
C11: RL Executives | D11: 1 | E11: 20000 | G11: RL Courier Exp | H11: 85 | I11: =H11/$H$14 -> 0.16839464
C12: Customer Success | D12: 0.2 | E12: 40000 | G12: Man Cost at Loading point/trip | H12: 0 | I12: =H12/$H$14 -> 0
C13: Project Manager | D13: 0 | E13: 40000 | G13: Net Margin | H13: 130 | I13: =H13/$H$14 -> 0.25754474
C14: Laptops | D14: =SUM(D10:D12) -> 1.7 | E14: 25000 | G14: Net Quote | H14: =SUM(H4:H13) -> 504.76667 | I14: =H14/$H$14 -> 1
C15: Total Capital (Assets) | D15: =D8*E8+D14*E14 -> 818750 | E15: 0.04 | F15: Dep | G15: Net Margin | H15: =H13*D4 -> 97500
C16: Monthly Manpower | D16: =SUMPRODUCT(D9:D13,E9:E13) -> 145000 | E16: 0.01 | F16: Int | G16: Cash Gen (Ops) | H16: =(H12+H13)*D4 -> 97500
C17: ePOD | G17: Months Capital Offset | H17: =D15/(H16+H4*D4) -> 6.2859885
C21: This quote is only for valsad plant, monthly trips considered are 550,
C22: Operations at plant concidered for 2 shifts
C23: This quote does not include manpower for Control tower
C24: Manpower considered for port.
C25: AVG. transit days considered as 5 days

Sheet summary
A1: S.No | B1: Description | C1: Model | D1: UOM | E1: Price
A2: 1 | B2: GPS Based Track and Trace | C2: Opex | D2: Per Trip | E2: ='Reverse Logistics'!H14-'Reverse Logistics'!H11 -> 330.19091
A3: 2 | B3: GPS Based Track and Trace including tracking from the port | C3: Opex | D3: Per Trip | E3: ='Reverse logistics with port'!H14-'Reverse logistics with port'!H11 -> 419.76667
A4: 3 | B4: Reverse Logistics Charges | C4: Opex | D4: Per Trip | E4: ='Reverse Logistics'!H11 -> 85
A5: 4 | B5: ePOD | C5: Opex | D5: Per Trip | E5: 12
A6: 5 | B6: Fixed GPS Non AIS 140(Capex Model)-Unlimited trip | C6: Capex | D6: First Year Per Device | E6: 2750
A7: 6 | B7: Fixed GPS Non AIS 140(Capex Model)-Unlimited trip | C7: Capex | D7: Second Year Per Device | E7: 1800

Sheet Trip count
A1: No | B1: Mines | C1: Monthly qty | D1: Total trips | E1: Daily trips | F1: Resources
A2: 1 | B2: Makardokra | C2: 591 | D2: =C2/30 -> 19.7 | E2: =D2/30 -> 0.65666667 | F2: 1
A3: 2 | B3: Gokul | C3: 1975 | D3: =C3/30 -> 65.833333 | E3: =D3/30 -> 2.1944444
A4: 3 | B4: Niljay | C4: 4108 | D4: =C4/30 -> 136.93333 | E4: =D4/30 -> 4.5644444 | F4: 1
A5: 4 | B5: Mungoli | C5: 5641 | D5: =C5/30 -> 188.03333 | E5: =D5/30 -> 6.2677778
A6: 5 | B6: Sasti | C6: 3024 | D6: =C6/30 -> 100.8 | E6: =D6/30 -> 3.36 | F6: 1 | G6: Try for half rate
A7: 6 | B7: Gauri | C7: 966 | D7: =C7/30 -> 32.2 | E7: =D7/30 -> 1.0733333
A8: 7 | B8: Inder Kamptee | C8: 2966 | D8: =C8/30 -> 98.866667 | E8: =D8/30 -> 3.2955556 | F8: Half rate

Sheet Reverse Logistics-Metal client
C2: Standard Model (Per Trip RL) | M2: No. of trips per day
C3: Inputs | G3: Per Trip Costings | K3: Commercial Values | M3: Loading points
C4: Trips Per Month | D4: 650 | G4: Capital | H4: =D15*E15/D4 -> 5.52 | I4: =H4/$H$14 -> 0.010764253 | K4: Duration (Months) | L4: 1 | M4: Loading duration
C5: Device Rotation Days | D5: 3 | G5: Interest | H5: =D15*E16/D4 -> 1.38 | I5: =H5/$H$14 -> 0.0026910632 | K5: Monthly CV | L5: =D4*(H14-H10) -> 333325.5
C6: Trips/Device/Month | D6: =30/D5 -> 10 | G6: Manpower | H6: =D16/D4 -> 161.53846 | I6: =H6/$H$14 -> 0.3150074 | K6: Annual CV | L6: =L5*12 -> 3999906
C7: Buffer Inventory | D7: 0.15 | F7: 38 | G7: SIM | H7: =D8*F7/D4 -> 4.37 | I7: =H7/$H$14 -> 0.0085217003 | K7: TCV | L7: =L5*L4 -> 333325.5
C8: Device Quantity | D8: =D4/D6*(1+D7) -> 74.75 | E8: 1200 | G8: Server+License | H8: 5 | I8: =H8/$H$14 -> 0.0097502291
C9: Field Technicians | D9: 7 | E9: 15000 | G9: Consumables | H9: =10+(20*10) -> 210 | I9: =H9/$H$14 -> 0.40950962
C10: Control Tower Executives | D10: 0 | E10: 18000 | G10: Penalties | H10: 0 | I10: =H10/$H$14 -> 0
C11: RL Executives | D11: 0 | E11: 20000 | G11: RL Courier Exp | H11: 25 | I11: =H11/$H$14 -> 0.048751146
C12: Customer Success | D12: 0 | E12: 40000 | G12: Man Cost at Loading point/trip | H12: 0 | I12: =H12/$H$14 -> 0
C13: Project Manager | D13: 0 | E13: 40000 | G13: Net Margin | H13: 100 | I13: =H13/$H$14 -> 0.19500458
C14: Laptops | D14: 0 | E14: 25000 | G14: Net Quote | H14: =SUM(H4:H13) -> 512.80846 | I14: =H14/$H$14 -> 1
C15: Total Capital (Assets) | D15: =D8*E8+D14*E14 -> 89700 | E15: 0.04 | F15: Dep | G15: Net Margin | H15: =H13*D4 -> 65000
C16: Monthly Manpower | D16: =SUMPRODUCT(D9:D13,E9:E13) -> 105000 | E16: 0.01 | F16: Int | G16: Cash Gen (Ops) | H16: =(H12+H13)*D4 -> 65000
G17: Months Capital Offset | H17: =D15/(H16+H4*D4) -> 1.3078089
C21: Quote to client | D21: 440

Sheet Fixed Installations
C2: Standard Model (Per Vehicle Per Month)
C3: Inputs | G3: Per Month Costings | K3: Commercial Values
C4: Vehicles | D4: 1000 | G4: Capital | H4: =D15*E15/D4 -> 369.25 | I4: =H4/$H$14 -> 0.38104329 | K4: Duration (Months) | L4: 48
G5: Interest | H5: =D15*E16/D4 -> 73.85 | I5: =H5/$H$14 -> 0.076208658 | K5: Monthly CV | L5: =D4*(H14-H10) -> 969050
C6: Contant(Not to be change) | D6: 1 | G6: Manpower | H6: =D16/D4 -> 100 | I6: =H6/$H$14 -> 0.10319385 | K6: Annual CV | L6: =L5*12 -> 11628600
C7: Buffer Inventory | D7: 0.05 | F7: 139 | G7: SIM | H7: =D8*F7/D4 -> 145.95 | I7: =H7/$H$14 -> 0.15061142 | K7: TCV | L7: =L5*L4 -> 46514400
C8: Device Quantity | D8: =D4/D6*(1+D7) -> 1050 | E8: 7000 | G8: Server+License | H8: 80 | I8: =H8/$H$14 -> 0.08255508
C9: Field Technicians | D9: 2 | E9: 20000 | G9: Consumables | H9: 0 | I9: =H9/$H$14 -> 0
C10: Control Tower Executives | D10: 0 | E10: 25000 | G10: Penalties | H10: 0 | I10: =H10/$H$14 -> 0
C11: RL Executives | D11: 0 | E11: 30000 | G11: RL Courier Exp | H11: 0 | I11: =H11/$H$14 -> 0
C12: Customer Success | D12: 1 | E12: 60000 | G12: Man+Dev Cost | H12: 0 | I12: =H12/$H$14 -> 0
C13: Project Manager | D13: 0 | E13: 40000 | G13: Net Margin | H13: 200 | I13: =H13/$H$14 -> 0.2063877 | L13: Concox | M13: 150 | O13: =M13*90 -> 13500
C14: Laptops | D14: =D13+D12+D10+D11 -> 1 | E14: 35000 | G14: Net Quote | H14: =SUM(H4:H13) -> 969.05 | I14: =H14/$H$14 -> 1 | L14: Howen | M14: 200 | O14: =M14*90 -> 18000
C15: Total Capital (Assets) | D15: =D8*E8+D14*E14 -> 7385000 | E15: 0.05 | F15: Dep | G15: Net Margin | H15: =H13*D4 -> 200000 | L15: Streamax | M15: 270 | O15: =M15*90 -> 24300
C16: Monthly Manpower | D16: =SUMPRODUCT(D9:D13,E9:E13) -> 100000 | E16: 0.01 | F16: Int | G16: Cash Gen (Ops) | H16: =(H12+H13)*D4 -> 200000
G17: Months Capital Offset | H17: =D15/(H16+H4*D4) -> 12.97321
H20: =D4*(H14-H8-H7-H6) -> 643100

Sheet Trips details
B1: Udaipur | J1: Sirohi
E2: 40
B3: Month | C3: Qty in KMT | D3: Qty in Ton | E3: Truck ton | F3: JKLC Nos. | G3: Delta | L3: 40
B4: Apr | C4: 14 | D4: =C4*1000 -> 14000 | E4: =D4/$E$2 -> 350 | F4: 350 | G4: =E4-F4 -> 0 | K4: MT/Month | L4: truck ton
B5: May | C5: 9 | D5: =C5*1000 -> 9000 | E5: =D5/$E$2 -> 225 | F5: 225 | G5: =E5-F5 -> 0 | J5: Coal Tonn | K5: 5000 | L5: =K5/$L$3 -> 125
B6: Jun | C6: 8 | D6: =C6*1000 -> 8000 | E6: =D6/$E$2 -> 200 | F6: 200 | G6: =E6-F6 -> 0
B7: Jul | C7: 12 | D7: =C7*1000 -> 12000 | E7: =D7/$E$2 -> 300 | F7: 300 | G7: =E7-F7 -> 0 | J7: Variance | K7: 3000 | L7: =K7/$L$3 -> 75
B8: Aug | C8: 8 | D8: =C8*1000 -> 8000 | E8: =D8/$E$2 -> 200 | F8: 200 | G8: =E8-F8 -> 0 | K8: 7000 | L8: =K8/$L$3 -> 175
B9: Sep | C9: 13 | D9: =C9*1000 -> 13000 | E9: =D9/$E$2 -> 325 | F9: 313 | G9: =E9-F9 -> 12 | K9: =AVERAGE(K7:K8) -> 5000 | L9: =K9/$L$3 -> 125
B10: Oct | C10: 20 | D10: =C10*1000 -> 20000 | E10: =D10/$E$2 -> 500 | F10: 500 | G10: =E10-F10 -> 0
B11: Nov | C11: 16 | D11: =C11*1000 -> 16000 | E11: =D11/$E$2 -> 400 | F11: 400 | G11: =E11-F11 -> 0
B12: Dec | C12: 18 | D12: =C12*1000 -> 18000 | E12: =D12/$E$2 -> 450 | F12: 450 | G12: =E12-F12 -> 0
B13: Jan | C13: 18 | D13: =C13*1000 -> 18000 | E13: =D13/$E$2 -> 450 | F13: 450 | G13: =E13-F13 -> 0
B14: Feb | C14: 20 | D14: =C14*1000 -> 20000 | E14: =D14/$E$2 -> 500 | F14: 500 | G14: =E14-F14 -> 0
B15: Mar | C15: 12 | D15: =C15*1000 -> 12000 | E15: =D15/$E$2 -> 300 | F15: 300 | G15: =E15-F15 -> 0
C16: =AVERAGE(C4:C15) -> 14 | D16: =AVERAGE(D4:D15) -> 14000 | E16: =AVERAGE(E4:E15) -> 350 | F16: =AVERAGE(F4:F15) -> 349 | G16: =AVERAGE(G4:G15) -> 1
F19: Total Trips | H19: =F16+L9 -> 474

Sheet Notes
B2: Sealing Business: 1. ~200 trucks sealed per day (24X7 operations). 2. Each sealing takes 5-8 minutes. Total of 12 seals per Truck. 2 people seal 1 truck 3. After every sealing 3 images of the truck are sent on the whatsapp group to HO. HO approves and then vehicle can leave. 3. Currently 32 technicials (Salary ~12-13k) and 8 Supervisors (25k CTC)..1 supervisor is overall incharge 4. Hiring of technicials is done through Newspaper / Local Consultancy or Supervisors 5. They have taken a parking space on rent (50k-1 lacs annual) + Rs. 10 per vehicle entry 6. Consumables at port: Seals, Tape, RFID Scanner (should be barcode scanner) 7. Staff had an instance of Strike which was resolved later on 8. Total 3 companies have sealing working in Gandhidham - UTCL, Zinc (HZL), Nuvoco 9. Nuvoco has started using a new sealing type (Wiring Sealing) which is more effective in preventing theft Other Business at Gandhidham: 1. 2 CS folks manage ...~55-60 customers and 2500 vehicles 2. 3 sales staff 3. Offer eLock, Fuel Sensor and AIS-140 (biggest customer Deepak Chemicals... 5100+GST..BSNL Cerififcation 250 extra) to transporters 4. Reverse logistics of Adani-Wilmar
B4: 1 | C4: Sealing a truck takes 15 minutes for a person
B5: 2 | C5: Parking Space for 50k - 1 Lac + 10 rs per vehicle

Sheet Llyods
C2: Standard Model (Per Trip RL) | M2: No. of trips per day
C3: Inputs | G3: Per Trip Costings | K3: Commercial Values | M3: Loading points
C4: Trips Per Month | D4: 450 | G4: Capital | H4: =D15*E15/D4 -> 35.342222 | I4: =H4/$H$14 -> 0.080630279 | K4: Duration (Months) | L4: 1 | M4: Loading duration
C5: Device Rotation Days | D5: 12 | G5: Interest | H5: =D15*E16/D4 -> 8.8355556 | I5: =H5/$H$14 -> 0.02015757 | K5: Monthly CV | L5: =D4*(H14-H10) -> 197246
C6: Trips/Device/Month | D6: =30/D5 -> 2.5 | G6: Manpower | H6: =D16/D4 -> 66.666667 | I6: =H6/$H$14 -> 0.15209434 | K6: Annual CV | L6: =L5*12 -> 2366952
C7: Buffer Inventory | D7: 0.15 | F7: 38 | G7: SIM | H7: =D8*F7/D4 -> 17.48 | I7: =H7/$H$14 -> 0.039879136 | K7: TCV | L7: =L5*L4 -> 197246
C8: Device Quantity | D8: =D4/D6*(1+D7) -> 207 | E8: 1800 | G8: Server+License | H8: 5 | I8: =H8/$H$14 -> 0.011407075
C9: Field Technicians | D9: 0 | E9: 18000 | G9: Consumables | H9: 85 | I9: =H9/$H$14 -> 0.19392028
C10: Control Tower Executives | D10: 0 | E10: 18000 | G10: Penalties | H10: 0 | I10: =H10/$H$14 -> 0
C11: RL Executives | D11: 0.5 | E11: 20000 | G11: RL Courier Exp | H11: 40 | I11: =H11/$H$14 -> 0.091256603
C12: Customer Success | D12: 0.5 | E12: 40000 | G12: Man Cost at Loading point/trip | H12: 80 | I12: =H12/$H$14 -> 0.18251321
C13: Project Manager | D13: 0 | E13: 40000 | G13: Net Margin | H13: 100 | I13: =H13/$H$14 -> 0.22814151
C14: Laptops | D14: 1 | E14: 25000 | G14: Net Quote | H14: =SUM(H4:H13) -> 438.32444 | I14: =H14/$H$14 -> 1
C15: Total Capital (Assets) | D15: =D8*E8+D14*E14 -> 397600 | E15: 0.04 | F15: Dep | G15: Net Margin | H15: =H13*D4 -> 45000
C16: Monthly Manpower | D16: =SUMPRODUCT(D9:D13,E9:E13) -> 30000 | E16: 0.01 | F16: Int | G16: Cash Gen (Ops) | H16: =(H12+H13)*D4 -> 81000
G17: Months Capital Offset | H17: =D15/(H16+H4*D4) -> 4.1030298
G20: 0.05
D21: Seals/ truck | E21: Seal cost | F21: Total | G21: Consumables+ margin
C22: Consumables | D22: 40 | E22: 12 | F22: =D22*E22 -> 480 | G22: =F22/(1-G20) -> 505.26316
D23: =D22*D4 -> 18000 | E23: `
C24: Wired metal seal grade A
