Workbook

Sheet Summary-3yr
A1: Sr No | B1: Details | C1: Type | D1: Price Full
A2: 1 | B2: Hardware | C2: One time | D2: =Commercials!K16 -> 403814.29
A3: 2 | B3: Implementation Cost | C3: One time | D3: =Commercials!K19 -> 237142.86 | G3: =SUM(D2:D4) -> 2962957.1
A4: 3 | B4: Project Management Cost | C4: For 3 Years | D4: =Commercials!K23 -> 2322000
A5: 4 | B5: AMC | C5: For 2 years | D5: =Commercials!K25 -> 140457.14

Sheet Quotation 
H1: Quotation
B2: Address - Corporate HQ : Axestrack Software Solutions Pvt. Ltd., Office No.-19, 6th Floor, Jaipur Electronic Market, Near Riddhi Siddhi, Gopalpura bypass, Jaipur - 302018 , Rajasthan, India
B3: GSTIN | F3: QUOTE # | H3: DATE
B4: MSME No
B5: Contact Person
B6: Phone | F6: Quote Validity : 15 days from submitted date
B7: Email Id
B9: CUSTOMER INFO
B10: Company Name
B11: Address
B12: Contact Person | F12: Phone
B13: Email Id
B15: DESCRIPTION OF WORK
B17: S.No. | C17: Year | E17: Description | G17: Type | I17: Amount | M17: S. No. | N17: Year | O17: Description | P17: Amount
B18: 1 | C18: Hardware Cost | E18: Hardware Cost | G18: One time | I18: =Commercials!K16 -> 403814.29 | M18: 1 | N18: First Year | O18: Hardware Cost, Installation,commissioning , training. Platform subscription & Support | P18: =Commercials!K20+Commercials!F21+Commercials!F22 -> 1414957.1
B19: 2 | C19: Implementation Cost | E19: Installation, Commissioning &Training | G19: One time | I19: =Commercials!K19 -> 237142.86 | M19: 2 | N19: Second Year | O19: Platform subscription & Support, AMC | P19: =Commercials!F21+Commercials!F22+(Commercials!K24/2) -> 844228.57
B20: 3 | C20: Subscription Fee Post Go-Live | E20: Platform Subscription + Support & Maintenance | G20: Monthly | I20: =(Commercials!F21+Commercials!F22)/12 -> 64500 | M20: 3 | N20: Third Year | O20: Platform subscription & Support, AMC | P20: =Commercials!F21+Commercials!F22+(Commercials!K24/2) -> 844228.57
B21: 4 | C21: AMC | E21: AMC from second year onwards | G21: Yearly | I21: =Commercials!K24/2 -> 70228.571 | M21: Total Project Cost | P21: =SUM(P18:P20) -> 3103414.3
B24: Terms & Conditions
B25: • All prices quoted in this proposal are in Indian Rupees (INR) and are exclusive of GST. Applicable taxes will be charged extra as per prevailing law. • Device ownership shall remain with the Client. • The above pricing doesnt involve integration with any ERP/ thrid party systems. To be charged seperately based on the efforts required. • The standard one-year hardware warranty, as per OEM guidelines, shall apply from the date of hardware delivery. Burnt, physically damaged, or tampered hardware is excluded from warranty and shall not be covered under AMC. Kindly refer to the attached Hardware Warranty T&C. • The minimum contract period shall be three (3) years from the date of deployment. • Internet connectivity, civil works (including trenching, power supply, LAN/Wi-Fi readiness, pole mounting, enclosures), UPS provisioning, and related site readiness shall remain in the Client’s scope, as outlined in the assumptions and dependencies section of the proposal. • AMC charges from the 2nd year onwards will be billed separately. Pricing and detailed AMC terms will be shared upon request. • Spares and accessory parts, if required, will be charged separately at prevailing rates. • The above costing remains valid for one (1) year from the date of proposal submission and includes the standard hardware warranty period. Payment Terms: • 100% of the hardware cost is payable upfront at project kickoff. • Payment for platform subscription, support, and maintenance will be on a monthly advance basis. • All invoices are payable within fifteen (15) days from the date of receipt (original or digitally signed). • Any delay in payment will attract an overdue charge of 1.5% per month or the maximum permissible under law, whichever is lower.
B26: Thanks for doing business with Axestrack Software Solution Pvt. Ltd.

Sheet Commercials
B2: Customer | D2: AM/NS Pune
B3: Date | D3: =TODAY() -> 45957
B4: Contract Year | D4: 3
B5: AMC Cost | D5: 0.2
B6: Hardware Transportation Cost | D6: 0.05
B7: Software Subscription cost per month Current | D7: 52000
B9: ERP Integration | D9: 0
F11: Total Equipments
B12: Model | C12: Items | D12: Details | E12: Type | F12: Unit Cost | G12: Nos. of years | H12: Total Cost to Axestrack for 3 years | I12: Margin | J12: Unit Price with Margin | K12: Cost for 3 Years
B13: One Time Cost | C13: Hardware Cost | D13: Hardware Cost | E13: One Time | F13: =BOQ!H11 -> 245800 | H13: =BOQ!H11 -> 245800 | I13: 0.3 | J13: =H13/(1-I13) -> 351142.86 | K13: =H13/(1-I13) -> 351142.86
D14: Spares | E14: One Time | H14: =F14*3 -> 0 | I14: 0.3 | J14: =H14/(1-I14) -> 0 | K14: =H14/(1-I14) -> 0
D15: Hardware Transportation cost | E15: One Time | F15: =F13*D6 -> 12290 | H15: =F15*3 -> 36870 | I15: 0.3 | J15: =H15/(1-I15) -> 52671.429 | K15: =H15/(1-I15) -> 52671.429
D16: Total Hardware Cost | H16: =SUM(H13:H15) -> 282670 | K16: =SUM(K13:K15) -> 403814.29
C17: Implementation Cost (Implementation+Hypercare) | D17: Installation, Training & Configuration | E17: One Time | F17: ='Manpower Cost New'!C38 -> 166000 | H17: =F17 -> 166000 | I17: 0.3 | J17: =H17/(1-I17) -> 237142.86 | K17: =H17/(1-I17) -> 237142.86
D18: ERP Integration | E18: One Time | F18: =D9 -> 0 | H18: =F18 -> 0 | J18: =H18/(1-I18) -> 0 | K18: =H18/(1-I18) -> 0
D19: Total Installation, Setup & API Development Cost | H19: =SUM(H17:H18) -> 166000 | K19: =SUM(K17:K18) -> 237142.86
G20: Total One Time Cost | H20: =H16+H19 -> 448670 | K20: =K16+K19 -> 640957.14
B21: Subscription Fee | C21: Project Management Cost | D21: Project Management, Support & Maintenance | E21: Per Year | F21: ='Manpower Cost New'!S8+('Manpower Cost New'!U26*3) -> 150000 | G21: =$D$4 -> 3 | H21: =G21*F21 -> 450000 | I21: 0 | J21: =(F21/(1-I21)) -> 150000 | K21: =H21/(1-I21) -> 450000
C22: Annual Subscription fee | D22: Platform Subscription Fee | E22: Per Year | F22: =D7*12 -> 624000 | G22: =$D$4 -> 3 | H22: =F22*G22 -> 1872000 | J22: =H22*I22 -> 0 | K22: =H22/(1-I22) -> 1872000
G23: Total Subscription & PMO Cost for 3 Years | H23: =SUM(H21:H22) -> 2322000 | K23: =SUM(K21:K22) -> 2322000
B24: AMC | C24: AMC | D24: AMC from 2nd Year onwards | E24: Per Year | F24: =SUM(H13:H14)*$D$5 -> 49160 | G24: =G21-1 -> 2 | H24: =F24*G24 -> 98320 | I24: 0.3 | J24: =(F24/(1-I24)) -> 70228.571 | K24: =H24/(1-I24) -> 140457.14
C25: AMC for 2 years | G25: AMC for 2 years | H25: =SUM(H24) -> 98320 | K25: =SUM(K24) -> 140457.14
G26: Total Cost of the Project for 3.5 Years | H26: =H20+H25+H23 -> 2868990 | I26: =1-H26/K26 -> 0.075537542 | K26: =SUM(K20+K23+K25) -> 3103414.3

Sheet BOQ
A1: Sr No | B1: Stage | C1: Hardware | D1: Unit Price | E1: Quantity per Check Point | F1: Checkpoints | G1: Hardware Count | H1: Total
A2: 1 | B2: Parking IN | C2: RFID Reader | D2: =VLOOKUP(C2,Master!$B$1:$C$25,2,FALSE) -> 27000 | E2: 1 | F2: 1 | G2: =E2*F2 -> 1 | H2: =D2*E2*F2 -> 27000
C3: Traffic Light | D3: =VLOOKUP(C3,Master!$B$1:$C$25,2,FALSE) -> 9200 | E3: 1 | F3: 1 | G3: =E3*F3 -> 1 | H3: =D3*E3*F3 -> 9200
C4: ANPR Camera | D4: =VLOOKUP(C4,Master!$B$1:$C$25,2,FALSE) -> 66000 | E4: 1 | F4: 1 | G4: =E4*F4 -> 1 | H4: =D4*E4*F4 -> 66000
C5: AT Controller | D5: =VLOOKUP(C5,Master!$B$1:$C$25,2,FALSE) -> 18400 | E5: 1 | F5: 1 | G5: =E5*F5 -> 1 | H5: =D5*E5*F5 -> 18400
A6: 3 | B6: Parking OUT | C6: RFID Reader | D6: =VLOOKUP(C6,Master!$B$1:$C$25,2,FALSE) -> 27000 | E6: 1 | F6: 1 | G6: =E6*F6 -> 1 | H6: =D6*E6*F6 -> 27000
C7: Traffic Light | D7: =VLOOKUP(C7,Master!$B$1:$C$25,2,FALSE) -> 9200 | E7: 1 | F7: 1 | G7: =E7*F7 -> 1 | H7: =D7*E7*F7 -> 9200
A8: 4 | B8: Gate IN | C8: RFID Reader | D8: =VLOOKUP(C8,Master!$B$1:$C$25,2,FALSE) -> 27000 | E8: 1 | F8: 1 | G8: =E8*F8 -> 1 | H8: =D8*E8*F8 -> 27000
C9: Breath Analyzer | D9: =VLOOKUP(C9,Master!$B$1:$C$25,2,FALSE) -> 35000 | E9: 1 | F9: 1 | G9: =E9*F9 -> 1 | H9: =D9*E9*F9 -> 35000
A10: 5 | B10: Gate OUT | C10: RFID Reader | D10: =VLOOKUP(C10,Master!$B$1:$C$25,2,FALSE) -> 27000 | E10: 1 | F10: 1 | G10: =E10*F10 -> 1 | H10: =D10*E10*F10 -> 27000
A11: Total | G11: =SUM(G2:G10) -> 9 | H11: =SUM(H2:H10) -> 245800

Sheet Sheet2
A1: Hardware | B1: Qty | C1: Price | D1: Total
A2: RFID Reader | B2: 4 | C2: =VLOOKUP(A2,Master!$B$2:$C$25,2,0) -> 27000 | D2: =B2*C2 -> 108000
A3: Traffic Light | B3: 1 | C3: =VLOOKUP(A3,Master!$B$1:$C$25,2,0) -> 9200 | D3: =B3*C3 -> 9200
A4: ANPR Camera | B4: 1 | C4: =VLOOKUP(A4,Master!$B$1:$C$25,2,0) -> 66000 | D4: =B4*C4 -> 66000
A5: Tablet (Industrial Grade) | B5: 2 | C5: =VLOOKUP(A5,Master!$B$2:$C$25,2,0) -> 47000 | D5: =B5*C5 -> 94000
D6: =SUM(D2:D5) -> 277200

Sheet Manpower Cost New
B2: Implementation | L2: Hypercare 3 months | N2: Onsite Manpower
B3: M1 to M6 | L3: M7 & M9 | N3: M7 to M48
B4: Installation, Training & Configuration Cost for phase 1 (a) | L4: Hypercare (a) (M7 to M9) | N4: Onsite Manpower, Support & Maintenance Cost (b) from M7 to M42
B5: Type of Manpower | C5: Count per shift | D5: Nos. of shifts | E5: Cost per Resource per month | F5: Duration in Months | G5: Total | L5: Type of Manpower | N5: Type of Manpower | O5: Count per shift | P5: Nos. of shifts | Q5: Cost per Resource per month | R5: Duration in Months | S5: Total
B6: PM | C6: 0 | D6: 1 | E6: =70000+20000 -> 90000 | F6: 0 | G6: =C6*D6*E6*F6 -> 0 | N6: Sr. CS (Offshore) | O6: 0.25 | P6: 1 | Q6: 50000 | R6: 12 | S6: =O6*P6*Q6*R6 -> 150000
B7: Hardware Engineers | C7: 1 | D7: 1 | E7: 40000 | F7: 1 | G7: =C7*D7*E7*F7 -> 40000 | L7: PM | N7: Support Engineers (CPL) | O7: 0 | P7: 0 | Q7: 40000 | R7: 12 | S7: =O7*P7*Q7*R7 -> 0
B8: Software Engineers | C8: 1 | D8: 1 | E8: 65000 | F8: 1 | G8: =C8*D8*E8*F8 -> 65000 | L8: Hardware Engineers | O8: =SUM(O6:O7) -> 0.25 | R8: Total | S8: =SUM(S6:S7) -> 150000
C9: =C6*D6+C7*D7+C8*D8 -> 2 | F9: Total (A) | G9: =SUM(G6:G8) -> 105000
L10: Software Engineers (Offshore)
B14: Current Equipments | C14: Count | D14: Productivity per resource | E14: Resources Required | I14: Planned Equipments | J14: Count
B15: Machines | C15: =SUM(Master!B41) -> 0 | D15: 6 | E15: =ROUND(C15/D15,0) -> 0 | I15: Machines | J15: =SUM(Master!C41) -> 0
B16: Gate Lanes | C16: =SUM(Master!B44:B55) -> 0 | D16: 7 | E16: =ROUND(C16/D16,0) -> 0 | I16: Gate Lanes | J16: =SUM(Master!C44:C55) -> 0
B17: Vehicles | C17: =SUM(Master!#REF!) -> #REF! | D17: 120 | E17: =ROUND(C17/D17,0) -> #REF! | I17: Vehicles | J17: =SUM(Master!#REF!) -> #REF!
D18: Onsite | E18: =SUM(E15:E17) -> #REF!
D19: MIS | E19: =ROUND(E18/8,0) -> #REF!
D20: Total | E20: =E18+E19 -> #REF!
B22: Travel & Lodging | L22: Onsite Manpower (b) (M7 to M9) | N22: Travel & Lodging for Support
B23: Type of Manpower | C23: Count | D23: Travel Allowance | E23: Travel Cost | F23: Stay Cost per Day | G23: Days per trip | H23: Frequency | I23: Total | L23: Type of Manpower | N23: Type of Manpower | O23: Type | P23: Travel Allowance | Q23: Travel Cost | R23: Stay Cost per Day | S23: Days per trip | T23: Frequency (Annually) | U23: Total
B24: PM/Seniors | C24: 1 | D24: 1000 | E24: 20000 | F24: 2500 | G24: 2 | H24: 0 | I24: =((H24*G24*D24)+(E24*H24)+(F24*G24*H24))*C24 -> 0 | L24: PM/ Sr. CS (Onsite) | N24: Project Manager | O24: Per Year | P24: 1500 | Q24: 20000 | R24: 4500 | S24: 2 | T24: 0 | U24: =(T24*S24*P24)+(Q24*T24)+(R24*S24*T24) -> 0
B25: Hardware Engineers | C25: 1 | D25: 1000 | E25: 20000 | F25: 0 | G25: 1 | H25: 1 | I25: =((H25*G25*D25)+(E25*H25)+(F25*G25*H25))*C25 -> 21000 | L25: Support Engineers (Onsite) | N25: Misc Travel | O25: Per Year | P25: 1500 | Q25: 20000 | R25: 4500 | S25: 2 | T25: 0 | U25: =(T25*S25*P25)+(Q25*T25)+(R25*S25*T25) -> 0
B26: Software Engineers | C26: 1 | D26: 1000 | E26: 20000 | F26: 0 | G26: 1 | H26: 0 | I26: =((H26*G26*D26)+(E26*H26)+(F26*G26*H26))*C26 -> 0 | L26: MIS Support (Offshore) | T26: Total | U26: =SUM(U24:U25) -> 0
H27: Total (B) | I27: =SUM(I24:I26) -> 21000
G29: Rent | H29: month | I29: Total
F30: Per month rent | G30: 40000 | H30: =F7 -> 1 | I30: =G30*H30 -> 40000
H31: Total (C) | I31: =SUM(I30:I30) -> 40000
H33: Total (B+C) | I33: =I31+I27 -> 61000
B38: Total Implementation Cost (M1 to M6) (A+B+C) | C38: =G9+I33 -> 166000 | N38: Live Project Management | O38: =(#REF!+#REF!+#REF!)+S8+(U26*3.5) -> #REF!
N39: (Travel+Lodging for Support considered for 3 years)
O41: =O38/2 -> #REF!

Sheet Master
B1: Hardware | C1: Price
B2: RFID Reader | C2: 27000 | D2: =C2/(1-0.25) -> 36000
B3: ANPR Camera | C3: 66000 | D3: =C3/(1-0.25) -> 88000
B4: Handheld RFID Reader | C4: 66000 | D4: =C4/(1-0.25) -> 88000
B5: RFID tags | C5: 30 | D5: =C5/(1-0.25) -> 40
B6: Boom Barrier | C6: 105200 | D6: =C6/(1-0.25) -> 140266.67
B7: PA System 8 horn | C7: 60000 | D7: =C7/(1-0.25) -> 80000
B8: LED Display-XXL | C8: 180000 | D8: =C8/(1-0.25) -> 240000
B9: AT Controller | C9: 18400 | D9: =C9/(1-0.25) -> 24533.333
B10: LED Display-2 Line | C10: 17500 | D10: =C10/(1-0.25) -> 23333.333
B11: LED Display-1 Line | C11: 12000 | D11: =C11/(1-0.25) -> 16000
B12: Tablet (Industrial Grade) | C12: 47000 | D12: =C12/(1-0.25) -> 62666.667
B13: AT Positioning Sensor | C13: 6500 | D13: =C13/(1-0.25) -> 8666.6667
... B19: Desktop | C19: 70000 | D19: =C19/(1-0.25) -> 93333.333
B20: Biometric | C20: 36000
B21: Breath Analyzer | C21: 35000
B22: Kiosk Cabin | C22: 150000
B23: Full Height Turnstile | C23: 450000
B24: 8 Port POE | C24: 4800
B25: Laser Printer | C25: 30000
