Workbook

Sheet Commercials Full
B2: Customer | D2: AM/NS Pune
B3: Date | D3: =TODAY() -> 45936
B4: Contract Year | D4: 3
B5: AMC Cost | D5: 0.23
B6: Hardware Transportation Cost | D6: 0.05
B7: Software Subscription cost per month Current | D7: 80000
B9: ERP Integration | D9: 200000
F11: Total Equipments
B12: Model | C12: Items | D12: Details | E12: Type | F12: Unit Cost | G12: Nos. of years | H12: Total Cost to Axestrack for 3 years | I12: Margin | J12: Unit Price with Margin | K12: Cost for 3 Years
B13: One Time Cost | C13: Hardware Cost | D13: Hardware Cost | E13: One Time | F13: ='Hardware List'!F9 -> 479200 | H13: ='Hardware List'!F9 -> 479200 | I13: 0.3 | J13: =H13/(1-I13) -> 684571.43 | K13: =H13/(1-I13) -> 684571.43
D14: Spares | E14: One Time | F14: ='Hardware List'!G9 -> 0 | H14: ='Hardware List'!G9 -> 0 | I14: 0.3 | J14: =H14/(1-I14) -> 0 | K14: =H14/(1-I14) -> 0
D15: Hardware Transportation cost | E15: One Time | F15: ='Hardware List'!H9*D6 -> 23960.05 | H15: =(SUM(H13:H14)*$D$6) -> 23960 | I15: 0.3 | J15: =H15/(1-I15) -> 34228.571 | K15: =H15/(1-I15) -> 34228.571
D16: Total Hardware Cost | H16: =SUM(H13:H15) -> 503160 | K16: =SUM(K13:K15) -> 718800
C17: Implementation Cost (Implementation+Hypercare) | D17: Installation, Training & Configuration | E17: One Time | F17: ='Manpower Cost New'!C38 -> 205500 | H17: =F17 -> 205500 | I17: 0.3 | J17: =H17/(1-I17) -> 293571.43 | K17: =H17/(1-I17) -> 293571.43
D18: ERP & Weighbridge Integration | E18: One Time | F18: =D9 -> 200000 | H18: =F18 -> 200000 | I18: 0 | J18: =H18/(1-I18) -> 200000 | K18: =H18/(1-I18) -> 200000
D19: Total Installation, Setup & API Development Cost | H19: =SUM(H17:H18) -> 405500 | K19: =SUM(K17:K18) -> 493571.43
G20: Total One Time Cost | H20: =H16+H19 -> 908660 | K20: =K16+K19 -> 1212371.4
B21: Subscription Fee | C21: Project Management Cost | D21: Project Management, Support & Maintenance | E21: Per Year | F21: ='Manpower Cost New'!S8+('Manpower Cost New'!U26*3) -> 126000 | G21: =$D$4 -> 3 | H21: =F21*G21 -> 378000 | I21: 0.3 | J21: =H21/(1-I21) -> 540000 | K21: =H21/(1-I21) -> 540000
C22: Annual Subscription fee | D22: Platform Subscription Fee | E22: Per Year | F22: =D7*12 -> 960000 | G22: =$D$4 -> 3 | H22: =F22*G22 -> 2880000 | J22: 0 | K22: =H22/(1-I22) -> 2880000
G23: Total Subscription & PMO Cost for 3 Years | H23: =SUM(H21:H22) -> 3258000 | K23: =SUM(K21:K22) -> 3420000
B24: AMC | C24: AMC | D24: AMC from 2nd Year onwards | E24: Per Year | F24: =SUM(H13:H14)*$D$5 -> 110216 | G24: =G21-1 -> 2 | H24: =F24*G24 -> 220432 | I24: 0.3 | J24: =H24/(1-I24) -> 314902.86 | K24: =H24/(1-I24) -> 314902.86
C25: AMC for 2 years | G25: AMC for 2 years | H25: =SUM(H24) -> 220432 | K25: =SUM(K24) -> 314902.86
G26: Total Cost of the Project | H26: =H20+H25+H23 -> 4387092 | I26: =1-H26/K26 -> 0.11323049 | K26: =SUM(K20+K23+K25) -> 4947274.3
D27: API track n trace | E27: 135
D28: AT GPS | E28: 235

Sheet Summary
A1: Sr No | B1: Details | C1: Type | D1: Price
A2: 1 | B2: Hardware | C2: One time | D2: ='Commercials Full'!K16 -> 718800
A3: 2 | B3: Implementation Cost | C3: One time | D3: ='Commercials Full'!K19 -> 493571.43
A4: 3 | B4: Project Management Cost | C4: For 3 Years | D4: ='Commercials Full'!K23 -> 3420000
A5: 4 | B5: AMC | C5: For 2 years | D5: ='Commercials Full'!K25 -> 314902.86
B6: Total | D6: =SUM(D2:D5) -> 4947274.3

Sheet BOQ
A1: Sr No | B1: Stage | C1: Hardware | D1: Unit Price | E1: Quantity per Check Point | F1: Checkpoints | G1: Hardware Count | H1: Total | I1: Remarks
A2: 1 | B2: Gate IN | C2: RFID Reader | D2: =VLOOKUP(C2,Master!$B$1:$C$25,2,FALSE) -> 27000 | E2: 1 | F2: 1 | G2: =E2*F2 -> 1 | H2: =D2*E2*F2 -> 27000
C3: Handheld RFID Reader | D3: =VLOOKUP(C3,Master!$B$1:$C$25,2,FALSE) -> 66000 | E3: 1 | F3: 1 | G3: =E3*F3 -> 1 | H3: =D3*E3*F3 -> 66000
C4: Boom Barrier | D4: =VLOOKUP(C4,Master!$B$1:$C$25,2,FALSE) -> 105200 | E4: 1 | F4: 1 | G4: =E4*F4 -> 1 | H4: =D4*E4*F4 -> 105200
C5: ANPR Camera | D5: =VLOOKUP(C5,Master!$B$1:$C$25,2,FALSE) -> 65000 | E5: 1 | F5: 1 | G5: =E5*F5 -> 1 | H5: =D5*E5*F5 -> 65000
C6: AT Controller | E6: 1 | F6: 1 | G6: 1
C7: Traffic Light | D7: =VLOOKUP(C7,Master!$B$1:$C$25,2,FALSE) -> 9200 | E7: 1 | F7: 1 | G7: =E7*F7 -> 1 | H7: =D7*E7*F7 -> 9200
A8: 2 | B8: Gate OUT | C8: RFID Reader | D8: =VLOOKUP(C8,Master!$B$1:$C$25,2,FALSE) -> 27000 | E8: 1 | F8: 1 | G8: =E8*F8 -> 1 | H8: =D8*E8*F8 -> 27000
C9: Boom Barrier | D9: =VLOOKUP(C9,Master!$B$1:$C$25,2,FALSE) -> 105200 | E9: 1 | F9: 1 | G9: =E9*F9 -> 1 | H9: =D9*E9*F9 -> 105200
C10: Traffic Light | E10: 1 | F10: 1 | G10: =E10*F10 -> 1
C11: Tablet (Industrial Grade) | D11: =VLOOKUP(C11,Master!$B$1:$C$25,2,FALSE) -> 47000 | E11: 1 | F11: 1 | G11: =E11*F11 -> 1 | H11: =D11*E11*F11 -> 47000
A12: Total | E12: 10 | G12: =SUM(G2:G11) -> 10 | H12: =SUM(H2:H11) -> 451600

Sheet Sheet2
A1: Hardware | B1: Qty | C1: Price | D1: Total
A2: RFID Reader | B2: 2 | C2: =VLOOKUP(A2,Master!$B$2:$C$25,2,0) -> 27000 | D2: =B2*C2 -> 54000
A3: Boom Barrier | B3: 2 | C3: =VLOOKUP(A3,Master!$B$2:$C$25,2,0) -> 105200 | D3: =B3*C3 -> 210400
A4: Traffic Light | B4: 2 | C4: =VLOOKUP(A4,Master!$B$1:$C$25,2,0) -> 9200 | D4: =B4*C4 -> 18400
A5: ANPR Camera | B5: 1 | C5: =VLOOKUP(A5,Master!$B$1:$C$25,2,0) -> 65000 | D5: =B5*C5 -> 65000
A6: Tablet (Industrial Grade) | B6: 2 | C6: =VLOOKUP(A6,Master!$B$2:$C$25,2,0) -> 47000 | D6: =B6*C6 -> 94000
D7: =SUM(D2:D6) -> 441800

Sheet Manpower Cost New
B2: Implementation | L2: Hypercare 3 months | N2: Onsite Manpower
B3: M1 to M6 | L3: M7 & M9 | N3: M7 to M48
B4: Installation, Training & Configuration Cost for phase 1 (a) | L4: Hypercare (a) (M7 to M9) | N4: Onsite Manpower, Support & Maintenance Cost (b) from M7 to M42
B5: Type of Manpower | C5: Count per shift | D5: Nos. of shifts | E5: Cost per Resource per month | F5: Duration in Months | G5: Total | L5: Type of Manpower | N5: Type of Manpower | O5: Count per shift | P5: Nos. of shifts | Q5: Cost per Resource per month | R5: Duration in Months | S5: Total
B6: PM | C6: 0 | D6: 1 | E6: =70000+20000 -> 90000 | F6: 0.8 | G6: =C6*D6*E6*F6 -> 0 | N6: Sr. CS (Offshore) | O6: 0.15 | P6: 1 | Q6: 70000 | R6: 12 | S6: =O6*P6*Q6*R6 -> 126000
B7: Hardware Engineers | C7: 2 | D7: 1 | E7: =40000+20000 -> 60000 | F7: 0.5 | G7: =C7*D7*E7*F7 -> 60000 | L7: PM | N7: Support Engineers (CPL) | O7: 0 | P7: 1 | Q7: 40000 | R7: 36 | S7: =O7*P7*Q7*R7 -> 0
B8: Software Engineers | C8: 1 | D8: 1 | E8: =65000+20000 -> 85000 | F8: 0.5 | G8: =C8*D8*E8*F8 -> 42500 | L8: Hardware Engineers | O8: =SUM(O6:O7) -> 0.15 | R8: Total | S8: =SUM(S6:S7) -> 126000
C9: =C6*D6+C7*D7+C8*D8 -> 3 | F9: Total (A) | G9: =SUM(G6:G8) -> 102500
L10: Software Engineers (Offshore)
B14: Current Equipments | C14: Count | D14: Productivity per resource | E14: Resources Required | I14: Planned Equipments | J14: Count
B15: Machines | C15: =SUM(Master!B41) -> 0 | D15: 6 | E15: =ROUND(C15/D15,0) -> 0 | I15: Machines | J15: =SUM(Master!C41) -> 0
B16: Gate Lanes | C16: =SUM(Master!B44:B55) -> 0 | D16: 7 | E16: =ROUND(C16/D16,0) -> 0 | I16: Gate Lanes | J16: =SUM(Master!C44:C55) -> 0
B17: Vehicles | C17: =SUM(Master!#REF!) -> #REF! | D17: 120 | E17: =ROUND(C17/D17,0) -> #REF! | I17: Vehicles | J17: =SUM(Master!#REF!) -> #REF!
D18: Onsite | E18: =SUM(E15:E17) -> #REF!
D19: MIS | E19: =ROUND(E18/8,0) -> #REF!
D20: Total | E20: =E18+E19 -> #REF!
B22: Travel & Lodging | L22: Onsite Manpower (b) (M7 to M9)
B23: Type of Manpower | C23: Count | D23: Travel Allowance | E23: Travel Cost | F23: Stay Cost per Day | G23: Days per trip | H23: Frequency | I23: Total | L23: Type of Manpower
B24: PM/Seniors | C24: 0 | D24: 1000 | E24: 20000 | F24: 2500 | G24: 5 | H24: 2 | I24: =((H24*G24*D24)+(E24*H24)+(F24*G24*H24))*C24 -> 0 | L24: PM/ Sr. CS (Onsite)
B25: Hardware Engineers | C25: 2 | D25: 1000 | E25: 20000 | F25: 0 | G25: 1 | H25: 1 | I25: =((H25*G25*D25)+(E25*H25)+(F25*G25*H25))*C25 -> 42000 | L25: Support Engineers (Onsite)
B26: Software Engineers | C26: 1 | D26: 1000 | E26: 20000 | F26: 0 | G26: 1 | H26: 1 | I26: =((H26*G26*D26)+(E26*H26)+(F26*G26*H26))*C26 -> 21000 | L26: MIS Support (Offshore)
H27: Total (B) | I27: =SUM(I24:I26) -> 63000
G29: Rent | H29: month | I29: Total
F30: Per month rent | G30: 40000 | H30: 1 | I30: =G30*H30 -> 40000
F31: Kitchen | G31: 40000 | H31: 0 | I31: =G31*H31 -> 0
H32: Total (C) | I32: =SUM(I30:I31) -> 40000
H34: Total (B+C) | I34: =I32+I27 -> 103000
B38: Total Implementation Cost (M1 to M6) (A+B+C) | C38: =G9+I34 -> 205500 | N38: Live Project Management | O38: =(#REF!+#REF!+#REF!)+S8+(U26*3.5) -> #REF!
N39: (Travel+Lodging for Support considered for 3 years)
O41: =O38/2 -> #REF!

Sheet Hardware List
A1: Hardware | B1: Price | C1: Hardware Count | D1: Spares (10%) | E1: Total Count | F1: Hardware Cost | G1: Spare Cost | H1: Total Cost- One Plant
A2: =Master!B2 -> RFID Reader | B2: =VLOOKUP(A2,Master!B:C,2,0) -> 27000 | C2: =SUMIF(BOQ!$C$2:$G$11,'Hardware List'!A2,BOQ!$G$2:$G$11) -> 2 | D2: =C2*10% -> 0.2 | E2: =C2+D2 -> 2.2 | F2: =C2*B2 -> 54000 | G2: 0 | H2: =F2+G2 -> 54000 | I2: =B2/(1-30%) -> 38571.429
A3: =Master!B3 -> ANPR Camera | B3: =VLOOKUP(A3,Master!B:C,2,0) -> 65000 | C3: =SUMIF(BOQ!$C$2:$G$11,'Hardware List'!A3,BOQ!$G$2:$G$11) -> 1 | D3: =C3*10% -> 0.1 | E3: =C3+D3 -> 1.1 | F3: =C3*B3 -> 65000 | G3: 0 | H3: =F3+G3 -> 65000 | I3: =B3/(1-30%) -> 92857.143
A4: =Master!B4 -> Handheld RFID Reader | B4: =VLOOKUP(A4,Master!B:C,2,0) -> 66000 | C4: =SUMIF(BOQ!$C$2:$G$11,'Hardware List'!A4,BOQ!$G$2:$G$11) -> 1 | D4: 0 | E4: =C4+D4 -> 1 | F4: =C4*B4 -> 66000 | G4: 0 | H4: =F4+G4 -> 66000 | I4: =B4/(1-30%) -> 94285.714
A5: =Master!B6 -> Boom Barrier | B5: =VLOOKUP(A5,Master!B:C,2,0) -> 105200 | C5: =SUMIF(BOQ!$C$2:$G$11,'Hardware List'!A5,BOQ!$G$2:$G$11) -> 2 | D5: =C5*10% -> 0.2 | E5: =C5+D5 -> 2.2 | F5: =C5*B5 -> 210400 | G5: 0 | H5: =F5+G5 -> 210400 | I5: =B5/(1-30%) -> 150285.71
A6: =Master!B12 -> Tablet (Industrial Grade) | B6: =VLOOKUP(A6,Master!B:C,2,0) -> 47000 | C6: =SUMIF(BOQ!$C$2:$G$11,'Hardware List'!A6,BOQ!$G$2:$G$11) -> 1 | D6: =C6*10% -> 0.1 | E6: =C6+D6 -> 1.1 | F6: =C6*B6 -> 47000 | G6: 0 | H6: =F6+G6 -> 47000 | I6: =B6/(1-30%) -> 67142.857
A7: =Master!B17 -> Traffic Light | B7: =VLOOKUP(A7,Master!B:C,2,0) -> 9200 | C7: 2 | D7: =C7*10% -> 0.2 | E7: =C7+D7 -> 2.2 | F7: =C7*B7 -> 18400 | G7: 0 | H7: =F7+G7 -> 18400 | I7: =B7/(1-30%) -> 13142.857
A8: AT Controller | B8: =VLOOKUP(A8,Master!B:C,2,0) -> 18400 | C8: 1 | D8: =C8*10% -> 0.1 | E8: =C8+D8 -> 1.1 | F8: =C8*B8 -> 18400 | G8: 1 | H8: =F8+G8 -> 18401 | I8: =B8/(1-30%) -> 26285.714
A9: Total | C9: =SUM(C1:C8) -> 10 | D9: 0 | E9: 10 | F9: =SUM(F1:F8) -> 479200 | G9: =SUM(G1:G7) -> 0 | H9: =SUM(H2:H8) -> 479201

Sheet Master
B1: Hardware | C1: Price
B2: RFID Reader | C2: 27000 | D2: =C2/(1-0.25) -> 36000
B3: ANPR Camera | C3: 65000 | D3: =C3/(1-0.25) -> 86666.667
B4: Handheld RFID Reader | C4: 66000 | D4: =C4/(1-0.25) -> 88000
B5: RFID tags | C5: 30 | D5: =C5/(1-0.25) -> 40
B6: Boom Barrier | C6: 105200 | D6: =C6/(1-0.25) -> 140266.67
B7: PA System 8 horn | C7: 60000 | D7: =C7/(1-0.25) -> 80000
B8: LED Display-XXL | C8: 180000 | D8: =C8/(1-0.25) -> 240000
B9: AT Controller | C9: 18400 | D9: =C9/(1-0.25) -> 24533.333
B10: LED Display-2 Line | C10: 17500 | D10: =C10/(1-0.25) -> 23333.333
B11: LED Display-1 Line | C11: 12000 | D11: =C11/(1-0.25) -> 16000
B12: Tablet (Industrial Grade) | C12: 47000 | D12: =C12/(1-0.25) -> 62666.667
B13: AT Positioning Sensor | C13: 6500 | D13: =C13/(1-0.25) -> 8666.6667
... B19: Desktop | C19: 70000 | D19: =C19/(1-0.25) -> 93333.333
B20: Biometric | C20: 36000
B21: Breath Analyzer | C21: 35000
B22: Kiosk Cabin | C22: 150000
B23: Full Height Turnstile | C23: 450000
B24: 8 Port POE | C24: 4800
B25: Laser Printer | C25: 30000
