Workbook

Sheet Quotation 
H1: Quotation
B2: Address - Corporate HQ : Axestrack Software Solutions Pvt. Ltd., Office No.-19, 6th Floor, Jaipur Electronic Market, Near Riddhi Siddhi, Gopalpura bypass, Jaipur - 302018 , Rajasthan, India
B3: GSTIN | D3: 08AACCH0299P1Z1 | F3: QUOTE # | H3: DATE
B4: MSME No | D4: UDYAM-RJ-17-0051921 | F4: ABC/XY/YYMM##
B5: Contact Person | D5: Rachit Agarwal
B6: Phone | F6: Quote Validity : 15 days from submitted date
B7: Email Id
B9: CUSTOMER INFO
B10: Company Name
B11: Address
B12: Contact Person | F12: Phone
B13: Email Id
B15: DESCRIPTION OF WORK
B16: Digitization and implement RFID based Gate Operation System (GOS) at Adani Kattupalli Port through the Connected Port Logistics platform, bundled with supply, installation, and Platform Deployment
B17: S.No. | C17: Year | E17: Description | G17: Type | I17: Amount
B18: 1 | C18: Hardware Cost (Refer to the hardware count breakup on proposal document on page no. 16) | E18: Hardware Cost -Port Main Gate In & Out -New Gate Complex In & Out -Old Gate Complex In & Out -CFS Gate In & Out -Liquid Pass Gate In & Out (bidirectional) -Liquid Terminal Load/Unload -Parking Yard | G18: One time | I18: ='Quotation BOQ1'!I30 -> 7531923 | J18: =I18/$K$22 -> 0.63045891
B19: 2 | E19: Hardware Transportation Cost | G19: One time | I19: =ROUNDUP('Commercials (C) '!L13,0) -> 376593 | J19: =I19/$K$22 -> 0.031522682
E20: Civil Work Cost | G20: One time | I20: 1532500 | J20: =I20/$K$22 -> 0.12827777
B21: 3 | C21: Implementation Cost | E21: Installation, Platform Customization, Deployment & Training (Including Travel, boarding and lodging cost) | G21: One time | I21: =ROUNDUP('Commercials (C) '!L23+'Commercials (C) '!L24,0) -> 2205715 | J21: =I21/$K$22 -> 0.18462917
B22: 4 | E22: ERP Integration Cost (As defined in SOW) | G22: One time | I22: =ROUNDUP('Commercials (C) '!K25,0) -> 300000 | J22: =I22/$K$22 -> 0.025111472 | K22: =SUM(I18:I22) -> 11946731
B23: 5 | C23: Subscription Fee Post Go-Live | E23: Platform Subscription + Support & Maintenance | G23: Monthly | I23: =ROUNDUP('Commercials (C) '!K34/12,0) -> 293572
B26: Refer Next Page for Project T&C/ Exclusions
B28: Terms & Conditions
B29: • All the prices mentioned in proposal are in rupees and exclusive of GST. Taxes as applicable • Device ownership remains with Client • These commercials are only for the gate Automation (GOS) for below location as below, any formal change or upgrade in hardware specifications or product features or location and lane count (beyond those installed during onboarding) will incur additional charges. • Port Main Gate In & Out : 2 Lanes per gate • New Gate Complex In & Out : 3 Lanes per gate • Old Gate Complex In & Out : 3 Lanes per gate • CFS Gate In & Out : 2 Lanes per gate • Liquid Pass Gate In & Out : 3 Lanes Bidirectional • Liquid Terminal Load/Unload : Manual via Handheld Device • Parking Yard : 2 Lanes per gate • The standard one-year hardware warranty period, as per OEM guidelines, will commence from the date of hardware delivery.(Burned / Physical Damaged hardware will not be part of AMC) - Kindly refer to Hardware warranty T&C attached. • The minimum contract period shall be three (3) years from the date of deployment. • Internet connectivity, civil works (including trenching, power supply, LAN/Wi-Fi readiness, pole mounting, enclosures), UPS provisioning, and related site readiness shall remain in the Client’s scope, as outlined in the assumptions and dependencies section of the proposal. • Civil works will be executed by Axestrack, subject to client approval of the execution methodology, vendor selection, and adherence to the client-defined quality checklist and safety standards. • AMC charges will be applicable from the second year onwards. These will be billed annually and calculated at 20% of the installed hardware cost. The AMC invoices will be raised separately from the second year. • Spares and accessory parts, if required, will be charged separately at prevailing rates. • Onsite Resources - one (1) in general shift for Hardware Monitoring, and offshore CS Customer Success for Project Management and Support is part of Monthly Subscription Fee. Any further requirement for Onsite resources will be charged separately. • The above costing remains valid for one (1) year from the date of proposal submission and includes the standard hardware warranty period. Payment Terms: • Full hardware cost upfront on project Kickoff • Payment for Platform Subscription + Support & Maintenance will be on quarterly basis. • 100% payments to be made within 15 days from the date of receipt of original or digitally signed invoice. In case of delay, overdue charges of 1.5% per month will be charged.
B31: Project Exclusions
B32: • Engaging in Customs or other regulatory bodies for compliance activities not related to automation.. • RFID Tags placement and mapping in system will done by Adani Port team. • Trade documentation initiatives beyond gate automation workflows. • Wagon-level container mapping, siding operations, or rake utilization optimization. • Customizations to ERP systems (ITUP, IPOS, and Navis N4) or third-party software outside defined API integrations. - The application APIs are compatible with ITUP, IPOS, and Navis N4 systems as per the defined integration scope. • Custom TOS modifications not related to vehicle movement/container movement/trip lifecycle. • Major civil construction, large-scale trenching, structural modification, or power feeder extension beyond defined gate automation areas shall remain outside Axestrack’s scope. • Manual interventions beyond defined automation (e.g., manual weighbridge ops, physical checks). • Hardware not supplied or supported under this project. • Coordination with third-party vendors/agents for systems not in the defined integration scope. Axestrack will liaise and coordinate with the ITUP, IPOS, and Navis teams to ensure successful integration and smooth implementation of the project. • Data cleansing/migration from legacy or manual records.
B33: Thanks for doing business with Axestrack Software Solution Pvt. Ltd.

Sheet Quote Nomeclature
B2: Quote no Format
B3: ABC/XY/YYMM##
B5: ABC | C5: Client name short Form like Hindalco Industries Limited will be HIL
B6: XY | C6: Axestrack Sales SPOC Intials
B7: YY | C7: Year
B8: MM | C8: Month
B9: ## | C9: Quote send by Sales SPOC in that particular month, quote nos. should be start from 11

Sheet Quotation BOQ1
H1: Quotation
B2: Address - Corporate HQ : Axestrack Software Solutions Pvt. Ltd., Office No.-19, 6th Floor, Jaipur Electronic Market, Near Riddhi Siddhi, Gopalpura bypass, Jaipur - 302018 , Rajasthan, India
B3: GSTIN | D3: 08AACCH0299P1Z1 | F3: QUOTE # | H3: DATE
B4: MSME No | D4: UDYAM-RJ-17-0051921 | F4: ABC/XY/YYMM##
B5: Contact Person | D5: Rachit Agarwal
B6: Phone | F6: Quote Validity : 15 days from submitted date
B7: Email Id
B9: CUSTOMER INFO
B10: Company Name
B11: Address
B12: Contact Person | F12: Phone
B13: Email Id
B15: Hardware BOQ
B16: Digitization and implement RFID based Gate Operation System (GOS) at Adani Kattupalli Port through the Connected Port Logistics platform, bundled with supply, installation, and Platform Deployment
B17: S.No. | C17: Hardware | E17: Make | F17: Unit Price | G17: Count | I17: Total
B18: 1 | C18: ='Total Hardware'!B3 -> RFID Reader | E18: ='Total Hardware'!C3 -> RFENERGIE | F18: =ROUNDUP(VLOOKUP(C18,'Total Hardware'!$B$3:$E$14,3,FALSE)/(1-30%),0) -> 38572 | G18: =ROUNDUP(VLOOKUP(C18,'Total Hardware'!$B$3:$E$14,4,FALSE),0) -> 28 | I18: =F18*G18 -> 1080016
B19: 2 | C19: ='Total Hardware'!B4 -> Handheld RFID Reader | E19: ='Total Hardware'!C4 -> Chainway | F19: =ROUNDUP(VLOOKUP(C19,'Total Hardware'!$B$3:$E$14,3,FALSE)/(1-30%),0) -> 94286 | G19: =ROUNDUP(VLOOKUP(C19,'Total Hardware'!$B$3:$E$14,4,FALSE),0) -> 1 | I19: =F19*G19 -> 94286
B20: 3 | C20: ='Total Hardware'!B5 -> AT Controller | E20: ='Total Hardware'!C5 -> Reputed | F20: =ROUNDUP(VLOOKUP(C20,'Total Hardware'!$B$3:$E$14,3,FALSE)/(1-30%),0) -> 22858 | G20: =ROUNDUP(VLOOKUP(C20,'Total Hardware'!$B$3:$E$14,4,FALSE),0) -> 25 | I20: =F20*G20 -> 571450
B21: 4 | C21: ='Total Hardware'!B6 -> ANPR Camera | E21: ='Total Hardware'!C6 -> Hikvision | F21: =ROUNDUP(VLOOKUP(C21,'Total Hardware'!$B$3:$E$14,3,FALSE)/(1-30%),0) -> 92858 | G21: =ROUNDUP(VLOOKUP(C21,'Total Hardware'!$B$3:$E$14,4,FALSE),0) -> 2 | I21: =F21*G21 -> 185716
B22: 5 | C22: ='Total Hardware'!B7 -> Smart Camera | E22: ='Total Hardware'!C7 -> Hikvision | F22: =ROUNDUP(VLOOKUP(C22,'Total Hardware'!$B$3:$E$14,3,FALSE)/(1-30%),0) -> 10000 | G22: =ROUNDUP(VLOOKUP(C22,'Total Hardware'!$B$3:$E$14,4,FALSE),0) -> 64 | I22: =F22*G22 -> 640000
B23: 6 | C23: ='Total Hardware'!B8 -> Tablet | E23: ='Total Hardware'!C8 -> Chainway | F23: =ROUNDUP(VLOOKUP(C23,'Total Hardware'!$B$3:$E$14,3,FALSE)/(1-30%),0) -> 58572 | G23: =ROUNDUP(VLOOKUP(C23,'Total Hardware'!$B$3:$E$14,4,FALSE),0) -> 2 | I23: =F23*G23 -> 117144
B24: 7 | C24: ='Total Hardware'!B9 -> PA System (Open Yard) | E24: ='Total Hardware'!C9 -> Ahuja | F24: =ROUNDUP(VLOOKUP(C24,'Total Hardware'!$B$3:$E$14,3,FALSE)/(1-30%),0) -> 40000 | G24: =ROUNDUP(VLOOKUP(C24,'Total Hardware'!$B$3:$E$14,4,FALSE),0) -> 0 | I24: =F24*G24 -> 0
B25: 8 | C25: ='Total Hardware'!B10 -> Display (2 Line) | E25: ='Total Hardware'!C10 -> Reputed | F25: =ROUNDUP(VLOOKUP(C25,'Total Hardware'!$B$3:$E$14,3,FALSE)/(1-30%),0) -> 13143 | G25: =ROUNDUP(VLOOKUP(C25,'Total Hardware'!$B$3:$E$14,4,FALSE),0) -> 4 | I25: =F25*G25 -> 52572
B26: 9 | C26: ='Total Hardware'!B11 -> Traffic Light | E26: ='Total Hardware'!C11 -> Reputed | F26: =ROUNDUP(VLOOKUP(C26,'Total Hardware'!$B$3:$E$14,3,FALSE)/(1-30%),0) -> 11429 | G26: =ROUNDUP(VLOOKUP(C26,'Total Hardware'!$B$3:$E$14,4,FALSE),0) -> 15 | I26: =F26*G26 -> 171435
B27: 10 | C27: ='Total Hardware'!B12 -> Printer Kiosk with Thermal Printer | E27: ='Total Hardware'!C12 -> Reputed | F27: =ROUNDUP(VLOOKUP(C27,'Total Hardware'!$B$3:$E$14,3,FALSE)/(1-30%),0) -> 142858 | G27: =ROUNDUP(VLOOKUP(C27,'Total Hardware'!$B$3:$E$14,4,FALSE),0) -> 6 | I27: =F27*G27 -> 857148
B28: 11 | C28: ='Total Hardware'!B13 -> Boom Barrier | E28: ='Total Hardware'!C13 -> Reputed | F28: =ROUNDUP(VLOOKUP(C28,'Total Hardware'!$B$3:$E$14,3,FALSE)/(1-30%),0) -> 163572 | G28: =ROUNDUP(VLOOKUP(C28,'Total Hardware'!$B$3:$E$14,4,FALSE),0) -> 23 | I28: =F28*G28 -> 3762156
B29: 12 | C29: ='Total Hardware'!B14 -> Boom Barrier Accessories | E29: ='Total Hardware'!C14 -> Reputed | F29: =ROUNDUP(VLOOKUP(C29,'Total Hardware'!$B$3:$E$14,3,FALSE)/(1-30%),0) -> 80286 | G29: =ROUNDUP(VLOOKUP(C29,'Total Hardware'!$B$3:$E$14,4,FALSE),0) -> 0 | I29: =F29*G29 -> 0
G30: =SUM(G18:H29) -> 170 | I30: =SUM(I18:I29) -> 7531923
B31: Thanks for doing business with Axestrack Software Solution Pvt. Ltd.

Sheet Quotation BOQ
A2: Sr. No. | B2: Hardware | D2: Unit Price | F2: Hardware Count | H2: Total Price
A3: 1 | B3: RFID Reader | D3: ='Total Hardware'!D3/(1-30%) -> 38571.429 | F3: =SUMIF(BOQ!$B$4:$G$54,'Quotation BOQ'!$B3,BOQ!$F$4:$F$54) -> 28 | H3: =D3*F3 -> 1080000
A4: 2 | B4: AT Controller | D4: ='Total Hardware'!D5/(1-30%) -> 22857.143 | F4: =SUMIF(BOQ!$B$4:$G$54,'Quotation BOQ'!$B4,BOQ!$F$4:$F$54) -> 25 | H4: =D4*F4 -> 571428.57
A5: 3 | B5: ANPR Camera | D5: ='Total Hardware'!D6/(1-30%) -> 92857.143 | F5: =SUMIF(BOQ!$B$4:$G$54,'Quotation BOQ'!$B5,BOQ!$F$4:$F$54) -> 2 | H5: =D5*F5 -> 185714.29
A6: 4 | B6: Smart Camera | D6: ='Total Hardware'!D7/(1-30%) -> 10000 | F6: =SUMIF(BOQ!$B$4:$G$54,'Quotation BOQ'!$B6,BOQ!$F$4:$F$54) -> 64 | H6: =D6*F6 -> 640000
A7: 5 | B7: Tablet | D7: ='Total Hardware'!D8/(1-30%) -> 58571.429 | F7: =SUMIF(BOQ!$B$4:$G$54,'Quotation BOQ'!$B7,BOQ!$F$4:$F$54) -> 2 | H7: =D7*F7 -> 117142.86
A8: 6 | B8: PA System (Open Yard) | D8: ='Total Hardware'!D9/(1-30%) -> 40000 | F8: =SUMIF(BOQ!$B$4:$G$54,'Quotation BOQ'!$B8,BOQ!$F$4:$F$54) -> 0 | H8: =D8*F8 -> 0
A9: 7 | B9: Display (2 Line) | D9: ='Total Hardware'!D10/(1-30%) -> 13142.857 | F9: =SUMIF(BOQ!$B$4:$G$54,'Quotation BOQ'!$B9,BOQ!$F$4:$F$54) -> 4 | H9: =D9*F9 -> 52571.429
A10: 8 | B10: Traffic Light | D10: ='Total Hardware'!D11/(1-30%) -> 11428.571 | F10: =SUMIF(BOQ!$B$4:$G$54,'Quotation BOQ'!$B10,BOQ!$F$4:$F$54) -> 15 | H10: =D10*F10 -> 171428.57
A11: 9 | B11: Printer Kiosk | D11: ='Total Hardware'!D12/(1-30%) -> 142857.14 | F11: =SUMIF(BOQ!$B$4:$G$54,'Quotation BOQ'!$B11,BOQ!$F$4:$F$54) -> 0 | H11: =D11*F11 -> 0
A12: 10 | B12: Boom Barrier | D12: ='Total Hardware'!D13/(1-30%) -> 163571.43 | F12: =SUMIF(BOQ!$B$4:$G$54,'Quotation BOQ'!$B12,BOQ!$F$4:$F$54) -> 23 | H12: =D12*F12 -> 3762142.9
B13: Total | F13: =SUM(F3:F12) -> 163 | H13: =SUM(H3:H12) -> 6580428.6

Sheet Commercials (C) 
B2: Customer | D2: Adani Port
B3: Date | D3: 45938
B4: Contract Year | D4: 3
B5: AMC Cost | D5: 0.2
B6: Hardware Transportation Cost | D6: 0.05
B7: Civil Labour Cost | D7: 0.7
B8: ERP Integration Cost | D8: 300000
B9: Software Subscription Cost/month | D9: 175000
B11: Model | C11: Items | E11: Details | F11: Type | G11: Unit Cost | H11: Nos. of years | I11: Landed Cost to Axestrack for 3 Years | J11: Margin | K11: Unit price on Margin | L11: Cost for Customer for 3 Years | M11: Project Margin
B12: One Time Cost | C12: Hardware Cost | D12: Hardware BOQ Cost | E12: Hardware as per BOQ | F12: One Time | I12: ='Total Hardware'!F15 -> 5272300 | J12: 0.3 | K12: =IF(H12=0,(I12/(1-J12)),(I12/H12)/(1-J12)) -> 7531857.1 | L12: =I12/(1-J12) -> 7531857.1 | M12: =L12-I12 -> 2259557.1
E13: Hardware Transportation Cost | F13: One Time | I13: =(I12)*D6 -> 263615 | J13: 0.3 | K13: =IF(H13=0,(I13/(1-J13)),(I13/H13)/(1-J13)) -> 376592.86 | L13: =I13/(1-J13) -> 376592.86 | M13: =L13-I13 -> 112977.86
E14: Hardware Cost | I14: =SUM(I12:I13) -> 5535915 | K14: =SUM(K12:K13) -> 7908450 | L14: =SUM(L12:L13) -> 7908450 | M14: =SUM(M12:M13) -> 2372535
D15: Spares BOQ Cost (Optional) | E15: Spares | F15: One Time | I15: ='Total Hardware'!H15 -> 332800 | J15: 0.3 | K15: =IF(H15=0,(I15/(1-J15)),(I15/H15)/(1-J15)) -> 475428.57 | L15: =I15/(1-J15) -> 475428.57 | M15: =L15-I15 -> 142628.57
E16: Spares Transportation Cost | F16: One Time | I16: =I15*D6 -> 16640 | J16: 0.3 | K16: =IF(H16=0,(I16/(1-J16)),(I16/H16)/(1-J16)) -> 23771.429 | L16: =I16/(1-J16) -> 23771.429 | M16: =L16-I16 -> 7131.4286
E17: Spares Cost | I17: =SUM(I15:I16) -> 349440 | K17: =SUM(K15:K16) -> 499200 | L17: =SUM(L15:L16) -> 499200 | M17: =SUM(M15:M16) -> 149760
C18: Civil Cost | D18: CIVIL BOQ Cost | E18: Civil hardware as per BOQ | F18: One Time | I18: =CIVIL!G33 -> 493000 | J18: 0.3 | K18: =IF(H18=0,(I18/(1-J18)),(I18/H18)/(1-J18)) -> 704285.71 | L18: =I18/(1-J18) -> 704285.71 | M18: =L18-I18 -> 211285.71
E19: Civil Hardware Transportation Cost | F19: One Time | I19: =I18*D6 -> 24650 | J19: 0.3 | K19: =IF(H19=0,(I19/(1-J19)),(I19/H19)/(1-J19)) -> 35214.286 | L19: =I19/(1-J19) -> 35214.286 | M19: =L19-I19 -> 10564.286
E20: Civil Labour Cost | F20: One Time | I20: =I18*D7 -> 345100 | J20: 0.3 | K20: =IF(H20=0,(I20/(1-J20)),(I20/H20)/(1-J20)) -> 493000 | L20: =I20/(1-J20) -> 493000 | M20: =L20-I20 -> 147900
E21: Civil Cost | I21: =SUM(I18:I20) -> 862750 | K21: =SUM(K18:K20) -> 1232500 | L21: =SUM(L18:L20) -> 1232500 | M21: =SUM(M18:M20) -> 369750
D22: Total Hardware Cost | I22: =I14+I17+I21 -> 6748105 | K22: =K14+K17+K21 -> 9640150 | L22: =L14+L17+L21 -> 9640150 | M22: =M14+M17+M21 -> 2892045
C23: Implementation Cost | D23: Installation, Training & Configuration | E23: One Time Installation & deploymnet | F23: One Time | I23: ='Manpower-PM Cost'!I10 -> 780000 | J23: 0.3 | K23: =IF(H23=0,(I23/(1-J23)),(I23/H23)/(1-J23)) -> 1114285.7 | L23: =I23/(1-J23) -> 1114285.7 | M23: =L23-I23 -> 334285.71
D24: Food & Accomodation | E24: One Time Accomodation | F24: One Time | I24: ='Manpower-PM Cost'!J27+'Manpower-PM Cost'!J33 -> 764000 | J24: 0.3 | K24: =IF(H24=0,(I24/(1-J24)),(I24/H24)/(1-J24)) -> 1091428.6 | L24: =I24/(1-J24) -> 1091428.6 | M24: =L24-I24 -> 327428.57
D25: ERP Integration | E25: ERP Integration | F25: One Time | I25: =D8 -> 300000 | J25: 0 | K25: =IF(H25=0,(I25/(1-J25)),(I25/H25)/(1-J25)) -> 300000 | L25: =I25/(1-J25) -> 300000 | M25: =L25-I25 -> 0
D26: Total Installation, Setup & API Development Cost | I26: =SUM(I23:I25) -> 1844000 | K26: =SUM(K23:K25) -> 2505714.3 | L26: =SUM(L23:L25) -> 2505714.3 | M26: =SUM(M23:M25) -> 661714.29
C27: One Time Cost | I27: =I22+I26 -> 8592105 | K27: =K22+K26 -> 12145864 | L27: =L22+L26 -> 12145864 | M27: =M22+M26 -> 3553759.3
C29: Annual Subscription fee | D29: Onsite Manpower, Project Management, Support & Maintenance | E29: Project Manpower Cost | F29: Per Year | G29: ='Manpower-PM Cost'!U10 -> 810000 | H29: =D4 -> 3 | I29: =G29*H29 -> 2430000 | J29: 0.3 | K29: =IF(H29=0,(I29/(1-J29)),(I29/H29)/(1-J29)*H29/$D$4) -> 1157142.9 | L29: =I29/(1-J29) -> 3471428.6 | M29: =L29*J29 -> 1041428.6
E30: Lodging & Travel Cost | F30: Per Year | G30: ='Manpower-PM Cost'!V27 -> 186000 | H30: =D4 -> 3 | I30: =G30*H30 -> 558000 | J30: 0.3 | K30: =IF(H30=0,(I30/(1-J30)),(I30/H30)/(1-J30)*H30/$D$4) -> 265714.29 | L30: =I30/(1-J30) -> 797142.86 | M30: =L30*J30 -> 239142.86
D31: Project Management Cost | I31: =SUM(I29:I30) -> 2988000 | K31: =SUM(K29:K30) -> 1422857.1 | L31: =SUM(L29:L30) -> 4268571.4
D32: Platform Subscription Fee | E32: Platform Subscription Fee | F32: Per Year | G32: =D9*12 -> 2100000 | H32: =D4 -> 3 | I32: =H32*G32 -> 6300000 | J32: 0 | K32: =IF(H32=0,(I32/(1-J32)),(I32/H32)/(1-J32)) -> 2100000 | L32: =I32/(1-J32) -> 6300000 | M32: =L32*0.5 -> 3150000
D33: Platform Fee | I33: =SUM(I32) -> 6300000 | K33: =SUM(K32) -> 2100000 | L33: =SUM(L32) -> 6300000
C34: Subscription Fee | I34: =I31+I33 -> 9288000 | K34: =K31+K33 -> 3522857.1 | L34: =L31+L33+L37 -> #REF! | P34: =O34/4 -> 0
K35: =K34/12 -> 293571.43
C37: AMC Second year Onwards | G37: =SUM(I12+#REF!+I15)*D5 -> #REF! | H37: 2 | I37: =G37*H37 -> #REF! | J37: 0.3 | K37: =IF(H37=0,(I37/(1-J37)),(I37/H37)/(1-J37)*H37/($D$4-1)) -> #REF! | L37: =I37/(1-J37) -> #REF! | M37: =L37*J37 -> #REF!

Sheet Manpower-PM Cost
B2: Implementation Cost | N2: Project Support Manpower (Post Go-Live)
C4: Implementation Cost | O4: Support Manpower (Post Go-Live)
C5: Installation, Training & Configuration Cost | O5: Support & Maintenance Manpower
C6: Type of Manpower | D6: Type | E6: Count per shift | F6: Nos. of shifts | G6: Cost per Resource per month | H6: Duration in Months | I6: Total | O6: Type of Manpower | P6: Type | Q6: Count per shift | R6: Nos. of shifts | S6: Cost per Resource per month | T6: Duration in Months | U6: Total
C7: PM | D7: Onsite | E7: 0.5 | F7: 1 | G7: 60000 | H7: 4 | I7: =PRODUCT(E7:H7) -> 120000 | O7: CS/PM | P7: Offshore | Q7: 0.5 | R7: 1 | S7: 50000 | T7: 12 | U7: =PRODUCT(Q7:T7) -> 300000
C8: Hardware Engineers | D8: Onsite | E8: 3 | F8: 1 | G8: 30000 | H8: 4 | I8: =PRODUCT(E8:H8) -> 360000 | O8: Hardware Engineers | P8: Onsite | Q8: 1 | R8: 1 | S8: 30000 | T8: 12 | U8: =PRODUCT(Q8:T8) -> 360000
C9: Software Engineers | D9: Offshore | E9: 2 | F9: 1 | G9: 50000 | H9: 3 | I9: =PRODUCT(E9:H9) -> 300000 | O9: Software Engineers | P9: Offshore | Q9: 0.25 | R9: 1 | S9: 50000 | T9: 12 | U9: =PRODUCT(Q9:T9) -> 150000
E10: =SUMPRODUCT(E7:E9,F7:F9) -> 5.5 | H10: Total | I10: =SUM(I7:I9) -> 780000 | Q10: =SUMPRODUCT(Q7:Q9,R7:R9) -> 1.75 | T10: Total | U10: =SUM(U7:U9) -> 810000
C13: Current Equipments | E13: Count | F13: Productivity per resource | G13: Resources Required | L13: Planned Equipments
C14: Machines | E14: 47 | F14: 6 | G14: =ROUND(E14/F14,0) -> 8 | L14: Machines
C15: Gate Lanes | E15: 40 | F15: 7 | G15: =ROUND(E15/F15,0) -> 6 | L15: Gate Lanes
C16: Vehicles | E16: 810 | F16: 120 | G16: =ROUND(E16/F16,0) -> 7 | L16: Vehicles
F17: Onsite | G17: =SUM(G14:G16) -> 21
F18: MIS | G18: =ROUND(G17/8,0) -> 3
C21: Travel Cost (Till Go-Live) | O21: Project Management Cost - Travel & Lodging
C22: Boarding & Lodging | O22: Annual Project Management Cost - Travel & Lodging
C23: Type of Manpower | D23: Type | E23: Day Allowance | F23: Travel Cost | G23: Stay Cost per Day | H23: Days per trip | I23: Frequency (Till Go-live) | J23: Total | O23: Type of Manpower | P23: Type | Q23: Travel Allowance | R23: Travel Cost | S23: Stay Cost per Day | T23: Days per trip | U23: Frequency (Annually) | V23: Total
C24: PM | D24: Onsite | E24: 1500 | F24: 25000 | G24: 4500 | H24: 2 | I24: 2 | J24: =(I24*H24*E24)+(F24*I24)+(G24*H24*I24) -> 74000 | O24: PM | P24: Per Year | Q24: 1500 | R24: 25000 | S24: 4500 | T24: 1 | U24: 3 | V24: =(U24*T24*Q24)+(R24*U24)+(S24*T24*U24) -> 93000
C25: Hardware Engineers | D25: Onsite | E25: 1500 | F25: 25000 | G25: 0 | H25: 0 | I25: 8 | J25: =(I25*H25*E25)+(F25*I25)+(G25*H25*I25) -> 200000 | O25: Hardware Engineers | P25: Per Year | Q25: 1500 | R25: 25000 | S25: 2000 | T25: 0 | U25: 0 | V25: =(U25*T25*Q25)+(R25*U25)+(S25*T25*U25) -> 0
C26: Software Engineers | D26: Offshore | E26: 1500 | F26: 25000 | G26: 4500 | H26: 0 | I26: 2 | J26: =(I26*H26*E26)+(F26*I26)+(G26*H26*I26) -> 50000 | O26: Mis. | P26: Per Year | Q26: 1500 | R26: 25000 | S26: 4500 | T26: 1 | U26: 3 | V26: =(U26*T26*Q26)+(R26*U26)+(S26*T26*U26) -> 93000
I27: Total | J27: =SUM(J24:J26) -> 324000 | U27: Total | V27: =SUM(V24:V26) -> 186000
H30: Rent | I30: month | J30: Total
G31: permonth rent | H31: 60000 | I31: 4 | J31: =H31*I31 -> 240000
G32: Kitchen | H32: 50000 | I32: 4 | J32: =H32*I32 -> 200000
J33: =SUM(J31:J32) -> 440000
J35: =J33+J27 -> 764000

Sheet Total Hardware
A2: Sr. No. | B2: Hardware | C2: make | D2: Unit Price | E2: Count | F2: Cost of Hardware | G2: Spares | H2: Cost of Spares | I2: Total Cost Landing | J2: Total Count
A3: 1 | B3: RFID Reader | C3: RFENERGIE | D3: =VLOOKUP($B3,Master!$A$3:$B$21,2,FALSE) -> 27000 | E3: =SUMIF(BOQ!$B$4:$G$54,'Total Hardware'!$B3,BOQ!$F$4:$F$54) -> 28 | F3: =E3*$D3 -> 756000 | G3: 2 | H3: =G3*$D3 -> 54000 | I3: =F3+H3 -> 810000 | J3: =E3+G3 -> 30
A4: 2 | B4: Handheld RFID Reader | C4: Chainway | D4: =VLOOKUP($B4,Master!$A$3:$B$21,2,FALSE) -> 66000 | E4: =SUMIF(BOQ!$B$4:$G$54,'Total Hardware'!$B4,BOQ!$F$4:$F$54) -> 1 | F4: =E4*$D4 -> 66000 | H4: =G4*$D4 -> 0 | I4: =F4+H4 -> 66000 | J4: =E4+G4 -> 1
A5: 3 | B5: AT Controller | C5: Reputed | D5: =VLOOKUP($B5,Master!$A$3:$B$21,2,FALSE) -> 16000 | E5: =SUMIF(BOQ!$B$4:$G$54,'Total Hardware'!$B5,BOQ!$F$4:$F$54) -> 25 | F5: =E5*$D5 -> 400000 | G5: 2 | H5: =G5*$D5 -> 32000 | I5: =F5+H5 -> 432000 | J5: =E5+G5 -> 27
A6: 4 | B6: ANPR Camera | C6: Hikvision | D6: =VLOOKUP($B6,Master!$A$3:$B$21,2,FALSE) -> 65000 | E6: =SUMIF(BOQ!$B$4:$G$54,'Total Hardware'!$B6,BOQ!$F$4:$F$54) -> 2 | F6: =E6*$D6 -> 130000 | H6: =G6*$D6 -> 0 | I6: =F6+H6 -> 130000 | J6: =E6+G6 -> 2
A7: 5 | B7: Smart Camera | C7: Hikvision | D7: =VLOOKUP($B7,Master!$A$3:$B$21,2,FALSE) -> 7000 | E7: =SUMIF(BOQ!$B$4:$G$54,'Total Hardware'!$B7,BOQ!$F$4:$F$54) -> 64 | F7: =E7*$D7 -> 448000 | G7: 2 | H7: =G7*$D7 -> 14000 | I7: =F7+H7 -> 462000 | J7: =E7+G7 -> 66
A8: 6 | B8: Tablet | C8: Chainway | D8: =VLOOKUP($B8,Master!$A$3:$B$21,2,FALSE) -> 41000 | E8: =SUMIF(BOQ!$B$4:$G$54,'Total Hardware'!$B8,BOQ!$F$4:$F$54) -> 2 | F8: =E8*$D8 -> 82000 | H8: =G8*$D8 -> 0 | I8: =F8+H8 -> 82000 | J8: =E8+G8 -> 2
A9: 7 | B9: PA System (Open Yard) | C9: Ahuja | D9: =VLOOKUP($B9,Master!$A$3:$B$21,2,FALSE) -> 28000 | E9: =SUMIF(BOQ!$B$4:$G$54,'Total Hardware'!$B9,BOQ!$F$4:$F$54) -> 0 | F9: =E9*$D9 -> 0 | H9: =G9*$D9 -> 0 | I9: =F9+H9 -> 0 | J9: =E9+G9 -> 0
A10: 8 | B10: Display (2 Line) | C10: Reputed | D10: =VLOOKUP($B10,Master!$A$3:$B$21,2,FALSE) -> 9200 | E10: =SUMIF(BOQ!$B$4:$G$54,'Total Hardware'!$B10,BOQ!$F$4:$F$54) -> 4 | F10: =E10*$D10 -> 36800 | H10: =G10*$D10 -> 0 | I10: =F10+H10 -> 36800 | J10: =E10+G10 -> 4
A11: 9 | B11: Traffic Light | C11: Reputed | D11: =VLOOKUP($B11,Master!$A$3:$B$21,2,FALSE) -> 8000 | E11: =SUMIF(BOQ!$B$4:$G$54,'Total Hardware'!$B11,BOQ!$F$4:$F$54) -> 15 | F11: =E11*$D11 -> 120000 | G11: 1 | H11: =G11*$D11 -> 8000 | I11: =F11+H11 -> 128000 | J11: =E11+G11 -> 16
A12: 10 | B12: Printer Kiosk with Thermal Printer | C12: Reputed | D12: =VLOOKUP($B12,Master!$A$3:$B$21,2,FALSE) -> 100000 | E12: =SUMIF(BOQ!$B$4:$G$54,'Total Hardware'!$B12,BOQ!$F$4:$F$54) -> 6 | F12: =E12*$D12 -> 600000 | H12: =G12*$D12 -> 0 | I12: =F12+H12 -> 600000 | J12: =E12+G12 -> 6
A13: 11 | B13: Boom Barrier | C13: Reputed | D13: =VLOOKUP($B13,Master!$A$3:$B$21,2,FALSE) -> 114500 | E13: =SUMIF(BOQ!$B$4:$G$54,'Total Hardware'!$B13,BOQ!$F$4:$F$54) -> 23 | F13: =E13*$D13 -> 2633500 | H13: =G13*$D13 -> 0 | I13: =F13+H13 -> 2633500 | J13: =E13+G13 -> 23
A14: 12 | B14: Boom Barrier Accessories | C14: Reputed | D14: =VLOOKUP($B14,Master!$A$3:$B$21,2,FALSE) -> 56200 | E14: =SUMIF(BOQ!$B$4:$G$54,'Total Hardware'!$B14,BOQ!$F$4:$F$54) -> 0 | F14: =E14*$D14 -> 0 | G14: 4 | H14: =G14*$D14 -> 224800 | I14: =F14+H14 -> 224800 | J14: =E14+G14 -> 4
B15: Total | E15: =SUM(E3:E14) -> 170 | F15: =SUM(F3:F14) -> 5272300 | G15: =SUM(G3:G14) -> 11 | H15: =SUM(H3:H14) -> 332800 | I15: =SUM(I3:I14) -> 5605100 | J15: =SUM(J3:J14) -> 181
B17: This is formula driven sheet. Only update the spares Count
B18: Please update the BOQ sheet for other fields

Sheet CIVIL
A3: Location/Machine | B3: Hardware | C3: Unit Price | D3: Quantity per Check Point | E3: Check point | F3: Total Quantity as per stage | G3: Hardware landing
A4: Port Main Gate In | B4: GI Pipe + Foundation + Junction Box | C4: =_xlfn.IFNA(VLOOKUP(B4,Master!$A$3:$B$21,2,FALSE),0) -> 4600 | D4: 1 | E4: =VLOOKUP($A4,Master!$A$24:$B$37,2,FALSE) -> 2 | F4: =D4*E4 -> 2 | G4: =F4*$C4 -> 9200
A5: Port Main Gate In | B5: Traffic Light GI Pipe + Foundation + Junction Box | C5: =_xlfn.IFNA(VLOOKUP(B5,Master!$A$3:$B$21,2,FALSE),0) -> 4600 | D5: 1 | E5: =VLOOKUP($A5,Master!$A$24:$B$37,2,FALSE) -> 2 | F5: =D5*E5 -> 2 | G5: =F5*$C5 -> 9200
A6: Port Main Gate In | B6: Camera Back GI Pipe + Foundation+Junction Box | C6: =_xlfn.IFNA(VLOOKUP(B6,Master!$A$3:$B$21,2,FALSE),0) -> 4900 | D6: 1 | E6: =VLOOKUP($A6,Master!$A$24:$B$37,2,FALSE) -> 2 | F6: =D6*E6 -> 2 | G6: =F6*$C6 -> 9800
A7: Port Main Gate In | B7: Boom Barrier Foundation | C7: =_xlfn.IFNA(VLOOKUP(B7,Master!$A$3:$B$21,2,FALSE),0) -> 6000 | D7: 1 | E7: =VLOOKUP($A7,Master!$A$24:$B$37,2,FALSE) -> 2 | F7: =D7*E7 -> 2 | G7: =F7*$C7 -> 12000
A8: Parking Yard Out | B8: GI Pipe + Foundation + Junction Box | C8: =_xlfn.IFNA(VLOOKUP(B8,Master!$A$3:$B$21,2,FALSE),0) -> 4600 | D8: 1 | E8: =VLOOKUP($A8,Master!$A$24:$B$37,2,FALSE) -> 2 | F8: =D8*E8 -> 2 | G8: =F8*$C8 -> 9200
A9: New Gate Complex In | B9: GI Pipe + Foundation + Junction Box | C9: =_xlfn.IFNA(VLOOKUP(B9,Master!$A$3:$B$21,2,FALSE),0) -> 4600 | D9: =1+2 -> 3 | E9: =VLOOKUP($A9,Master!$A$24:$B$37,2,FALSE) -> 3 | F9: =D9*E9 -> 9 | G9: =F9*$C9 -> 41400
A10: New Gate Complex In | B10: Top + back View GI Pipe + Foundation+ Junction box | C10: =_xlfn.IFNA(VLOOKUP(B10,Master!$A$3:$B$21,2,FALSE),0) -> 10200 | D10: 1 | E10: =VLOOKUP($A10,Master!$A$24:$B$37,2,FALSE) -> 3 | F10: =D10*E10 -> 3 | G10: =F10*$C10 -> 30600
A11: New Gate Complex In | B11: Boom Barrier Foundation | C11: =_xlfn.IFNA(VLOOKUP(B11,Master!$A$3:$B$21,2,FALSE),0) -> 6000 | D11: 1 | E11: =VLOOKUP($A11,Master!$A$24:$B$37,2,FALSE) -> 3 | F11: =D11*E11 -> 3 | G11: =F11*$C11 -> 18000
A12: Old Gate Complex In | B12: GI Pipe + Foundation + Junction Box | C12: =_xlfn.IFNA(VLOOKUP(B12,Master!$A$3:$B$21,2,FALSE),0) -> 4600 | D12: 1 | E12: =VLOOKUP($A12,Master!$A$24:$B$37,2,FALSE) -> 3 | F12: =D12*E12 -> 3 | G12: =F12*$C12 -> 13800
A13: Old Gate Complex In | B13: Camera Back GI Pipe + Foundation+Junction Box | C13: =_xlfn.IFNA(VLOOKUP(B13,Master!$A$3:$B$21,2,FALSE),0) -> 4900 | D13: 1 | E13: =VLOOKUP($A13,Master!$A$24:$B$37,2,FALSE) -> 3 | F13: =D13*E13 -> 3 | G13: =F13*$C13 -> 14700
A14: Old Gate Complex In | B14: Boom Barrier Foundation | C14: =_xlfn.IFNA(VLOOKUP(B14,Master!$A$3:$B$21,2,FALSE),0) -> 6000 | D14: 1 | E14: =VLOOKUP($A14,Master!$A$24:$B$37,2,FALSE) -> 3 | F14: =D14*E14 -> 3 | G14: =F14*$C14 -> 18000 | H14: NVR
A15: Old Gate Complex In | B15: Kiosk Foundation | C15: =_xlfn.IFNA(VLOOKUP(B15,Master!$A$3:$B$21,2,FALSE),0) -> 4000 | D15: 1 | E15: =VLOOKUP($A15,Master!$A$24:$B$37,2,FALSE) -> 3 | F15: =D15*E15 -> 3 | G15: =F15*$C15 -> 12000
A16: Old Gate Complex Out | B16: GI Pipe + Foundation + Junction Box | C16: =_xlfn.IFNA(VLOOKUP(B16,Master!$A$3:$B$21,2,FALSE),0) -> 4600 | D16: 1 | E16: =VLOOKUP($A16,Master!$A$24:$B$37,2,FALSE) -> 3 | F16: =D16*E16 -> 3 | G16: =F16*$C16 -> 13800
A17: Old Gate Complex Out | B17: Camera Back GI Pipe + Foundation+Junction Box | C17: =_xlfn.IFNA(VLOOKUP(B17,Master!$A$3:$B$21,2,FALSE),0) -> 4900 | D17: 1 | E17: =VLOOKUP($A17,Master!$A$24:$B$37,2,FALSE) -> 3 | F17: =D17*E17 -> 3 | G17: =F17*$C17 -> 14700
A18: Old Gate Complex Out | B18: Boom Barrier Foundation | C18: =_xlfn.IFNA(VLOOKUP(B18,Master!$A$3:$B$21,2,FALSE),0) -> 6000 | D18: 1 | E18: =VLOOKUP($A18,Master!$A$24:$B$37,2,FALSE) -> 3 | F18: =D18*E18 -> 3 | G18: =F18*$C18 -> 18000
A19: Old Gate Complex Out | B19: Kiosk Foundation | C19: =_xlfn.IFNA(VLOOKUP(B19,Master!$A$3:$B$21,2,FALSE),0) -> 4000 | D19: 1 | E19: =VLOOKUP($A19,Master!$A$24:$B$37,2,FALSE) -> 3 | F19: =D19*E19 -> 3 | G19: =F19*$C19 -> 12000
A20: New Gate Complex Out | B20: GI Pipe + Foundation + Junction Box | C20: =_xlfn.IFNA(VLOOKUP(B20,Master!$A$3:$B$21,2,FALSE),0) -> 4600 | D20: =1+2 -> 3 | E20: =VLOOKUP($A20,Master!$A$24:$B$37,2,FALSE) -> 3 | F20: =D20*E20 -> 9 | G20: =F20*$C20 -> 41400
A21: New Gate Complex Out | B21: Top + back View GI Pipe + Foundation+ Junction box | C21: =_xlfn.IFNA(VLOOKUP(B21,Master!$A$3:$B$21,2,FALSE),0) -> 10200 | D21: 1 | E21: =VLOOKUP($A21,Master!$A$24:$B$37,2,FALSE) -> 3 | F21: =D21*E21 -> 3 | G21: =F21*$C21 -> 30600
A22: New Gate Complex Out | B22: Boom Barrier Foundation | C22: =_xlfn.IFNA(VLOOKUP(B22,Master!$A$3:$B$21,2,FALSE),0) -> 6000 | D22: 1 | E22: =VLOOKUP($A22,Master!$A$24:$B$37,2,FALSE) -> 3 | F22: =D22*E22 -> 3 | G22: =F22*$C22 -> 18000
A23: Port Main Gate Out | B23: GI Pipe + Foundation + Junction Box | C23: =_xlfn.IFNA(VLOOKUP(B23,Master!$A$3:$B$21,2,FALSE),0) -> 4600 | D23: 1 | E23: =VLOOKUP($A23,Master!$A$24:$B$37,2,FALSE) -> 2 | F23: =D23*E23 -> 2 | G23: =F23*$C23 -> 9200
A24: Port Main Gate Out | B24: Traffic Light GI Pipe + Foundation + Junction Box | C24: =_xlfn.IFNA(VLOOKUP(B24,Master!$A$3:$B$21,2,FALSE),0) -> 4600 | D24: 1 | E24: =VLOOKUP($A24,Master!$A$24:$B$37,2,FALSE) -> 2 | F24: =D24*E24 -> 2 | G24: =F24*$C24 -> 9200
A25: Port Main Gate Out | B25: Camera Back GI Pipe + Foundation+Junction Box | C25: =_xlfn.IFNA(VLOOKUP(B25,Master!$A$3:$B$21,2,FALSE),0) -> 4900 | D25: 1 | E25: =VLOOKUP($A25,Master!$A$24:$B$37,2,FALSE) -> 2 | F25: =D25*E25 -> 2 | G25: =F25*$C25 -> 9800
A26: Port Main Gate Out | B26: Boom Barrier Foundation | C26: =_xlfn.IFNA(VLOOKUP(B26,Master!$A$3:$B$21,2,FALSE),0) -> 6000 | D26: 1 | E26: =VLOOKUP($A26,Master!$A$24:$B$37,2,FALSE) -> 2 | F26: =D26*E26 -> 2 | G26: =F26*$C26 -> 12000
A27: CFS Gate In | B27: GI Pipe + Foundation + Junction Box | C27: =_xlfn.IFNA(VLOOKUP(B27,Master!$A$3:$B$21,2,FALSE),0) -> 4600 | D27: 2 | E27: =VLOOKUP($A27,Master!$A$24:$B$37,2,FALSE) -> 2 | F27: =D27*E27 -> 4 | G27: =F27*$C27 -> 18400
A28: CFS Gate In | B28: Boom Barrier Foundation | C28: =_xlfn.IFNA(VLOOKUP(B28,Master!$A$3:$B$21,2,FALSE),0) -> 6000 | D28: 1 | E28: =VLOOKUP($A28,Master!$A$24:$B$37,2,FALSE) -> 2 | F28: =D28*E28 -> 2 | G28: =F28*$C28 -> 12000
A29: CFS Gate Out | B29: GI Pipe + Foundation + Junction Box | C29: =_xlfn.IFNA(VLOOKUP(B29,Master!$A$3:$B$21,2,FALSE),0) -> 4600 | D29: 2 | E29: =VLOOKUP($A29,Master!$A$24:$B$37,2,FALSE) -> 2 | F29: =D29*E29 -> 4 | G29: =F29*$C29 -> 18400
A30: CFS Gate Out | B30: Boom Barrier Foundation | C30: =_xlfn.IFNA(VLOOKUP(B30,Master!$A$3:$B$21,2,FALSE),0) -> 6000 | D30: 1 | E30: =VLOOKUP($A30,Master!$A$24:$B$37,2,FALSE) -> 2 | F30: =D30*E30 -> 2 | G30: =F30*$C30 -> 12000
A31: Liquid Pass Gate In/Out Bidirectional | B31: GI Pipe + Foundation + Junction Box | C31: =_xlfn.IFNA(VLOOKUP(B31,Master!$A$3:$B$21,2,FALSE),0) -> 4600 | D31: 2 | E31: =VLOOKUP($A31,Master!$A$24:$B$37,2,FALSE) -> 3 | F31: =D31*E31 -> 6 | G31: =F31*$C31 -> 27600
A32: Liquid Pass Gate In/Out Bidirectional | B32: Boom Barrier Foundation | C32: =_xlfn.IFNA(VLOOKUP(B32,Master!$A$3:$B$21,2,FALSE),0) -> 6000 | D32: 1 | E32: =VLOOKUP($A32,Master!$A$24:$B$37,2,FALSE) -> 3 | F32: =D32*E32 -> 3 | G32: =F32*$C32 -> 18000
G33: =SUM(G4:G32) -> 493000

Sheet BOQ
A3: Location/Machine | B3: Hardware | C3: Unit Price | D3: Quantity per Check Point | E3: Check point | F3: Total Quantity as per stage | G3: Hardware landing
A4: Port Main Gate In | B4: RFID Reader | C4: =_xlfn.IFNA(VLOOKUP(B4,Master!$A$3:$B$21,2,FALSE),0) -> 27000 | D4: 1 | E4: =VLOOKUP($A4,Master!$A$24:$B$37,2,FALSE) -> 2 | F4: =D4*E4 -> 2 | G4: =F4*$C4 -> 54000
A5: Port Main Gate In | B5: Boom Barrier | C5: =_xlfn.IFNA(VLOOKUP(B5,Master!$A$3:$B$21,2,FALSE),0) -> 114500 | D5: 1 | E5: =VLOOKUP($A5,Master!$A$24:$B$37,2,FALSE) -> 2 | F5: =D5*E5 -> 2 | G5: =F5*$C5 -> 229000
A6: Port Main Gate In | B6: Smart Camera | C6: =_xlfn.IFNA(VLOOKUP(B6,Master!$A$3:$B$21,2,FALSE),0) -> 7000 | D6: 2 | E6: =VLOOKUP($A6,Master!$A$24:$B$37,2,FALSE) -> 2 | F6: =D6*E6 -> 4 | G6: =F6*$C6 -> 28000
A7: Port Main Gate In | B7: Display (2 Line) | C7: =_xlfn.IFNA(VLOOKUP(B7,Master!$A$3:$B$21,2,FALSE),0) -> 9200 | D7: 1 | E7: =VLOOKUP($A7,Master!$A$24:$B$37,2,FALSE) -> 2 | F7: =D7*E7 -> 2 | G7: =F7*$C7 -> 18400
A8: Port Main Gate In | B8: Traffic Light | C8: =_xlfn.IFNA(VLOOKUP(B8,Master!$A$3:$B$21,2,FALSE),0) -> 8000 | D8: 1 | E8: =VLOOKUP($A8,Master!$A$24:$B$37,2,FALSE) -> 2 | F8: =D8*E8 -> 2 | G8: =F8*$C8 -> 16000
A9: Port Main Gate In | B9: AT Controller | C9: =_xlfn.IFNA(VLOOKUP(B9,Master!$A$3:$B$21,2,FALSE),0) -> 16000 | D9: 1 | E9: =VLOOKUP($A9,Master!$A$24:$B$37,2,FALSE) -> 2 | F9: =D9*E9 -> 2 | G9: =F9*$C9 -> 32000
A10: Port Main Gate In | B10: Tablet | C10: =_xlfn.IFNA(VLOOKUP(B10,Master!$A$3:$B$21,2,FALSE),0) -> 41000 | D10: 1 | E10: =VLOOKUP($A10,Master!$A$24:$B$37,2,FALSE) -> 2 | F10: =D10*E10 -> 2 | G10: =F10*$C10 -> 82000
A11: Port Main Gate In | B11: ANPR Camera | C11: =_xlfn.IFNA(VLOOKUP(B11,Master!$A$3:$B$21,2,FALSE),0) -> 65000 | D11: 1 | E11: =VLOOKUP($A11,Master!$A$24:$B$37,2,FALSE) -> 2 | F11: =D11*E11 -> 2 | G11: =F11*$C11 -> 130000
A12: Parking Yard Out | B12: RFID Reader | C12: =_xlfn.IFNA(VLOOKUP(B12,Master!$A$3:$B$21,2,FALSE),0) -> 27000 | D12: 1 | E12: =VLOOKUP($A12,Master!$A$24:$B$37,2,FALSE) -> 2 | F12: =D12*E12 -> 2 | G12: =F12*$C12 -> 54000
A13: Parking Yard Out | B13: Display (2 Line) | C13: =_xlfn.IFNA(VLOOKUP(B13,Master!$A$3:$B$21,2,FALSE),0) -> 9200 | D13: 1 | E13: =VLOOKUP($A13,Master!$A$24:$B$37,2,FALSE) -> 2 | F13: =D13*E13 -> 2 | G13: =F13*$C13 -> 18400
A14: Parking Yard Out | B14: Traffic Light | C14: =_xlfn.IFNA(VLOOKUP(B14,Master!$A$3:$B$21,2,FALSE),0) -> 8000 | D14: 1 | E14: =VLOOKUP($A14,Master!$A$24:$B$37,2,FALSE) -> 2 | F14: =D14*E14 -> 2 | G14: =F14*$C14 -> 16000
A15: Parking Yard Out | B15: AT Controller | C15: =_xlfn.IFNA(VLOOKUP(B15,Master!$A$3:$B$21,2,FALSE),0) -> 16000 | D15: 1 | E15: =VLOOKUP($A15,Master!$A$24:$B$37,2,FALSE) -> 2 | F15: =D15*E15 -> 2 | G15: =F15*$C15 -> 32000
... A22: Old Gate Complex In | B22: Boom Barrier | C22: =_xlfn.IFNA(VLOOKUP(B22,Master!$A$3:$B$21,2,FALSE),0) -> 114500 | D22: 1 | E22: =VLOOKUP($A22,Master!$A$24:$B$37,2,FALSE) -> 3 | F22: =D22*E22 -> 3 | G22: =F22*$C22 -> 343500
A23: Old Gate Complex In | B23: Smart Camera | C23: =_xlfn.IFNA(VLOOKUP(B23,Master!$A$3:$B$21,2,FALSE),0) -> 7000 | D23: 2 | E23: =VLOOKUP($A23,Master!$A$24:$B$37,2,FALSE) -> 3 | F23: =D23*E23 -> 6 | G23: =F23*$C23 -> 42000 | H23: NVR
A24: Old Gate Complex In | B24: Printer Kiosk with Thermal Printer | C24: =_xlfn.IFNA(VLOOKUP(B24,Master!$A$3:$B$21,2,FALSE),0) -> 100000 | D24: 1 | E24: =VLOOKUP($A24,Master!$A$24:$B$37,2,FALSE) -> 3 | F24: =D24*E24 -> 3 | G24: =F24*$C24 -> 300000
A25: Old Gate Complex In | B25: Traffic Light | C25: =_xlfn.IFNA(VLOOKUP(B25,Master!$A$3:$B$21,2,FALSE),0) -> 8000 | D25: 1 | E25: =VLOOKUP($A25,Master!$A$24:$B$37,2,FALSE) -> 3 | F25: =D25*E25 -> 3 | G25: =F25*$C25 -> 24000
A26: Old Gate Complex In | B26: AT Controller | C26: =_xlfn.IFNA(VLOOKUP(B26,Master!$A$3:$B$21,2,FALSE),0) -> 16000 | D26: 1 | E26: =VLOOKUP($A26,Master!$A$24:$B$37,2,FALSE) -> 3 | F26: =D26*E26 -> 3 | G26: =F26*$C26 -> 48000
A27: Old Gate Complex Out | B27: RFID Reader | C27: =_xlfn.IFNA(VLOOKUP(B27,Master!$A$3:$B$21,2,FALSE),0) -> 27000 | D27: 1 | E27: =VLOOKUP($A27,Master!$A$24:$B$37,2,FALSE) -> 3 | F27: =D27*E27 -> 3 | G27: =F27*$C27 -> 81000
A28: Old Gate Complex Out | B28: Boom Barrier | C28: =_xlfn.IFNA(VLOOKUP(B28,Master!$A$3:$B$21,2,FALSE),0) -> 114500 | D28: 1 | E28: =VLOOKUP($A28,Master!$A$24:$B$37,2,FALSE) -> 3 | F28: =D28*E28 -> 3 | G28: =F28*$C28 -> 343500
A29: Old Gate Complex Out | B29: Smart Camera | C29: =_xlfn.IFNA(VLOOKUP(B29,Master!$A$3:$B$21,2,FALSE),0) -> 7000 | D29: 2 | E29: =VLOOKUP($A29,Master!$A$24:$B$37,2,FALSE) -> 3 | F29: =D29*E29 -> 6 | G29: =F29*$C29 -> 42000
A30: Old Gate Complex Out | B30: Printer Kiosk with Thermal Printer | C30: =_xlfn.IFNA(VLOOKUP(B30,Master!$A$3:$B$21,2,FALSE),0) -> 100000 | D30: 1 | E30: =VLOOKUP($A30,Master!$A$24:$B$37,2,FALSE) -> 3 | F30: =D30*E30 -> 3 | G30: =F30*$C30 -> 300000
A31: Old Gate Complex Out | B31: AT Controller | C31: =_xlfn.IFNA(VLOOKUP(B31,Master!$A$3:$B$21,2,FALSE),0) -> 16000 | D31: 1 | E31: =VLOOKUP($A31,Master!$A$24:$B$37,2,FALSE) -> 3 | F31: =D31*E31 -> 3 | G31: =F31*$C31 -> 48000
A32: New Gate Complex Out | B32: RFID Reader | C32: =_xlfn.IFNA(VLOOKUP(B32,Master!$A$3:$B$21,2,FALSE),0) -> 27000 | D32: 1 | E32: =VLOOKUP($A32,Master!$A$24:$B$37,2,FALSE) -> 3 | F32: =D32*E32 -> 3 | G32: =F32*$C32 -> 81000
A33: New Gate Complex Out | B33: Boom Barrier | C33: =_xlfn.IFNA(VLOOKUP(B33,Master!$A$3:$B$21,2,FALSE),0) -> 114500 | D33: 1 | E33: =VLOOKUP($A33,Master!$A$24:$B$37,2,FALSE) -> 3 | F33: =D33*E33 -> 3 | G33: =F33*$C33 -> 343500
A34: New Gate Complex Out | B34: Smart Camera | C34: =_xlfn.IFNA(VLOOKUP(B34,Master!$A$3:$B$21,2,FALSE),0) -> 7000 | D34: 5 | E34: =VLOOKUP($A34,Master!$A$24:$B$37,2,FALSE) -> 3 | F34: =D34*E34 -> 15 | G34: =F34*$C34 -> 105000
A35: New Gate Complex Out | B35: Traffic Light | C35: =_xlfn.IFNA(VLOOKUP(B35,Master!$A$3:$B$21,2,FALSE),0) -> 8000 | D35: 1 | E35: =VLOOKUP($A35,Master!$A$24:$B$37,2,FALSE) -> 3 | F35: =D35*E35 -> 3 | G35: =F35*$C35 -> 24000
... A54: Liquid Load/Unload | B54: Handheld RFID Reader | C54: =_xlfn.IFNA(VLOOKUP(B54,Master!$A$3:$B$21,2,FALSE),0) -> 66000 | D54: 1 | E54: =VLOOKUP($A54,Master!$A$24:$B$37,2,FALSE) -> 1 | F54: =D54*E54 -> 1 | G54: =F54*$C54 -> 66000
G55: =SUM(G4:G54) -> 5272300

Sheet Master
A2: Equipment | B2: Cost
A3: RFID Reader | B3: 27000 | C3: RFENERGIE - HR15
A4: Handheld RFID Reader | B4: 66000 | C4: Chainway - C72 - Handheld RFID Reader
A5: AT Controller | B5: 16000 | C5: In House
A6: ANPR Camera | B6: 65000 | C6: Hikvision - IDS-2CD7A45G0-IZ
A7: Smart Camera | B7: 7000 | C7: Hikvision - Bullet/Dom Camera 6 MP - DS-2CD3066G2-IS
A8: Tablet | B8: 41000 | C8: Chainway - P80 - Tablet Rugged Industrial Grade
A9: PA System (Open Yard) | B9: 28000 | C9: 5 Speakers - Ahuja Amplifier - SS250DP - Horn Speaker - SUH-25MT"
A10: Display (2 Line) | B10: 9200 | C10: In House
A11: Traffic Light | B11: 8000 | C11: In House
A12: Printer Kiosk with Thermal Printer | B12: 100000 | C12: Kisok Printer -
A13: Boom Barrier | B13: 114500 | C13: FAAC B614 Anti Hit 3 Mtr
A14: Boom Barrier Accessories | B14: 56200 | C14: BOOM BARRIER SPARE KIT - BG2000
A15: GI Pipe + Foundation + Junction Box | B15: =2200+1200+1200 -> 4600
A16: Traffic Light GI Pipe + Foundation + Junction Box | B16: =2200+1200+1200 -> 4600
A17: Camera Back GI Pipe + Foundation+Junction Box | B17: =2500+1200+1200 -> 4900
A18: Top + back View GI Pipe + Foundation+ Junction box | B18: =5000+4000+1200 -> 10200
A19: Kiosk Foundation | B19: 4000
A20: Boom Barrier Foundation | B20: 6000
A21: Boom Barrier Accessories | B21: 56200 | C21: BOOM BARRIER SPARE KIT - BG2000
A23: Location | B23: Lane
A24: Port Main Gate In | B24: 2
A25: Parking Yard Out | B25: 2
A26: New Gate Complex In | B26: 3
A27: Old Gate Complex In | B27: 3
A28: Old Gate Complex Out | B28: 3
A29: New Gate Complex Out | B29: 3
A30: Port Main Gate Out | B30: 2
A31: CFS Gate In | B31: 2
A32: CFS Gate Out | B32: 2
A33: Liquid Pass Gate In | B33: 2
A34: Liquid Load/Unload | B34: 1
A35: Liquid Pass Gate Out | B35: 1
... A37: Other | B37: 1
