Workbook

Sheet Budget-Complete
E2: Budgetary Quotation For Complete Solution
B3: Address - Corporate HQ : Axestrack Software Solutions Pvt. Ltd., Office No.-19, 6th Floor, Jaipur Electronic Market, Near Riddhi Siddhi, Gopalpura bypass, Jaipur - 302018 , Rajasthan, India
B4: GSTIN | C4: 08AACCH0299P1Z1 | E4: QUOTE # | G4: Date
B5: MSME No | C5: UDYAM-RJ-17-0051921 | E5: AMNS/SA/250430 | G5: =TODAY() -> 45853
B6: Contact | C6: Saket Agrawal | E6: Quote Validity : 15 days from submitted date
B7: Phone | C7: 7045054957
B8: Email Id | C8: Saket.agrawal@axestrack.com
B10: CUSTOMER INFO
B11: Name | C11: ArcelorMittal Nippon Steel India
B12: Location | C12: Sanaswadi-Pune
B13: Contact | C13: Dr. Dnyandev Badvar | E13: Phone | G13: 9158895606
B14: Email Id | C14: dnyandev.badvar@amns.in
B16: DESCRIPTION OF WORK
B17: Budgetary Commercials for the complete proposed solution aim to digitize the movement of Vehicles across the various stages of the plant
B18: S.No. | C18: Items | E18: Type | F18: Unit Price | G18: Amount
B19: 1 | C19: Hardware Cost | D19: Hardware | E19: One Time | F19: =Summary!E2 -> 4745866.7 | G19: =F19 -> 4745866.7
B20: 2 | C20: Implementation Cost | D20: Installation, Training & Configuration | E20: ='[1]Commercials Full'!E21 -> One Time | F20: ='Commercials Full-One Plant'!K17 -> 2666666.7 | G20: =F20 -> 2666666.7
D21: ERP Integration | E21: ='[1]Commercials Full'!E22 -> One Time | F21: ='Commercials Full-One Plant'!K18 -> 266666.67 | G21: =F21 -> 266666.67
C22: Project Management Cost | D22: Onsite Manpower for Support & Maintenance, Platform Subscription fees | E22: For 3 years | F22: =Summary!E3 -> 3261840 | G22: =F22 -> 3261840
B23: 3 | C23: AMC | D23: AMC-Second year Onwards | E23: For 2 years | F23: =Summary!#REF! -> #REF! | G23: =F23 -> #REF!
B24: Total Cost for 3 Years | G24: =SUM(G19:G23) -> #REF!
B26: Terms & Conditions
B27: - All the prices mentioned above are in rupees and exclusive of GST. Taxes as per applicable - AMC will not cover the physical damages and theft of hardware. - Civil work, Mounting poles, Power supply, LAN connectivity for hardware setup at all checkpoints/machines is under the scope of AMNS - The standard warranty period for Hardware of 1 year shall apply, as per OEM. - Contract period is for 3 Years and the costing is for 5 yards. -The commercials are a budgetary and can vary based on the actual scope of work and changes. -Assumption is, the existing hardware are in right condition and integratable. It may vary during the actual process of integration.
B28: Thanks for business with Axestrack Software Solution Pvt. Ltd.

Sheet Summary
A1: Sr No | B1: Details | D1: Full | E1: Phase I (NewShed) | F1: Phase II (50%*2) | G1: Phase III (80%*2)
A2: 1 | B2: Hardware and Implementation | C2: One Time | D2: ='Commercials Full-One Plant'!K20 -> 15817253 | E2: ='Commercials-Phase I'!K20 -> 4745866.7 | F2: ='Commercials-Phase II'!K20 -> 4479200 | G2: ='Commercials-Phase III'!K20 -> 6592186.7
A3: 3 | B3: Project Management Cost | C3: Opex | D3: ='Commercials Full-One Plant'!K23+'Commercials Full-One Plant'!K25 -> 7982784 | E3: ='Commercials-Phase I'!K23+'Commercials-Phase I'!K25 -> 3261840 | F3: ='Commercials-Phase II'!K23+'Commercials-Phase II'!K25 -> 2175840 | G3: ='Commercials-Phase III'!K23+'Commercials-Phase III'!K25 -> 2545104
B4: Total | D4: =SUM(D2:D3) -> 23800037 | E4: =SUM(E2:E3) -> 8007706.7 | F4: =SUM(F2:F3) -> 6655040 | G4: =SUM(G2:G3) -> 9137290.7

Sheet Commercials Full-One Plant
B2: Customer | D2: AM/NS Pune
B3: Date | D3: =TODAY() -> 45853
B4: Contract Year | D4: 3
B5: AMC Cost | D5: 0.1
B6: Hardware Transportation Cost | D6: 0.05
B7: Software Subscription cost per month Current | D7: 120000
B9: ERP Integration | D9: 200000
F11: Total Equipments
B12: Model | C12: Items | D12: Details | E12: Type | F12: Unit Cost | G12: Nos. of years | H12: Total Cost to Axestrack for 3 years | I12: Margin | J12: Unit Price with Margin | K12: Cost for 3 Years
B13: One Time Cost | C13: Hardware Cost | D13: Hardware Cost | E13: One Time | F13: ='Hardware List-BLE'!D7 -> 9202800 | H13: =F13 -> 9202800 | I13: 0.25 | J13: =H13/(1-I13) -> 12270400 | K13: =H13/(1-I13) -> 12270400
D14: Spares | E14: One Time | F14: 0 | H14: 0 | I14: 0.25 | J14: =H14/(1-I14) -> 0 | K14: =H14/(1-I14) -> 0
D15: Hardware Transportation cost | E15: One Time | F15: =(SUM(F13:F14)*$D$6) -> 460140 | H15: =(SUM(H13:H14)*$D$6) -> 460140 | I15: 0.25 | J15: =H15/(1-I15) -> 613520 | K15: =H15/(1-I15) -> 613520
D16: Total Hardware Cost | H16: =SUM(H13:H15) -> 9662940 | K16: =SUM(K13:K15) -> 12883920
C17: Implementation Cost (Implementation+Hypercare) | D17: Installation, Training & Configuration | E17: One Time | F17: 2000000 | H17: =F17 -> 2000000 | I17: 0.25 | J17: =H17/(1-I17) -> 2666666.7 | K17: =H17/(1-I17) -> 2666666.7
D18: ERP Integration | E18: One Time | F18: =D9 -> 200000 | H18: =F18 -> 200000 | I18: 0.25 | J18: =H18/(1-I18) -> 266666.67 | K18: =H18/(1-I18) -> 266666.67
D19: Total Installation, Setup & API Development Cost | H19: =SUM(H17:H18) -> 2200000 | K19: =SUM(K17:K18) -> 2933333.3
G20: Total One Time Cost | H20: =H16+H19 -> 11862940 | K20: =K16+K19 -> 15817253
B21: Subscription Fee | C21: Project Management Cost | D21: Onsite Manpower, Project Management, Support & Maintenance | E21: Per Year | F21: ='Manpower Cost New'!S8+'Manpower Cost New'!U26 -> 1086000 | G21: =$D$4 -> 3 | H21: =F21 -> 1086000 | I21: 0 | J21: =H21 -> 1086000 | K21: =J21 -> 1086000
C22: Annual Subscription fee | D22: Platform Subscription Fee | E22: Per Year | F22: =D7*12 -> 1440000 | G22: =$D$4 -> 3 | H22: =F22*G22 -> 4320000 | J22: 0 | K22: =H22 -> 4320000
G23: Total Subscription & PMO Cost for 3 Years | H23: =SUM(H21:H22) -> 5406000 | K23: =SUM(K21:K22) -> 5406000
B24: AMC | C24: AMC | D24: AMC from 2nd Year onwards | E24: Per Year | F24: =SUM(F13:F15)*$D$5 -> 966294 | G24: =G21-1 -> 2 | H24: =F24*G24 -> 1932588 | I24: 0.25 | J24: =H24/(1-I24) -> 2576784 | K24: =J24 -> 2576784
C25: AMC for 2 years | G25: AMC for 2 years | H25: =SUM(H24) -> 1932588 | K25: =K24 -> 2576784
G26: Total Cost of the Project for 3 Years | H26: =H20+H23+H25 -> 19201528 | I26: =1-H26/K26 -> 0.19321437 | K26: =K20+K23+K24 -> 23800037

Sheet Sheet2
A1: Hardware | B1: Qty | C1: Price | D1: Total
A2: RFID Reader | B2: 4 | C2: =VLOOKUP(A2,#REF!,2,0) -> #REF! | D2: =B2*C2 -> #REF!
A3: Traffic Light | B3: 1 | C3: =VLOOKUP(A3,#REF!,2,0) -> #REF! | D3: =B3*C3 -> #REF!
A4: ANPR Camera | B4: 1 | C4: =VLOOKUP(A4,#REF!,2,0) -> #REF! | D4: =B4*C4 -> #REF!
A5: Tablet (Industrial Grade) | B5: 2 | C5: =VLOOKUP(A5,#REF!,2,0) -> #REF! | D5: =B5*C5 -> #REF!
D6: =SUM(D2:D5) -> #REF!

Sheet Manpower Cost New
B2: Implementation | L2: Hypercare 3 months | N2: Onsite Manpower
B3: M1 to M6 | L3: M7 & M9 | N3: M4 to M36
B4: Installation, Training & Configuration Cost for phase 1 (a) | L4: Hypercare (a) (M7 to M9) | N4: Onsite Manpower, Support & Maintenance Cost (b) from M7 to M42
B5: Type of Manpower | C5: Count per shift | D5: Nos. of shifts | E5: Cost per Resource per month | F5: Duration in Months | G5: Total | L5: Type of Manpower | N5: Type of Manpower | O5: Count per shift | P5: Nos. of shifts | Q5: Cost per Resource per month | R5: Duration in Months | S5: Total
B6: PM | N6: Sr. CS (Offshore) | O6: 0 | P6: 1 | Q6: 50000 | R6: 33 | S6: 0
B7: Hardware Engineers | L7: PM | N7: Support Engineers (CPL) | O7: 1 | P7: 1 | Q7: 30000 | R7: 33 | S7: =Q7*R7 -> 990000
B8: Software Engineers | L8: Hardware Engineers | S8: =SUM(S6:S7) -> 990000
L10: Software Engineers (Offshore)
B14: Current Equipments | C14: Count | D14: Productivity per resource | E14: Resources Required | I14: Planned Equipments | J14: Count
B15: Machines | C15: =SUM(#REF!) -> #REF! | D15: 6 | E15: =ROUND(C15/D15,0) -> #REF! | I15: Machines | J15: =SUM(#REF!) -> #REF!
B16: Gate Lanes | C16: =SUM(#REF!) -> #REF! | D16: 7 | E16: =ROUND(C16/D16,0) -> #REF! | I16: Gate Lanes | J16: =SUM(#REF!) -> #REF!
B17: Vehicles | C17: =SUM(#REF!) -> #REF! | D17: 120 | E17: =ROUND(C17/D17,0) -> #REF! | I17: Vehicles | J17: =SUM(#REF!) -> #REF!
D18: Onsite | E18: =SUM(E15:E17) -> #REF!
D19: MIS | E19: =ROUND(E18/8,0) -> #REF!
D20: Total | E20: =E18+E19 -> #REF!
B22: Travel & Lodging | L22: Onsite Manpower (b) (M7 to M9) | N22: Travel & Lodging for Support
B23: Type of Manpower | C23: Count | D23: Travel Allowance | E23: Travel Cost | F23: Stay Cost per Day | G23: Days per trip | H23: Frequency | I23: Total | L23: Type of Manpower | N23: Type of Manpower | O23: Type | P23: Travel Allowance | Q23: Travel Cost | R23: Stay Cost per Day | S23: Days per trip | T23: Frequency (Annually) | U23: Total
B24: PM/Seniors | L24: PM/ Sr. CS (Onsite) | N24: Project Manager | O24: Per Year | P24: 1500 | Q24: 20000 | R24: 4500 | S24: 2 | T24: 1 | U24: =(P24*S24*T24)+(Q24*T24)+(R24*S24*T24) -> 32000
B25: Hardware Engineers | L25: Support Engineers (Onsite) | N25: Customer Success | O25: Per Year | P25: 1500 | Q25: 20000 | R25: 4500 | S25: 2 | T25: 2 | U25: =(T25*S25*P25)+(Q25*T25)+(R25*S25*T25) -> 64000
B26: Software Engineers | L26: MIS Support (Offshore) | T26: Total | U26: =SUM(U24:U25) -> 96000
G29: Rent | H29: month | I29: Total
F30: Per month rent
F31: Kitchen
H34: Total (B+C) | I34: =I32+I27 -> 0
B38: Total Implementation Cost (M1 to M6) (A+B+C) | C38: =G9+I34 -> 0 | N38: Live Project Management | O38: =(#REF!+#REF!+#REF!)+S8+(U26*3.5) -> #REF!
N39: (Travel+Lodging for Support considered for 3 years)
O41: =O38/2 -> #REF!

Sheet Sheet1
B2: =22*15 -> 330 | D2: =B2*27000 -> 8910000
B3: 6000 | D3: =70*B3 -> 420000

Sheet Hardware List-BLE
A1: Phase I
A2: Hardware | B2: Price | C2: Hardware Count | D2: Total Cost- One Plant
A3: BLE Gateway | B3: 11200 | C3: =SUM(J12:J14) -> 144 | D3: =B3*C3 -> 1612800 | H3: 0.5 | I3: 35 | J3: =I3*2 -> 70
A4: BLE Tags | B4: 1050 | C4: 6000 | D4: =B4*C4 -> 6300000 | H4: 0.8 | I4: =70*0.8 -> 56 | J4: =I4*2 -> 112
A5: Handheld Barcode Reader | B5: 15 | C5: 66000 | D5: =C5*B5 -> 990000 | J5: =J3+J4 -> 182
A6: High Configured System | B6: 3 | C6: 100000 | D6: =C6*B6 -> 300000
A7: Total | D7: =SUM(D3:D6) -> 9202800
H8: 42
A9: Phase I- New shed | H9: =21*2 -> 42
A10: Hardware | B10: Price | C10: Hardware Count | D10: Total Cost- One Plant | H10: =(42*0.8)*2 -> 67.2
A11: BLE Gateway | B11: 11200 | C11: =J12 -> 40 | D11: =B11*C11 -> 448000 | G11: Gateway
A12: BLE Tags | B12: 1050 | C12: =J17 -> 1666.6667 | D12: =B12*C12 -> 1750000 | G12: I | H12: x | I12: 40 | J12: =I12 -> 40
A13: Handheld Barcode Reader | B13: 5 | C13: 66000 | D13: =C13*B13 -> 330000 | G13: II | H13: 0.5 | I13: =I12/2 -> 20 | J13: =I13*2 -> 40
A14: High Configured System | B14: 1 | C14: 100000 | D14: =C14 -> 100000 | G14: III | H14: 0.8 | I14: =I12*H14 -> 32 | J14: =I14*2 -> 64
A15: Total | D15: =SUM(D11:D14) -> 2628000
A17: Phase II- 2 * 50% of New shed | G17: I | H17: X | I17: =6000/3.6 -> 1666.6667 | J17: =I17 -> 1666.6667
A18: Hardware | B18: Price | C18: Hardware Count | D18: Total Cost- One Plant | G18: II | H18: 0.5 | I18: =I17/2 -> 833.33333 | J18: =I18*2 -> 1666.6667
A19: BLE Gateway | B19: 11200 | C19: =J13 -> 40 | D19: =B19*C19 -> 448000 | G19: III | H19: 0.8 | I19: =H19*I17 -> 1333.3333 | J19: =I19*2 -> 2666.6667
A20: BLE Tags | B20: 1050 | C20: =J18 -> 1666.6667 | D20: =B20*C20 -> 1750000
A21: Handheld Barcode Reader | B21: 5 | C21: 66000 | D21: =C21*B21 -> 330000
A22: High Configured System | B22: 1 | C22: 100000 | D22: =C22 -> 100000
A23: Total | D23: =SUM(D19:D22) -> 2628000
A25: Phase III- 2*80% of New Shed
A26: Hardware | B26: Price | C26: Hardware Count | D26: Total Cost- One Plant
A27: BLE Gateway | B27: 11200 | C27: =J14 -> 64 | D27: =B27*C27 -> 716800 | F27: =D15+D23+D31 -> 9202800
A28: BLE Tags | B28: 1050 | C28: =J19 -> 2666.6667 | D28: =B28*C28 -> 2800000
A29: Handheld Barcode Reader | B29: 5 | C29: 66000 | D29: =C29*B29 -> 330000
A30: High Configured System | B30: 1 | C30: 100000 | D30: =C30 -> 100000
A31: Total | D31: =SUM(D27:D30) -> 3946800

Sheet Commercials-Phase I
B2: Customer | D2: AM/NS Pune
B3: Date | D3: =TODAY() -> 45853
B4: Contract Year | D4: 3
B5: AMC Cost | D5: 0.1
B6: Hardware Transportation Cost | D6: 0.05
B7: Software Subscription cost per month Current | D7: 40000
B9: ERP Integration | D9: 200000
F11: Total Equipments
B12: Model | C12: Items | D12: Details | E12: Type | F12: Unit Cost | G12: Nos. of years | H12: Total Cost to Axestrack for 3 years | I12: Margin | J12: Unit Price with Margin | K12: Cost for 3 Years
B13: One Time Cost | C13: Hardware Cost | D13: Hardware Cost | E13: One Time | F13: ='Hardware List-BLE'!D15 -> 2628000 | H13: =F13 -> 2628000 | I13: 0.25 | J13: =H13/(1-I13) -> 3504000 | K13: =H13/(1-I13) -> 3504000
D14: Spares | E14: One Time | F14: 0 | H14: 0 | I14: 0.25 | J14: =H14/(1-I14) -> 0 | K14: =H14/(1-I14) -> 0
D15: Hardware Transportation cost | E15: One Time | F15: =(SUM(F13:F14)*$D$6) -> 131400 | H15: =(SUM(H13:H14)*$D$6) -> 131400 | I15: 0.25 | J15: =H15/(1-I15) -> 175200 | K15: =H15/(1-I15) -> 175200
D16: Total Hardware Cost | H16: =SUM(H13:H15) -> 2759400 | K16: =SUM(K13:K15) -> 3679200
C17: Implementation Cost (Implementation+Hypercare) | D17: Installation, Training & Configuration | E17: One Time | F17: 600000 | H17: =F17 -> 600000 | I17: 0.25 | J17: =H17/(1-I17) -> 800000 | K17: =H17/(1-I17) -> 800000
D18: ERP Integration | E18: One Time | F18: =D9 -> 200000 | H18: =F18 -> 200000 | I18: 0.25 | J18: =H18/(1-I18) -> 266666.67 | K18: =H18/(1-I18) -> 266666.67
D19: Total Installation, Setup & API Development Cost | H19: =SUM(H17:H18) -> 800000 | K19: =SUM(K17:K18) -> 1066666.7
G20: Total One Time Cost | H20: =H16+H19 -> 3559400 | K20: =K16+K19 -> 4745866.7
B21: Subscription Fee | C21: Project Management Cost | D21: Onsite Manpower, Project Management, Support & Maintenance | E21: Per Year | F21: ='Manpower Cost New'!S8+'Manpower Cost New'!U26 -> 1086000 | G21: =$D$4 -> 3 | H21: =F21 -> 1086000 | I21: 0 | J21: =H21 -> 1086000 | K21: =J21 -> 1086000
C22: Annual Subscription fee | D22: Platform Subscription Fee | E22: Per Year | F22: =D7*12 -> 480000 | G22: =$D$4 -> 3 | H22: =F22*G22 -> 1440000 | J22: 0 | K22: =H22 -> 1440000
G23: Total Subscription & PMO Cost for 3 Years | H23: =SUM(H21:H22) -> 2526000 | K23: =SUM(K21:K22) -> 2526000
B24: AMC | C24: AMC | D24: AMC from 2nd Year onwards | E24: Per Year | F24: =SUM(F13:F15)*$D$5 -> 275940 | G24: =G21-1 -> 2 | H24: =F24*G24 -> 551880 | I24: 0.25 | J24: =H24/(1-I24) -> 735840 | K24: =J24 -> 735840
C25: AMC for 2 years | G25: AMC for 2 years | H25: =SUM(H24) -> 551880 | K25: =K24 -> 735840
G26: Total Cost of the Project for 3 Years | H26: =H20+H23+H25 -> 6637280 | I26: =1-H26/K26 -> 0.17113847 | K26: =K20+K23+K24 -> 8007706.7

Sheet Commercials-Phase II
B2: Customer | D2: AM/NS Pune
B3: Date | D3: =TODAY() -> 45853
B4: Contract Year | D4: 3
B5: AMC Cost | D5: 0.1
B6: Hardware Transportation Cost | D6: 0.05
B7: Software Subscription cost per month Current | D7: 40000
B9: ERP Integration | D9: 0
F11: Total Equipments
B12: Model | C12: Items | D12: Details | E12: Type | F12: Unit Cost | G12: Nos. of years | H12: Total Cost to Axestrack for 3 years | I12: Margin | J12: Unit Price with Margin | K12: Cost for 3 Years
B13: One Time Cost | C13: Hardware Cost | D13: Hardware Cost | E13: One Time | F13: ='Hardware List-BLE'!D23 -> 2628000 | H13: =F13 -> 2628000 | I13: 0.25 | J13: =H13/(1-I13) -> 3504000 | K13: =H13/(1-I13) -> 3504000
D14: Spares | E14: One Time | F14: 0 | H14: 0 | I14: 0.25 | J14: =H14/(1-I14) -> 0 | K14: =H14/(1-I14) -> 0
D15: Hardware Transportation cost | E15: One Time | F15: =(SUM(F13:F14)*$D$6) -> 131400 | H15: =(SUM(H13:H14)*$D$6) -> 131400 | I15: 0.25 | J15: =H15/(1-I15) -> 175200 | K15: =H15/(1-I15) -> 175200
D16: Total Hardware Cost | H16: =SUM(H13:H15) -> 2759400 | K16: =SUM(K13:K15) -> 3679200
C17: Implementation Cost (Implementation+Hypercare) | D17: Installation, Training & Configuration | E17: One Time | F17: 600000 | H17: =F17 -> 600000 | I17: 0.25 | J17: =H17/(1-I17) -> 800000 | K17: =H17/(1-I17) -> 800000
D18: ERP Integration | E18: One Time | F18: =D9 -> 0 | H18: =F18 -> 0 | I18: 0.25 | J18: =H18/(1-I18) -> 0 | K18: =H18/(1-I18) -> 0
D19: Total Installation, Setup & API Development Cost | H19: =SUM(H17:H18) -> 600000 | K19: =SUM(K17:K18) -> 800000
G20: Total One Time Cost | H20: =H16+H19 -> 3359400 | K20: =K16+K19 -> 4479200
B21: Subscription Fee | C21: Project Management Cost | D21: Onsite Manpower, Project Management, Support & Maintenance | E21: Per Year | F21: 0 | G21: =$D$4 -> 3 | H21: =F21 -> 0 | I21: 0 | J21: =H21 -> 0 | K21: =J21 -> 0
C22: Annual Subscription fee | D22: Platform Subscription Fee | E22: Per Year | F22: =D7*12 -> 480000 | G22: =$D$4 -> 3 | H22: =F22*G22 -> 1440000 | J22: 0 | K22: =H22 -> 1440000
G23: Total Subscription & PMO Cost for 3 Years | H23: =SUM(H21:H22) -> 1440000 | K23: =SUM(K21:K22) -> 1440000
B24: AMC | C24: AMC | D24: AMC from 2nd Year onwards | E24: Per Year | F24: =SUM(F13:F15)*$D$5 -> 275940 | G24: =G21-1 -> 2 | H24: =F24*G24 -> 551880 | I24: 0.25 | J24: =H24/(1-I24) -> 735840 | K24: =J24 -> 735840
C25: AMC for 2 years | G25: AMC for 2 years | H25: =SUM(H24) -> 551880 | K25: =K24 -> 735840
G26: Total Cost of the Project for 3 Years | H26: =H20+H23+H25 -> 5351280 | I26: =1-H26/K26 -> 0.19590566 | K26: =K20+K23+K24 -> 6655040

Sheet Commercials-Phase III
B2: Customer | D2: AM/NS Pune
B3: Date | D3: =TODAY() -> 45853
B4: Contract Year | D4: 3
B5: AMC Cost | D5: 0.1
B6: Hardware Transportation Cost | D6: 0.05
B7: Software Subscription cost per month Current | D7: 40000
B9: ERP Integration | D9: 200000
F11: Total Equipments
B12: Model | C12: Items | D12: Details | E12: Type | F12: Unit Cost | G12: Nos. of years | H12: Total Cost to Axestrack for 3 years | I12: Margin | J12: Unit Price with Margin | K12: Cost for 3 Years
B13: One Time Cost | C13: Hardware Cost | D13: Hardware Cost | E13: One Time | F13: ='Hardware List-BLE'!D31 -> 3946800 | H13: =F13 -> 3946800 | I13: 0.25 | J13: =H13/(1-I13) -> 5262400 | K13: =H13/(1-I13) -> 5262400
D14: Spares | E14: One Time | F14: 0 | H14: 0 | I14: 0.25 | J14: =H14/(1-I14) -> 0 | K14: =H14/(1-I14) -> 0
D15: Hardware Transportation cost | E15: One Time | F15: =(SUM(F13:F14)*$D$6) -> 197340 | H15: =(SUM(H13:H14)*$D$6) -> 197340 | I15: 0.25 | J15: =H15/(1-I15) -> 263120 | K15: =H15/(1-I15) -> 263120
D16: Total Hardware Cost | H16: =SUM(H13:H15) -> 4144140 | K16: =SUM(K13:K15) -> 5525520
C17: Implementation Cost (Implementation+Hypercare) | D17: Installation, Training & Configuration | E17: One Time | F17: 800000 | H17: =F17 -> 800000 | I17: 0.25 | J17: =H17/(1-I17) -> 1066666.7 | K17: =H17/(1-I17) -> 1066666.7
D18: ERP Integration | E18: One Time | F18: 0 | H18: =F18 -> 0 | I18: 0.25 | J18: =H18/(1-I18) -> 0 | K18: =H18/(1-I18) -> 0
D19: Total Installation, Setup & API Development Cost | H19: =SUM(H17:H18) -> 800000 | K19: =SUM(K17:K18) -> 1066666.7
G20: Total One Time Cost | H20: =H16+H19 -> 4944140 | K20: =K16+K19 -> 6592186.7
B21: Subscription Fee | C21: Project Management Cost | D21: Onsite Manpower, Project Management, Support & Maintenance | E21: Per Year | F21: 0 | G21: =$D$4 -> 3 | H21: =F21 -> 0 | I21: 0 | J21: =H21 -> 0 | K21: =J21 -> 0
C22: Annual Subscription fee | D22: Platform Subscription Fee | E22: Per Year | F22: =D7*12 -> 480000 | G22: =$D$4 -> 3 | H22: =F22*G22 -> 1440000 | J22: 0 | K22: =H22 -> 1440000
G23: Total Subscription & PMO Cost for 3 Years | H23: =SUM(H21:H22) -> 1440000 | K23: =SUM(K21:K22) -> 1440000
B24: AMC | C24: AMC | D24: AMC from 2nd Year onwards | E24: Per Year | F24: =SUM(F13:F15)*$D$5 -> 414414 | G24: =G21-1 -> 2 | H24: =F24*G24 -> 828828 | I24: 0.25 | J24: =H24/(1-I24) -> 1105104 | K24: =J24 -> 1105104
C25: AMC for 2 years | G25: AMC for 2 years | H25: =SUM(H24) -> 828828 | K25: =K24 -> 1105104
G26: Total Cost of the Project for 3 Years | H26: =H20+H23+H25 -> 7212968 | I26: =1-H26/K26 -> 0.21060101 | K26: =K20+K23+K24 -> 9137290.7
K27: ='Commercials-Phase II'!K26 -> 6655040
K28: ='Commercials-Phase I'!K26 -> 8007706.7

Sheet Commercials Full-RFID
B2: Customer | D2: AM/NS Pune
B3: Date | D3: =TODAY() -> 45853
B4: Contract Year | D4: 3
B5: AMC Cost | D5: 0.1
B6: Hardware Transportation Cost | D6: 0.05
B7: Software Subscription cost per month Current | D7: 120000
B9: ERP Integration | D9: 200000
F11: Total Equipments
B12: Model | C12: Items | D12: Details | E12: Type | F12: Unit Cost | G12: Nos. of years | H12: Total Cost to Axestrack for 3 years | I12: Margin | J12: Unit Price with Margin | K12: Cost for 3 Years
B13: One Time Cost | C13: Hardware Cost | D13: Hardware Cost | E13: One Time | F13: ='Hardware List-RFID'!D7 -> 2810000 | H13: =F13 -> 2810000 | I13: 0.25 | J13: =H13/(1-I13) -> 3746666.7 | K13: =H13/(1-I13) -> 3746666.7
D14: Spares | E14: One Time | F14: 0 | H14: 0 | I14: 0.25 | J14: =H14/(1-I14) -> 0 | K14: =H14/(1-I14) -> 0
D15: Hardware Transportation cost | E15: One Time | F15: =(SUM(F13:F14)*$D$6) -> 140500 | H15: =(SUM(H13:H14)*$D$6) -> 140500 | I15: 0.25 | J15: =H15/(1-I15) -> 187333.33 | K15: =H15/(1-I15) -> 187333.33
D16: Total Hardware Cost | H16: =SUM(H13:H15) -> 2950500 | K16: =SUM(K13:K15) -> 3934000
C17: Implementation Cost (Implementation+Hypercare) | D17: Installation, Training & Configuration | E17: One Time | F17: 1000000 | H17: =F17 -> 1000000 | I17: 0.25 | J17: =H17/(1-I17) -> 1333333.3 | K17: =H17/(1-I17) -> 1333333.3
D18: ERP Integration | E18: One Time | F18: =D9 -> 200000 | H18: =F18 -> 200000 | I18: 0.25 | J18: =H18/(1-I18) -> 266666.67 | K18: =H18/(1-I18) -> 266666.67
D19: Total Installation, Setup & API Development Cost | H19: =SUM(H17:H18) -> 1200000 | K19: =SUM(K17:K18) -> 1600000
G20: Total One Time Cost | H20: =H16+H19 -> 4150500 | K20: =K16+K19 -> 5534000
B21: Subscription Fee | C21: Project Management Cost | D21: Onsite Manpower, Project Management, Support & Maintenance | E21: Per Year | F21: ='Manpower Cost New'!S8+'Manpower Cost New'!U26 -> 1086000 | G21: =$D$4 -> 3 | H21: =F21 -> 1086000 | I21: 0 | J21: =H21 -> 1086000 | K21: =J21 -> 1086000
C22: Annual Subscription fee | D22: Platform Subscription Fee | E22: Per Year | F22: =D7*12 -> 1440000 | G22: =$D$4 -> 3 | H22: =F22*G22 -> 4320000 | J22: 0 | K22: =H22 -> 4320000
G23: Total Subscription & PMO Cost for 3 Years | H23: =SUM(H21:H22) -> 5406000 | K23: =SUM(K21:K22) -> 5406000
B24: AMC | C24: AMC | D24: AMC from 2nd Year onwards | E24: Per Year | F24: =('Hardware List-RFID'!D5+'Hardware List-RFID'!D6)*D5 -> 227000 | G24: =G21-1 -> 2 | H24: =F24*G24 -> 454000 | I24: 0.25 | J24: =H24/(1-I24) -> 605333.33 | K24: =J24 -> 605333.33
C25: AMC for 2 years | G25: AMC for 2 years | H25: =SUM(H24) -> 454000 | K25: =K24 -> 605333.33
G26: Total Cost of the Project for 3 Years | H26: =H20+H23+H25 -> 10010500 | I26: =1-H26/K26 -> 0.13293972 | K26: =K20+K23+K25 -> 11545333

Sheet Hardware List-RFID
A1: Phase I
A2: Hardware | B2: Price | C2: Hardware Count | D2: Total Cost- One Plant
A3: RFID Tags For coils | B3: 60 | C3: =(6000+200) -> 6200 | D3: =C3*B3 -> 372000
A4: RFID Tags for Crane | B4: 60 | C4: =(540+20)*5 -> 2800 | D4: =C4*B4 -> 168000 | I4: =(12*21)*2 -> 504
A5: RFID Reader | B5: 40000 | C5: =(4*5) -> 20 | D5: =B5*C5 -> 800000
A6: Handheld RFID Reader | B6: 70000 | C6: =10+11 -> 21 | D6: =B6*C6 -> 1470000
A7: Total | D7: =SUM(D3:D6) -> 2810000
A9: Phase I- New shed
A10: Hardware | B10: Price | C10: Hardware Count | D10: Total Cost- One Plant
A11: RFID Tags For coils | B11: 60 | C11: =J12+200 -> 1866.6667 | D11: =C11*B11 -> 112000
A12: RFID Tags for Crane | B12: 60 | C12: 560 | D12: =C12*B12 -> 33600 | G12: I | H12: X | I12: =6000/3.6 -> 1666.6667 | J12: =I12 -> 1666.6667
A13: RFID Reader | B13: 40000 | C13: 4 | D13: =B13*C13 -> 160000 | G13: II | H13: 0.5 | I13: =I12/2 -> 833.33333 | J13: =I13*2 -> 1666.6667
A14: Handheld RFID Reader | B14: 70000 | C14: 8 | D14: =B14*C14 -> 560000 | G14: III | H14: 0.8 | I14: =H14*I12 -> 1333.3333 | J14: =I14*2 -> 2666.6667
A15: Total | D15: =SUM(D11:D14) -> 865600
A17: Phase II- 2* 50% of New shed
A18: Hardware | B18: Price | C18: Hardware Count | D18: Total Cost- One Plant | H18: =D15+D23+D30 -> 2810000
A19: RFID Tags For coils | B19: 60 | C19: =J13 -> 1666.6667 | D19: =C19*B19 -> 100000
A20: RFID Tags for Crane | B20: 60 | C20: 1120 | D20: =C20*B20 -> 67200
A21: RFID Reader | B21: 40000 | C21: 8 | D21: =B21*C21 -> 320000
A22: Handheld RFID Reader | B22: 70000 | C22: 5 | D22: =B22*C22 -> 350000
A23: Total | D23: =SUM(D19:D22) -> 837200
A24: Phase III 2* 80% of new shed
A25: Hardware | B25: Price | C25: Hardware Count | D25: Total Cost- One Plant
A26: RFID Tags For coils | B26: 60 | C26: =J14 -> 2666.6667 | D26: =C26*B26 -> 160000
A27: RFID Tags for Crane | B27: 60 | C27: 1120 | D27: =C27*B27 -> 67200
A28: RFID Reader | B28: 40000 | C28: 8 | D28: =B28*C28 -> 320000
A29: Handheld RFID Reader | B29: 70000 | C29: 8 | D29: =B29*C29 -> 560000
A30: Total | D30: =SUM(D26:D29) -> 1107200

Sheet Commercials Full-RFID Phase I
B2: Customer | D2: AM/NS Pune
B3: Date | D3: =TODAY() -> 45853
B4: Contract Year | D4: 3
B5: AMC Cost | D5: 0.1
B6: Hardware Transportation Cost | D6: 0.05
B7: Software Subscription cost per month Current | D7: 40000
B9: ERP Integration | D9: 200000
F11: Total Equipments
B12: Model | C12: Items | D12: Details | E12: Type | F12: Unit Cost | G12: Nos. of years | H12: Total Cost to Axestrack for 3 years | I12: Margin | J12: Unit Price with Margin | K12: Cost for 3 Years
B13: One Time Cost | C13: Hardware Cost | D13: Hardware Cost | E13: One Time | F13: ='Hardware List-RFID'!D15 -> 865600 | H13: =F13 -> 865600 | I13: 0.25 | J13: =H13/(1-I13) -> 1154133.3 | K13: =H13/(1-I13) -> 1154133.3
D14: Spares | E14: One Time | F14: 0 | H14: 0 | I14: 0.25 | J14: =H14/(1-I14) -> 0 | K14: =H14/(1-I14) -> 0
D15: Hardware Transportation cost | E15: One Time | F15: =(SUM(F13:F14)*$D$6) -> 43280 | H15: =(SUM(H13:H14)*$D$6) -> 43280 | I15: 0.25 | J15: =H15/(1-I15) -> 57706.667 | K15: =H15/(1-I15) -> 57706.667
D16: Total Hardware Cost | H16: =SUM(H13:H15) -> 908880 | K16: =SUM(K13:K15) -> 1211840
C17: Implementation Cost (Implementation+Hypercare) | D17: Installation, Training & Configuration | E17: One Time | F17: 300000 | H17: =F17 -> 300000 | I17: 0.25 | J17: =H17/(1-I17) -> 400000 | K17: =H17/(1-I17) -> 400000
D18: ERP Integration | E18: One Time | F18: =D9 -> 200000 | H18: =F18 -> 200000 | I18: 0.25 | J18: =H18/(1-I18) -> 266666.67 | K18: =H18/(1-I18) -> 266666.67
D19: Total Installation, Setup & API Development Cost | H19: =SUM(H17:H18) -> 500000 | K19: =SUM(K17:K18) -> 666666.67
G20: Total One Time Cost | H20: =H16+H19 -> 1408880 | K20: =K16+K19 -> 1878506.7
B21: Subscription Fee | C21: Project Management Cost | D21: Onsite Manpower, Project Management, Support & Maintenance | E21: Per Year | F21: ='Manpower Cost New'!S8+'Manpower Cost New'!U26 -> 1086000 | G21: =$D$4 -> 3 | H21: =F21 -> 1086000 | I21: 0 | J21: =H21 -> 1086000 | K21: =J21 -> 1086000
C22: Annual Subscription fee | D22: Platform Subscription Fee | E22: Per Year | F22: =D7*12 -> 480000 | G22: =$D$4 -> 3 | H22: =F22*G22 -> 1440000 | J22: 0 | K22: =H22 -> 1440000
G23: Total Subscription & PMO Cost for 3 Years | H23: =SUM(H21:H22) -> 2526000 | K23: =SUM(K21:K22) -> 2526000
B24: AMC | C24: AMC | D24: AMC from 2nd Year onwards | E24: Per Year | F24: =('Hardware List-RFID'!D13+'Hardware List-RFID'!D14)*D5 -> 72000 | G24: =G21-1 -> 2 | H24: =F24*G24 -> 144000 | I24: 0.25 | J24: =H24/(1-I24) -> 192000 | K24: =J24 -> 192000
C25: AMC for 2 years | G25: AMC for 2 years | H25: =SUM(H24) -> 144000 | K25: =K24 -> 192000
G26: Total Cost of the Project for 3 Years | H26: =H20+H23+H25 -> 4078880 | I26: =1-H26/K26 -> 0.11261306 | K26: =K20+K23+K25 -> 4596506.7

Sheet Commercials-RFID Phase II
B2: Customer | D2: AM/NS Pune
B3: Date | D3: =TODAY() -> 45853
B4: Contract Year | D4: 3
B5: AMC Cost | D5: 0.1
B6: Hardware Transportation Cost | D6: 0.05
B7: Software Subscription cost per month Current | D7: 40000
B9: ERP Integration | D9: 0
F11: Total Equipments
B12: Model | C12: Items | D12: Details | E12: Type | F12: Unit Cost | G12: Nos. of years | H12: Total Cost to Axestrack for 3 years | I12: Margin | J12: Unit Price with Margin | K12: Cost for 3 Years
B13: One Time Cost | C13: Hardware Cost | D13: Hardware Cost | E13: One Time | F13: ='Hardware List-RFID'!D23 -> 837200 | H13: =F13 -> 837200 | I13: 0.25 | J13: =H13/(1-I13) -> 1116266.7 | K13: =H13/(1-I13) -> 1116266.7
D14: Spares | E14: One Time | F14: 0 | H14: 0 | I14: 0.25 | J14: =H14/(1-I14) -> 0 | K14: =H14/(1-I14) -> 0
D15: Hardware Transportation cost | E15: One Time | F15: =(SUM(F13:F14)*$D$6) -> 41860 | H15: =(SUM(H13:H14)*$D$6) -> 41860 | I15: 0.25 | J15: =H15/(1-I15) -> 55813.333 | K15: =H15/(1-I15) -> 55813.333
D16: Total Hardware Cost | H16: =SUM(H13:H15) -> 879060 | K16: =SUM(K13:K15) -> 1172080
C17: Implementation Cost (Implementation+Hypercare) | D17: Installation, Training & Configuration | E17: One Time | F17: 300000 | H17: =F17 -> 300000 | I17: 0.25 | J17: =H17/(1-I17) -> 400000 | K17: =H17/(1-I17) -> 400000
D18: ERP Integration | E18: One Time | F18: =D9 -> 0 | H18: =F18 -> 0 | I18: 0.25 | J18: =H18/(1-I18) -> 0 | K18: =H18/(1-I18) -> 0
D19: Total Installation, Setup & API Development Cost | H19: =SUM(H17:H18) -> 300000 | K19: =SUM(K17:K18) -> 400000
G20: Total One Time Cost | H20: =H16+H19 -> 1179060 | K20: =K16+K19 -> 1572080
B21: Subscription Fee | C21: Project Management Cost | D21: Onsite Manpower, Project Management, Support & Maintenance | E21: Per Year | F21: 0 | G21: =$D$4 -> 3 | H21: =F21 -> 0 | I21: 0 | J21: =H21 -> 0 | K21: =J21 -> 0
C22: Annual Subscription fee | D22: Platform Subscription Fee | E22: Per Year | F22: =D7*12 -> 480000 | G22: =$D$4 -> 3 | H22: =F22*G22 -> 1440000 | J22: 0 | K22: =H22 -> 1440000
G23: Total Subscription & PMO Cost for 3 Years | H23: =SUM(H21:H22) -> 1440000 | K23: =SUM(K21:K22) -> 1440000
B24: AMC | C24: AMC | D24: AMC from 2nd Year onwards | E24: Per Year | F24: =('Hardware List-RFID'!D21+'Hardware List-RFID'!D22)*D5 -> 67000 | G24: =G21-1 -> 2 | H24: =F24*G24 -> 134000 | I24: 0.25 | J24: =H24/(1-I24) -> 178666.67 | K24: =J24 -> 178666.67
C25: AMC for 2 years | G25: AMC for 2 years | H25: =SUM(H24) -> 134000 | K25: =K24 -> 178666.67
G26: Total Cost of the Project for 3 Years | H26: =H20+H23+H25 -> 2753060 | I26: =1-H26/K26 -> 0.13717374 | K26: =K20+K23+K25 -> 3190746.7

Sheet Commercials-RFID Phase III
B2: Customer | D2: AM/NS Pune
B3: Date | D3: =TODAY() -> 45853
B4: Contract Year | D4: 3
B5: AMC Cost | D5: 0.1
B6: Hardware Transportation Cost | D6: 0.05
B7: Software Subscription cost per month Current | D7: 40000
B9: ERP Integration | D9: 0
F11: Total Equipments
B12: Model | C12: Items | D12: Details | E12: Type | F12: Unit Cost | G12: Nos. of years | H12: Total Cost to Axestrack for 3 years | I12: Margin | J12: Unit Price with Margin | K12: Cost for 3 Years
B13: One Time Cost | C13: Hardware Cost | D13: Hardware Cost | E13: One Time | F13: ='Hardware List-RFID'!D30 -> 1107200 | H13: =F13 -> 1107200 | I13: 0.25 | J13: =H13/(1-I13) -> 1476266.7 | K13: =H13/(1-I13) -> 1476266.7
D14: Spares | E14: One Time | F14: 0 | H14: 0 | I14: 0.25 | J14: =H14/(1-I14) -> 0 | K14: =H14/(1-I14) -> 0
D15: Hardware Transportation cost | E15: One Time | F15: =(SUM(F13:F14)*$D$6) -> 55360 | H15: =(SUM(H13:H14)*$D$6) -> 55360 | I15: 0.25 | J15: =H15/(1-I15) -> 73813.333 | K15: =H15/(1-I15) -> 73813.333
D16: Total Hardware Cost | H16: =SUM(H13:H15) -> 1162560 | K16: =SUM(K13:K15) -> 1550080
C17: Implementation Cost (Implementation+Hypercare) | D17: Installation, Training & Configuration | E17: One Time | F17: 400000 | H17: =F17 -> 400000 | I17: 0.25 | J17: =H17/(1-I17) -> 533333.33 | K17: =H17/(1-I17) -> 533333.33
D18: ERP Integration | E18: One Time | F18: =D9 -> 0 | H18: =F18 -> 0 | I18: 0.25 | J18: =H18/(1-I18) -> 0 | K18: =H18/(1-I18) -> 0
D19: Total Installation, Setup & API Development Cost | H19: =SUM(H17:H18) -> 400000 | K19: =SUM(K17:K18) -> 533333.33
G20: Total One Time Cost | H20: =H16+H19 -> 1562560 | K20: =K16+K19 -> 2083413.3
B21: Subscription Fee | C21: Project Management Cost | D21: Onsite Manpower, Project Management, Support & Maintenance | E21: Per Year | F21: 0 | G21: =$D$4 -> 3 | H21: =F21 -> 0 | I21: 0 | J21: =H21 -> 0 | K21: =J21 -> 0
C22: Annual Subscription fee | D22: Platform Subscription Fee | E22: Per Year | F22: =D7*12 -> 480000 | G22: =$D$4 -> 3 | H22: =F22*G22 -> 1440000 | J22: 0 | K22: =H22 -> 1440000
G23: Total Subscription & PMO Cost for 3 Years | H23: =SUM(H21:H22) -> 1440000 | K23: =SUM(K21:K22) -> 1440000
B24: AMC | C24: AMC | D24: AMC from 2nd Year onwards | E24: Per Year | F24: =('Hardware List-RFID'!D28+'Hardware List-RFID'!D29)*D5 -> 88000 | G24: =G21-1 -> 2 | H24: =F24*G24 -> 176000 | I24: 0.25 | J24: =H24/(1-I24) -> 234666.67 | K24: =J24 -> 234666.67
C25: AMC for 2 years | G25: AMC for 2 years | H25: =SUM(H24) -> 176000 | K25: =K24 -> 234666.67
G26: Total Cost of the Project for 3 Years | H26: =H20+H23+H25 -> 3178560 | I26: =1-H26/K26 -> 0.1542064 | K26: =K20+K23+K25 -> 3758080
K27: ='Commercials-RFID Phase II'!K26 -> 3190746.7
K28: ='Commercials Full-RFID Phase I'!K26 -> 4596506.7
