Workbook

Sheet Quotation
F1: Quotation
B2: Address - Corporate HQ : Axestrack Software Solutions Pvt. Ltd., Office No.-19, 6th Floor, Jaipur Electronic Market, Near Riddhi Siddhi, Gopalpura bypass, Jaipur - 302018 , Rajasthan, India
B3: GSTIN | D3: 08AACCH0299P1Z1 | E3: QUOTE # | F3: DATE
B4: MSME No | D4: UDYAM-RJ-17-0051921 | E4: AM/AB/20250711 | F4: =TODAY() -> 45863
B5: Contact Person | D5: Mr. Abhilash Jain
B6: Phone | D6: +91 9928151368 | E6: Quote Validity : 15 days from submitted date
B7: Email Id | D7: abhilash.jain@axestrack.com
B9: CUSTOMER INFO
B10: Company Name | D10: Amazon India
B11: Address | D11: World Trade Centre, 1st Cross Rd, Milk Colony, Subramanyanagar, 2 State, Rajajinagar, Bengaluru, Karnataka 560055
B12: Contact Person | D12: Mr. Vinod Kumar T | E12: Phone | F12: +91 99017 67680
B13: Email Id | D13: vinok@amazon.com
B15: DESCRIPTION OF WORK
B16: ITCT (Integrated Telematics Command Tower)
B17: S.No. | C17: Items | F17: Type | G17: Amount (in INR)
B18: 1 | C18: aOS Digital Layer (Consolidated Single View for Multi Vendor Video Telematics, Analytical Dashboard, Reports & Notifications) | F18: Per Trip day | G18: 35
B19: 2 | C19: Managed Control Tower - Accident Prevention (L1)* (Real Time Intervention for accident prevention on Critical alerts) | F19: Per Trip day | G19: 50
B20: 3 | C20: Managed Control Tower - Safety Compliance (L1+L2)* (Real Time Intervention for accident prevention and Safety Compliance alerts) | F20: Per Trip day | G20: 75
B21: 4 | C21: Managed Control Tower - Performance Management (L1+L2+L3)* (Real Time Intervention for accident prevention, Safety Compliance & performance management) | F21: Per Trip day | G21: 125
B22: 5 | C22: Setup Fee (Design, Onboarding, Training & Configuration) | F22: One Time | G22: 500000
B23: 6 | C23: Video Telematics Integration Fee (API integration with Video Telematics Providers) | F23: One Time Per Vendor | G23: 150000
B24: 7 | C24: ERP Integration Fee (API integration with Amazon's ERP) | F24: One Time | G24: 500000
B25: * : Refer next page for detailed description
B27: Kindly refer to Next Page for the Terms & Conditions
B29: Terms & Conditions
B30: • All the prices mentioned above are in INR and exclusive of GST. Taxes as applicable • Above estimates is based on received details; any formal change or upgrade in solution features (beyond those deployed during onboarding) will incur additional charges. • Minimum Contract period will be for 3 Years • During the setup phase, Axestrack's consultants' Lodging, Food & Accommodation will be provided by Amazon Payment Terms: • The Setup charges will need to be paid upfront within 7 days of PO release • Recurring payment will be on monthly basis • 100% payments to be made within 15 days from the date of receipt of original or digitally signed invoice.
B31: Thanks for doing business with Axestrack Software Solution Pvt. Ltd.

Sheet Appendix
D1: Appendix
B3: Alert | C3: Alert Description | D3: SLA
B4: L1 : High severity alerts with high probability of accident, they need immediate intervention
B5: Critical Fatigue Smart Alert | C5: 3 fatigue events in 15 mins at speeds over 50 km/h. Signs include yawning, drowsiness, frequent blinking, and head dropping | D5: 10 min
B6: Critical Distraction Smart Alert | C6: 3 distraction events in 15 mins at speeds over 50 km/h. Signs include looking away from road.
B7: Driver on phone smart alert | C7: Driver detected using a mobile phone above the speed threshold for a sustained duration, posing a high safety risk.
B8: Overspeed smart alert | C8: X speed alerts in Y time
B9: Screen Occlusion | C9: Screen occlusion detected, indicating the Camera’s view is partially or fully blocked deliberately by driver
B10: L2 : Low Severity alerts that may not directly result in an accident, but are important from safety perspective
B11: Driver Authentication | C11: Failed driver identity verification, indicating unauthorized or unverified driver activity. | D11: 30 min
B12: HA / HB / HC | C12: Sudden acceleration (HA), harsh braking (HB), or harsh cornering (HC), indicating aggressive driving behavior.
B13: Continuous Driving | C13: Driver exceeded the permissible continuous driving duration without adequate rest, posing fatigue risk.
B14: Night Drive | C14: Vehicle operated during restricted night hours.
B15: Seat Belt | C15: Driver detected without wearing a seat belt.
B16: Smoking | C16: Driver detected smoking while operating the vehicle, leading to safety concerns.
B17: L3 : Real time interventions for efficient performance and TAT management
B18: TAT monitoring (if Track & Trace module is subscribed) | C18: Halt monitoring, Restricted Areas, Night Drive, Daily Kilometers, Slow Moving Vehicle etc. | D18: -
B19: Detention Monitoring | C19: Source & Destination detention optimization
B20: ePOD validation (if ePOD module subscribed) | C20: Stakeholder coordination for ePOD
B22: Thanks for doing business with Axestrack Software Solution Pvt. Ltd.

Sheet Outcome Based
I1: =COUNTA(B4:B11) -> 8 | K1: =I1 -> 8 | M1: =K1 -> 8
A2: Stages | B2: Objectives | C2: Performance Indicator | D2: Measurement Criteria | E2: Target | F2: upto 80% | G2: 80-95% | H2: 95% and above | J2: Outcome-Based Pricing
I3: <90% = Basic Pricing | L3: 90% to 95% = Standard Pricing | N3: >95% = Premium Pricing
A4: Gate In | B4: Gate Digitalization | C4: Vehicle to be logged digitally at entry | D4: % of vehicle entering plant | E4: 0.9 | F4: 175000 | G4: 190000 | H4: 210000 | I4: =#REF!*#REF! -> #REF! | J4: =$I$4/#REF! -> #REF! | K4: =#REF!*#REF! -> #REF! | L4: =$K$4/#REF! -> #REF! | M4: =#REF!*#REF! -> #REF! | N4: =$M$4/#REF! -> #REF!
B5: Vehicle ULIP Verification (RC, Fitness, PUC) | C5: Vehicles with valid documents verified digitally | D5: % of vehicle registered on CPL | E5: 0.9 | J5: =$I$4/#REF! -> #REF! | L5: =$K$4/#REF! -> #REF! | N5: =$M$4/#REF! -> #REF!
B6: Reporting Timestamp | C6: Vehicles with recorded reporting time | D6: % of vehicle registered on CPL | E6: 0.9 | J6: =$I$4/#REF! -> #REF! | L6: =$K$4/#REF! -> #REF! | N6: =$M$4/#REF! -> #REF!
B7: Alert | C7: Alerts triggered for identified events | D7: % of eligible events | E7: 0.9 | J7: =$I$4/#REF! -> #REF! | L7: =$K$4/#REF! -> #REF! | N7: =$M$4/#REF! -> #REF!
A8: Security Check | B8: Vehicle Check | C8: Digital inspection through compliance checklist | D8: % of vehicle registered on CPL | E8: 0.9 | I8: =#REF!*#REF! -> #REF! | J8: =$I$8/#REF! -> #REF! | K8: =#REF!*#REF! -> #REF! | L8: =$K$8/#REF! -> #REF! | M8: =#REF!*#REF! -> #REF! | N8: =$M$8/#REF! -> #REF!
A9: Tare / Gross Weight | B9: Man less Weighbridge automation | C9: Vehicles processed through automated weighbridge | D9: % of vehicle registered on CPL | E9: 0.9 | I9: =#REF!*#REF! -> #REF! | J9: =$I$9/#REF! -> #REF! | K9: =#REF!*#REF! -> #REF! | L9: =$K$9/#REF! -> #REF! | M9: =#REF!*#REF! -> #REF! | N9: =$M$9/#REF! -> #REF!
A10: Loading/ Unloading | B10: IN-OUT Timestamp | C10: Vehicle to be logged digitally at loading/unloading docks | D10: % of vehicle registered on CPL | E10: 0.9 | I10: =#REF!*#REF! -> #REF! | J10: =$I$10/#REF! -> #REF! | K10: =#REF!*#REF! -> #REF! | L10: =$K$10/#REF! -> #REF! | M10: =#REF!*#REF! -> #REF! | N10: =$M$10/#REF! -> #REF!
A11: Gate Out | B11: Exit Timestamp | C11: Vehicles with recorded exit time | D11: % of vehicle registered on CPL | E11: 0.9 | I11: =#REF!*#REF! -> #REF! | J11: =$I$11/#REF! -> #REF! | K11: =#REF!*#REF! -> #REF! | L11: =$K$11/#REF! -> #REF! | M11: =#REF!*#REF! -> #REF! | N11: =$M$11/#REF! -> #REF!
A12: General | B12: Stagewise TAT | C12: Stagewise TAT for each vehicle | D12: % of vehicle registered on CPL | E12: 0.9
I13: =SUM(I4:I11) -> #REF! | J13: =SUM(J4:J11) -> #REF! | K13: =SUM(K4:K11) -> #REF! | L13: =SUM(L4:L11) -> #REF! | M13: =SUM(M4:M11) -> #REF! | N13: =SUM(N4:N11) -> #REF!

Sheet Quotation Year.wise (3 Years)
H1: Quotation
B2: Address - Corporate HQ : Axestrack Software Solutions Pvt. Ltd., Office No.-19, 6th Floor, Jaipur Electronic Market, Near Riddhi Siddhi, Gopalpura bypass, Jaipur - 302018 , Rajasthan, India
B3: GSTIN | D3: 08AACCH0299P1Z1 | F3: QUOTE # | H3: DATE
B4: MSME No | D4: UDYAM-RJ-17-0051921 | F4: ABC/XY/YYMM## | H4: =TODAY() -> 45863
B5: Contact Person
B6: Phone | F6: Quote Validity : 15 days from submitted date
B7: Email Id
B9: CUSTOMER INFO
B10: Company Name | D10: Mundra Solar Techno-Park Private Limited
B11: Address | D11: Village Tunda, Taluka Mundra, Kutch 370 435, Gujarat, India
B12: Contact Person | D12: Agam Balotra | F12: Phone | H12: +91 6357937439
B13: Email Id | D13: agam.balotra@adani.com
B15: DESCRIPTION OF WORK
B16: Digitization of MSTPL EMC’s traffic operations through the Connected Plant Logistics platform, bundled with supply, installation, and 3-year AMC of essential hardware.
B17: S.No. | C17: Year | E17: Items | G17: Type | I17: Amount
B18: 1 | C18: Implementation Cost (4 months) | E18: Platform Deployment + Integrations + Go-Live | G18: One time | I18: =ROUNDUP('Commercials (C) - 29> with Tab'!L20,0) -> #REF!
B19: 2 | C19: Hardware Cost | E19: Hardware for installation during project phase + Spares + Hardware AMC for 3 years | G19: One time | I19: =ROUNDUP('Commercials (C) - 29> with Tab'!L17+'Commercials (C) - 29> with Tab'!L29,0) -> #REF!
B20: 3 | C20: SaaS Subription fee (Post Go-Live) | E20: Software Fee + Support & Maintenance | G20: Per Trip | I20: 8
B21: 4 | C21: Support Manpower (Post Go-Live) | E21: Post Go-Live Project support team | G21: Per Month | I21: =ROUNDUP('Commercials (C) - 29> with Tab'!K24/12,0) -> #REF!
B23: Please refer to the next page for Terms and Conditions & Notes
B25: Terms & Conditions
B26: • All the prices mentioned in proposal are in rupees and exclusive of GST. Taxes as applicable • Device ownership remains with Client • Above estimation is based on received details; any formal change or upgrade in hardware specifications or product features (beyond those installed during onboarding) will incur additional charges. • The standard one-year hardware warranty period, as per OEM guidelines, will commence from the date of hardware delivery.(Burned / Physical Damaged hardware will not be part of AMC) - Kindly refer to Hardware warranty T&C attached. • Minimum Contract period will be for 3 Years Payment Terms: • Payment will be on milestone basis • Milestone 1: 100% of Hardware cost with PO. • Milestone 2: 100% of implementation cost at the time of project kick-off. • A minimum monthly advance subscription fee of ₹1,00,000 (Rupees One Lakh only) shall apply, covering up to 12,500 trips per month, inclusive of both goods transportation and passenger vehicle movements. In the event that the number of trips in any given month exceeds 12,500, a charge of ₹8 per trip shall be applicable on the total number of trips for that month. • 100% payments to be made within 15 days from the date of receipt of original or digitally signed invoice. In case of delay, overdue charges of 1.5% per month will be charged.
B27: Project Exclusions
B28: • The solution exclusively applies to 40-ft container trucks; smaller trucks are not included at Loading & Unloading dock • Weighbridge process automation • ERP/third-party product performance optimization • Data cleansing and extraction from source systems • Bug fixes or issues related to third-party services or plugins • Customizations related to third-party products or platforms • Civil works, including trenching, mounting poles, power provisioning, LAN setup, and enclosures • Hardware setup or commissioning if dependent on non-Axestrack devices • Coordination with third-party vendors or agents for non-Axestrack platforms or integrations
B29: Thanks for doing business with Axestrack Software Solution Pvt. Ltd.

Sheet Quote Nomeclature
B2: Quote no Format
B3: ABC/XY/YYMM##
B5: ABC | C5: Client name short Form like Hindalco Industries Limited will be HIL
B6: XY | C6: Axestrack Sales SPOC Intials
B7: YY | C7: Year
B8: MM | C8: Month
B9: ## | C9: Quote send by Sales SPOC in that particular month, quote nos. should be start from 11

Sheet Commercials (C) - Full
B2: Customer | D2: MSTPL
B3: Date | D3: =TODAY() -> 45863
B4: Contract Year | D4: 5 | F4: Full solution befoere 29th discussion
B5: AMC Cost | D5: 0.2
B6: Hardware Transportation Cost | D6: 0.03
B7: ERP Integration Cost | D7: 0
B8: Software Subscription Cost/month | D8: 190000
I9: change in formula | K9: change in formula
B10: Model | C10: Items | E10: Details | F10: Type | G10: Unit Cost | H10: Nos. of years | I10: Landed Cost to Axestrack for 5 Years | J10: Margin | K10: Unit price on Margin | L10: Cost for Customer for 3 Years | M10: Project Margin
B11: One Time Cost | C11: Hardware Cost | D11: Hardware BOQ Cost | E11: Hardware - BOQ | F11: One Time | I11: =#REF! -> #REF! | J11: 0.2307692 | K11: =IF(H11=0,(I11/(1-J11)),(I11/H11)/(1-J11)) -> #REF! | L11: =I11/(1-J11) -> #REF! | M11: =L11*J11 -> #REF!
E12: Hardware Transportation Cost | F12: One Time | I12: =I11*D6 -> #REF! | J12: 0.040225 | K12: =IF(H12=0,(I12/(1-J12)),(I12/H12)/(1-J12)) -> #REF! | L12: =I12/(1-J12) -> #REF! | M12: =L12*J12 -> #REF!
E13: Hardware BOQ Cost | I13: =SUM(I11:I12) -> #REF! | K13: =SUM(K11:K12) -> #REF! | L13: =SUM(L11:L12) -> #REF!
D14: Spares BOQ Cost (Optional) | E14: Spares - BOQ | F14: One Time | I14: =#REF! -> #REF! | J14: 0 | K14: =IF(H14=0,(I14/(1-J14)),(I14/H14)/(1-J14)) -> #REF! | L14: =I14/(1-J14) -> #REF! | M14: =L14*J14 -> #REF!
E15: Spares Transportation Cost | F15: One Time | I15: 0 | J15: 0 | K15: =IF(H15=0,(I15/(1-J15)),(I15/H15)/(1-J15)) -> 0 | L15: =I15/(1-J15) -> 0 | M15: =L15*J15 -> 0
E16: Spares BOQ Cost | I16: =SUM(I14:I15) -> #REF! | K16: =SUM(K14:K15) -> #REF! | L16: =SUM(L14:L15) -> #REF!
D17: Total Hardware Cost | I17: =I13+I16 -> #REF! | K17: =K13+K16 -> #REF! | L17: =L13+L16 -> #REF!
C18: Implementation Cost | D18: Installation, Training & Configuration | E18: One Time Installation + Third Party | F18: One Time | I18: =#REF!+#REF! -> #REF! | J18: 0.035625 | K18: =IF(H18=0,(I18/(1-J18)),(I18/H18)/(1-J18)) -> #REF! | L18: =I18/(1-J18) -> #REF! | M18: =L18*J18 -> #REF!
D19: ERP Integration | E19: ERP Integration | F19: One Time | I19: =D7 -> 0 | J19: 0 | K19: =IF(H19=0,(I19/(1-J19)),(I19/H19)/(1-J19)) -> 0 | L19: =I19/(1-J19) -> 0 | M19: =L19*J19 -> 0
D20: Total Installation, Setup & API Development Cost | I20: =SUM(I18:I19) -> #REF! | K20: =SUM(K18:K19) -> #REF! | L20: =SUM(L18:L19) -> #REF!
C21: One Time Cost | I21: =I17+I20 -> #REF! | K21: =K17+K20 -> #REF! | L21: =L17+L20 -> #REF!
C22: Annual Subscription fee | D22: Onsite Manpower, Project Management, Support & Maintenance | E22: Project Manpower Cost | F22: Per Year | G22: =#REF! -> #REF! | H22: =D4 -> 5 | I22: =G22*H22 -> #REF! | J22: 0.0125 | K22: =IF(H22=0,(I22/(1-J22)),(I22/H22)/(1-J22)*H22/$D$4) -> #REF! | L22: =I22/(1-J22) -> #REF! | M22: =L22*J22 -> #REF!
E23: Lodging & Travel Cost | F23: Per Year | G23: =#REF! -> #REF! | H23: =D4 -> 5 | I23: =G23*H23 -> #REF! | J23: 0.0125 | K23: =IF(H23=0,(I23/(1-J23)),(I23/H23)/(1-J23)*H23/$D$4) -> #REF! | L23: =I23/(1-J23) -> #REF! | M23: =L23*J23 -> #REF!
D24: Project Management Cost | I24: =SUM(I22:I23) -> #REF! | K24: =SUM(K22:K23) -> #REF! | L24: =SUM(L22:L23) -> #REF!
D25: Platform Subscription Fee | E25: Platform Subscription Fee | F25: Per Year | G25: =D8*12 -> 2280000 | H25: =D4 -> 5 | I25: =G25*H25 -> 11400000 | J25: 0 | K25: =IF(H25=0,(I25/(1-J25)),(I25/H25)/(1-J25)) -> 2280000 | L25: =I25/(1-J25) -> 11400000 | M25: =L25*0.5 -> 5700000 | N25: 0.5
D26: Platform Fee | I26: =SUM(I25) -> 11400000 | K26: =SUM(K25) -> 2280000 | L26: =SUM(L25) -> 11400000
C27: Subscription Fee | I27: =I24+I26 -> #REF! | K27: =K24+K26 -> #REF! | L27: =L24+L26 -> #REF!
B28: AMC | C28: AMC | D28: Hardware AMC | E28: Hardware AMC from 2nd Year onwards | F28: Per Year | G28: =(I11+I14)*D5 -> #REF! | H28: =('AMC & months'!C6-'AMC & months'!C7)/12 -> 4.0833333 | I28: =_xlfn.IFNA(G28*H28,0) -> #REF! | J28: 0.2 | K28: =IF(H28=0,(I28/(1-J28)),(I28/H28)/(1-J28)*H28/($D$4-1)) -> #REF! | L28: =I28/(1-J28) -> #REF! | M28: =L28*J28 -> #REF!
C29: AMC | I29: =SUM(I28:I28) -> #REF! | K29: =SUM(K28:K28) -> #REF! | L29: =SUM(L28:L28) -> #REF!
B30: Total Cost of the Project Implementation & Support + AMC | I30: =I21+I27+I29 -> #REF! | L30: =L21+L27+L29 -> #REF! | M30: =SUM(M11:M29) -> #REF!
M31: =M30/L30 -> #REF!
D33: Hardware | E33: Transportation | F33: Spares | G33: One Time Installation + Third Party | H33: ERP | I33: Manpower Post Go-live | J33: SaaS Fee | K33: Hardware AMC | L33: Total
C34: Implementation | D34: =L11 -> #REF! | E34: =L12 -> #REF! | F34: =L14 -> #REF! | G34: =L18 -> #REF! | H34: =L19 -> 0 | L34: =SUM(D34:K34) -> #REF! | M34: =L34=L21 -> #REF!
C35: Year 1 (Post Go-live) | I35: =$K$22+$K$23 -> #REF! | J35: =$K$25 -> 2280000 | L35: =SUM(D35:K35) -> #REF! | M35: =L35=K27 -> #REF!
C36: Year 2 | I36: =$K$22+$K$23 -> #REF! | J36: =$K$25 -> 2280000 | K36: =$K$28 -> #REF! | L36: =SUM(D36:K36) -> #REF! | M36: =L36=K27+K29 -> #REF!
C37: Year 3 | I37: =$K$22+$K$23 -> #REF! | J37: =$K$25 -> 2280000 | K37: =$K$28 -> #REF! | L37: =SUM(D37:K37) -> #REF!
C38: Year 4 | I38: =$K$22+$K$23 -> #REF! | J38: =$K$25 -> 2280000 | K38: =$K$28 -> #REF! | L38: =SUM(D38:K38) -> #REF!
C39: Year 5 | I39: =$K$22+$K$23 -> #REF! | J39: =$K$25 -> 2280000 | K39: =$K$28 -> #REF! | L39: =SUM(D39:K39) -> #REF! | M39: =L39=K27+K29 -> #REF!
D40: =SUM(D34:D39) -> #REF! | E40: =SUM(E34:E39) -> #REF! | F40: =SUM(F34:F39) -> #REF! | G40: =SUM(G34:G39) -> #REF! | H40: =SUM(H34:H39) -> 0 | I40: =SUM(I34:I39) -> #REF! | J40: =SUM(J34:J39) -> 11400000 | K40: =SUM(K34:K39) -> #REF! | L40: =SUM(L34:L39) -> #REF! | M40: =L40=L30 -> #REF!
D41: =D40=L11 -> #REF! | E41: =E40=L12 -> #REF! | F41: =F40=L14 -> #REF! | G41: =G40=L18 -> #REF! | H41: =H40=L19 -> TRUE | I41: =I40=L24 -> #REF! | J41: =J40=L26 -> TRUE | K41: =K40=L29 -> #REF! | L41: =L40 -> #REF!

Sheet Commercials (C) - 29> with Tab
B2: Customer | D2: MSTPL
B3: Date | D3: =TODAY() -> 45863
B4: Contract Year | D4: 5 | F4: After 29th June 2024 Discussion - With Tablet
B5: AMC Cost | D5: 0.2
B6: Hardware Transportation Cost | D6: 0.03
B7: ERP Integration Cost | D7: 0
B8: Software Subscription Cost/month | D8: 190000
I9: change in formula | K9: change in formula
B10: Model | C10: Items | E10: Details | F10: Type | G10: Unit Cost | H10: Nos. of years | I10: Landed Cost to Axestrack for 5 Years | J10: Margin | K10: Unit price on Margin | L10: Cost for Customer for 3 Years | M10: Project Margin
B11: One Time Cost | C11: Hardware Cost | D11: Hardware BOQ Cost | E11: Hardware - BOQ | F11: One Time | I11: =#REF! -> #REF! | J11: 0.2307692 | K11: =IF(H11=0,(I11/(1-J11)),(I11/H11)/(1-J11)) -> #REF! | L11: =I11/(1-J11) -> #REF! | M11: =L11*J11 -> #REF!
E12: Hardware Transportation Cost | F12: One Time | I12: =I11*D6 -> #REF! | J12: 0.40189 | K12: =IF(H12=0,(I12/(1-J12)),(I12/H12)/(1-J12)) -> #REF! | L12: =I12/(1-J12) -> #REF! | M12: =L12*J12 -> #REF!
E13: Hardware BOQ Cost | I13: =SUM(I11:I12) -> #REF! | K13: =SUM(K11:K12) -> #REF! | L13: =SUM(L11:L12) -> #REF!
D14: Spares BOQ Cost (Optional) | E14: Spares - BOQ | F14: One Time | I14: =#REF! -> #REF! | J14: 0 | K14: =IF(H14=0,(I14/(1-J14)),(I14/H14)/(1-J14)) -> #REF! | L14: =I14/(1-J14) -> #REF! | M14: =L14*J14 -> #REF!
E15: Spares Transportation Cost | F15: One Time | I15: 0 | J15: 0 | K15: =IF(H15=0,(I15/(1-J15)),(I15/H15)/(1-J15)) -> 0 | L15: =I15/(1-J15) -> 0 | M15: =L15*J15 -> 0
E16: Spares BOQ Cost | I16: =SUM(I14:I15) -> #REF! | K16: =SUM(K14:K15) -> #REF! | L16: =SUM(L14:L15) -> #REF!
D17: Total Hardware Cost | I17: =I13+I16 -> #REF! | K17: =K13+K16 -> #REF! | L17: =L13+L16 -> #REF!
C18: Implementation Cost | D18: Installation, Training & Configuration | E18: One Time Installation + Third Party | F18: One Time | I18: =#REF!+#REF! -> #REF! | J18: 0.035625 | K18: =IF(H18=0,(I18/(1-J18)),(I18/H18)/(1-J18)) -> #REF! | L18: =I18/(1-J18) -> #REF! | M18: =L18*J18 -> #REF!
D19: ERP Integration | E19: ERP Integration | F19: One Time | I19: =D7 -> 0 | J19: 0 | K19: =IF(H19=0,(I19/(1-J19)),(I19/H19)/(1-J19)) -> 0 | L19: =I19/(1-J19) -> 0 | M19: =L19*J19 -> 0
D20: Total Installation, Setup & API Development Cost | I20: =SUM(I18:I19) -> #REF! | K20: =SUM(K18:K19) -> #REF! | L20: =SUM(L18:L19) -> #REF!
C21: One Time Cost | I21: =I17+I20 -> #REF! | K21: =K17+K20 -> #REF! | L21: =L17+L20 -> #REF!
C22: Annual Subscription fee | D22: Onsite Manpower, Project Management, Support & Maintenance | E22: Project Manpower Cost | F22: Per Year | G22: =#REF! -> #REF! | H22: =D4 -> 5 | I22: =G22*H22 -> #REF! | J22: 0.0125 | K22: =IF(H22=0,(I22/(1-J22)),(I22/H22)/(1-J22)*H22/$D$4) -> #REF! | L22: =I22/(1-J22) -> #REF! | M22: =L22*J22 -> #REF!
E23: Lodging & Travel Cost | F23: Per Year | G23: =#REF! -> #REF! | H23: =D4 -> 5 | I23: =G23*H23 -> #REF! | J23: 0.0125 | K23: =IF(H23=0,(I23/(1-J23)),(I23/H23)/(1-J23)*H23/$D$4) -> #REF! | L23: =I23/(1-J23) -> #REF! | M23: =L23*J23 -> #REF!
D24: Project Management Cost | I24: =SUM(I22:I23) -> #REF! | K24: =SUM(K22:K23) -> #REF! | L24: =SUM(L22:L23) -> #REF!
D25: Platform Subscription Fee | E25: Platform Subscription Fee | F25: Per Year | G25: =D8*12 -> 2280000 | H25: =D4 -> 5 | I25: =G25*H25 -> 11400000 | J25: 0 | K25: =IF(H25=0,(I25/(1-J25)),(I25/H25)/(1-J25)) -> 2280000 | L25: =I25/(1-J25) -> 11400000 | M25: =L25*0.5 -> 5700000 | N25: 0.5
D26: Platform Fee | I26: =SUM(I25) -> 11400000 | K26: =SUM(K25) -> 2280000 | L26: =SUM(L25) -> 11400000
C27: Subscription Fee | I27: =I24+I26 -> #REF! | K27: =K24+K26 -> #REF! | L27: =L24+L26 -> #REF!
B28: AMC | C28: AMC | D28: Hardware AMC | E28: Hardware AMC from 2nd Year onwards | F28: Per Year | G28: =(I11+I14)*D5 -> #REF! | H28: =('AMC & months'!C6-'AMC & months'!C7)/12 -> 4.0833333 | I28: =_xlfn.IFNA(G28*H28,0) -> #REF! | J28: 0.2 | K28: =IF(H28=0,(I28/(1-J28)),(I28/H28)/(1-J28)*H28/($D$4-1)) -> #REF! | L28: =I28/(1-J28) -> #REF! | M28: =L28*J28 -> #REF!
C29: AMC | I29: =SUM(I28:I28) -> #REF! | K29: =SUM(K28:K28) -> #REF! | L29: =SUM(L28:L28) -> #REF!
B30: Total Cost of the Project Implementation & Support + AMC | I30: =I21+I27+I29 -> #REF! | L30: =L21+L27+L29 -> #REF! | M30: =SUM(M11:M29) -> #REF!
M31: =M30/L30 -> #REF!
D33: Hardware | E33: Transportation | F33: Spares | G33: One Time Installation + Third Party | H33: ERP | I33: Manpower Post Go-live | J33: SaaS Fee | K33: Hardware AMC | L33: Total
C34: Implementation | D34: =L11 -> #REF! | E34: =L12 -> #REF! | F34: =L14 -> #REF! | G34: =L18 -> #REF! | H34: =L19 -> 0 | L34: =SUM(D34:K34) -> #REF! | M34: =L34=L21 -> #REF!
C35: Year 1 (Post Go-live) | I35: =$K$22+$K$23 -> #REF! | J35: =$K$25 -> 2280000 | L35: =SUM(D35:K35) -> #REF! | M35: =L35=K27 -> #REF!
C36: Year 2 | I36: =$K$22+$K$23 -> #REF! | J36: =$K$25 -> 2280000 | K36: =$K$28 -> #REF! | L36: =SUM(D36:K36) -> #REF! | M36: =L36=K27+K29 -> #REF!
C37: Year 3 | I37: =$K$22+$K$23 -> #REF! | J37: =$K$25 -> 2280000 | K37: =$K$28 -> #REF! | L37: =SUM(D37:K37) -> #REF!
C38: Year 4 | I38: =$K$22+$K$23 -> #REF! | J38: =$K$25 -> 2280000 | K38: =$K$28 -> #REF! | L38: =SUM(D38:K38) -> #REF!
C39: Year 5 | I39: =$K$22+$K$23 -> #REF! | J39: =$K$25 -> 2280000 | K39: =$K$28 -> #REF! | L39: =SUM(D39:K39) -> #REF! | M39: =L39=K27+K29 -> #REF!
D40: =SUM(D34:D39) -> #REF! | E40: =SUM(E34:E39) -> #REF! | F40: =SUM(F34:F39) -> #REF! | G40: =SUM(G34:G39) -> #REF! | H40: =SUM(H34:H39) -> 0 | I40: =SUM(I34:I39) -> #REF! | J40: =SUM(J34:J39) -> 11400000 | K40: =SUM(K34:K39) -> #REF! | L40: =SUM(L34:L39) -> #REF! | M40: =L40=L30 -> #REF!
D41: =D40=L11 -> #REF! | E41: =E40=L12 -> #REF! | F41: =F40=L14 -> #REF! | G41: =G40=L18 -> #REF! | H41: =H40=L19 -> TRUE | I41: =I40=L24 -> #REF! | J41: =J40=L26 -> TRUE | K41: =K40=L29 -> #REF! | L41: =L40 -> #REF!

Sheet Slab wise
D1: Type | E1: Landing Price | F1: Cost for Customer
A2: One Time Cost | B2: Hardware Cost | C2: Total Hardware Cost including Transportation | D2: One Time | E2: ='Commercials (C) - 29> with Tab'!I17 -> #REF! | F2: ='Commercials (C) - 29> with Tab'!K17 -> #REF!
B3: Implementation Cost | C3: Installation, Training & Configuration Cost | D3: One Time | E3: ='Commercials (C) - 29> with Tab'!I18 -> #REF! | F3: ='Commercials (C) - 29> with Tab'!L18 -> #REF!
C4: ERP Integration | D4: One Time | E4: ='Commercials (C) - 29> with Tab'!I19 -> 0 | F4: ='Commercials (C) - 29> with Tab'!L19 -> 0
B5: TOTAL ONE TIME COST | E5: =SUM(E2:E4) -> #REF! | F5: =SUM(F2:F4) -> #REF!
A6: AMC | B6: AMC | C6: AMC from 2nd Year Onwards | D6: Per Year | E6: ='Commercials (C) - 29> with Tab'!G28 -> #REF! | F6: ='Commercials (C) - 29> with Tab'!K28 -> #REF!
B7: AMC | E7: =E6 -> #REF! | F7: =F6 -> #REF!
A9: Annual Subscription fee | B9: Subscription fee | C9: PMO Cost | D9: Per Year | E9: ='Commercials (C) - 29> with Tab'!G23 -> #REF! | F9: ='Commercials (C) - 29> with Tab'!K23 -> #REF!
C10: Platform Fee | D10: Per Year | E10: ='Commercials (C) - 29> with Tab'!G25 -> 2280000 | F10: ='Commercials (C) - 29> with Tab'!K25 -> 2280000
B11: SUBSCRIPTION FEE | E11: =SUM(E9:E10) -> #REF! | F11: =SUM(F9:F10) -> #REF!
A13: Year Wise Cost | C13: One Time Cost | D13: Saas Fee + PMO | E13: Hardware AMC | F13: Total
B14: Year - 1 | C14: =F5 -> #REF! | D14: =F11 -> #REF! | F14: =SUM(C14:E14) -> #REF! | G14: =F14/F17 -> #REF!
B15: Year - 2 | D15: =F11 -> #REF! | E15: =F7 -> #REF! | F15: =SUM(C15:E15) -> #REF! | G15: =F15/F17 -> #REF!
B16: Year - 3 | D16: =F11 -> #REF! | E16: =F7 -> #REF! | F16: =SUM(C16:E16) -> #REF! | G16: =F16/F17 -> #REF!
C17: =SUM(C14:C16) -> #REF! | D17: =SUM(D14:D16) -> #REF! | E17: =SUM(E14:E16) -> #REF! | F17: =SUM(F14:F16) -> #REF!
A19: Slab Wise Pricing per Trip | B19: Trips per month | C19: Count for Cal. | D19: Price Per trip | E19: Per month price | F19: The per trip price is calculated on the Total Subscription fee only.
B20: Upto 1000 | C20: 1000 | D20: =$F$11/12/C20 -> #REF! | E20: =C20*D20 -> #REF!
B21: 1001 to 1250 | C21: 1250 | E21: =$D$20*C21 -> #REF!
B22: 1251 to 1500 | C22: 1500 | E22: =$D$20*C22 -> #REF!
B23: 1501 to 1750 | C23: 1750 | E23: =$D$20*C23 -> #REF!
B24: More than 1750 | C24: 2000 | E24: =$D$20*C24 -> #REF!

Sheet Sheet1
B3: type of heads | C3: Headers
B4: hardware | C4: Rfid reader | D4: Handheld | E4: tags
B5: Transportation cost
B6: Spares
B7: Spares Trasnporation cost
B8: Impl. Cots | C8: Installation, Training & Configuration | D8: ERP Integration
B9: Annual Subscription fee | C9: Onsite Manpower | D9: PMO Cost | E9: Platform Subscription Fee
B10: AMC | C10: AMC from 2nd year

Sheet AMC & months
A1: 3 Years
C2: Months
B3: Implementation Period | C3: 2
B4: Hypercare Period | C4: 1
B5: Hardware Delivery Month | C5: 1
B6: Project Period | C6: ='Commercials (C) - 29> with Tab'!D4*12+C3 -> 62
B7: OEM Warranty Till | C7: =C5+12 -> 13
A8: AMC 1 | B8: AMC 2nd Year till | C8: =C7+12 -> 25
A9: AMC 2 | B9: AMC 3rd Year till | C9: =C8+12 -> 37
A10: AMC 3 | B10: AMC 4th Year till | C10: =C9+12 -> 49
A11: AMC 4 | B11: AMC 5th Year till | C11: =C10+12 -> 61
B12: Remaining month | C12: =C6-C11 -> 1
A14: Manpower Month post implementation
C15: Months
B16: Implementation Period | C16: =C3 -> 2
B17: Hypercare Period | C17: =C4 -> 1
B18: Project Period | C18: =C6 -> 62
A19: Manpower 1 | B19: 1st year | C19: 0
A20: Manpower 2 | B20: 2nd year | C20: 0
A21: Manpower 3 | B21: 3rd year | C21: 0
B23: Manpower Period post hypercare | C23: 0

Sheet Sheet4
C1: After 29th June 2024 Discussion - Without Tablet
B2: Hardware Stage wise

Sheet Sheet2
A1: Stage | B1: OLD - 29 | C1: New | D1: OLD (No tablet)
B2: 236600 | D2: 236600
B3: 486200 | D3: 364000
B4: 807300 | D4: 807300
B5: 353600 | D5: 231400
B6: 1222000 | D6: 702000
B7: 1007500
B9: =SUM(B2:B7) -> 4113200 | D9: =SUM(D2:D7) -> 2341300
A11: Transportation | B11: 158700 | D11: 158700
B12: =B11/B9 -> 0.038583098 | D12: =D11/D9 -> 0.067782856
